Workbook

Sheet Inputs
A1: VYNDI 36-Month Fund & Materials Projection
A2: Editable planning workbook · approved-plan baseline · ₹ lakh unless stated
A4: Approved plan input | B4: Value | D4: Model | E4: Mix | F4: ASP ₹L | G4: Launch month
A5: Horizon start | B5: 46266 | D5: Longitude | E5: 0.2 | F5: 1.25 | G5: 14
A6: Commercial launch month | B6: 14 | D6: Latitude | E6: 0.6 | F6: 2.25 | G6: 14
A7: Altitude launch month | B7: 16 | D7: Altitude | E7: 0.2 | F7: 3.5 | G7: 16
A8: Demand multiplier | B8: 1 | D8: Total | E8: =SUM(E5:E7)
A9: Material buffer | B9: 0.15
A10: Cash collection assumption | B10: 0.8
A11: Opening cash (₹L) | B11: 1
A12: Cash floor (₹L) | B12: 15
A14: Gate | B14: Month | C14: Core ₹L | D14: Optional? | E14: Purpose
A15: T1 | B15: 1 | C15: 15 | D15: No | E15: Foundation
A16: T2 | B16: 3 | C16: 35 | D16: No | E16: Engineering
A17: T3 | B17: 6 | C17: 35 | D17: No | E17: Validation
A18: STBY | B18: 9 | C18: 25 | D18: Yes | E18: Contingent cash-gap cover
A19: T4 | B19: 10 | C19: 50 | D19: No | E19: Tooling / pilot
A20: T5 | B20: 14 | C20: 65 | D20: No | E20: Launch working capital
A21: Core total | C21: =SUM(C15:C17,C19:C20)
A24: Material / component | B24: Unit | C24: Per Longitude | D24: Per Latitude | E24: Per Altitude | F24: Unit cost ₹ | G24: Basis
A25: Aluminium/OEM frameset | B25: set | C25: 1 | D25: 0 | E25: 0 | F25: 45000 | G25: Planning assumption
A26: T700 prepreg | B26: kg | C26: 0 | D26: 3.2 | E26: 2.5 | F26: 3500 | G26: Editable; release against approved ply book
A27: T800 prepreg | B27: kg | C27: 0 | D27: 1.3 | E27: 2.2 | F27: 6500 | G27: Editable; release against approved ply book
A28: Resin & bonding system | B28: kg | C28: 0 | D28: 0.8 | E28: 0.9 | F28: 1800 | G28: Editable manufacturing assumption
A29: Paint & clear coat | B29: L | C29: 0.35 | D29: 0.35 | E29: 0.35 | F29: 2200 | G29: Editable manufacturing assumption
A30: Groupset | B30: set | C30: 1 | D30: 1 | E30: 1 | F30: 65000 | G30: Exact variant BOM controls selection
A31: Wheelset | B31: set | C31: 1 | D31: 1 | E31: 1 | F31: 35000 | G31: Exact variant BOM controls selection
A32: Tyres | B32: ea | C32: 2 | D32: 2 | E32: 2 | F32: 3500 | G32: Two per bicycle
A33: Cockpit | B33: set | C33: 1 | D33: 1 | E33: 1 | F33: 12000 | G33: Stem/bar or integrated option
A34: Saddle | B34: ea | C34: 1 | D34: 1 | E34: 1 | F34: 4500 | G34: Variant option
A35: Brake system | B35: set | C35: 1 | D35: 1 | E35: 1 | F35: 18000 | G35: Variant option
A36: Packaging kit | B36: kit | C36: 1 | D36: 1 | E36: 1 | F36: 2500 | G36: Shipment-ready packaging
A37: Note | C37: Blue cells are editable assumptions. Quantities are planning estimates, not released purchase orders.
A40: Ramp index | B40: Total bicycles | D40: Capex month | E40: ₹L | F40: Source | G40: Note
A41: 1 | B41: 3 | D41: 3 | E41: 4 | F41: finance/model.ts | G41: CAD/engineering
A42: 2 | B42: 3 | D42: 5 | E42: 8 | F42: finance/model.ts | G42: Development
A43: 3 | B43: 4 | D43: 6 | E43: 6 | F43: finance/model.ts | G43: Validation
A44: 4 | B44: 4 | D44: 7 | E44: 5.5 | F44: finance/model.ts | G44: Pilot preparation
A45: 5 | B45: 5 | D45: 8 | E45: 10 | F45: finance/model.ts | G45: Pre-tooling
A46: 6 | B46: 5 | D46: 10 | E46: 28 | F46: finance/model.ts | G46: Tooling
A47: 7 | B47: 6
A48: 8 | B48: 6
A49: 9 | B49: 8 | D49: Workbook source | E49: Repository path / URL | F49: Status | G49: Use
A50: 10 | B50: 8 | D50: Approved operating plan | E50: https://github.com/shyamsundhar1982/tiger-field-flora-finch/blob/c8bfd35f38970948dec86f8e41be046ecaa5da55/src/lib/planning/operating-plan.ts | F50: Source baseline | G50: Start, launch and demand ramp
A51: 11 | B51: 10 | D51: Finance model | E51: https://github.com/shyamsundhar1982/tiger-field-flora-finch/blob/c8bfd35f38970948dec86f8e41be046ecaa5da55/src/lib/finance/model.ts | F51: Source baseline | G51: Mix, opex, capex and funding timing
A52: 12 | B52: 10 | D52: Funding tranches | E52: https://github.com/shyamsundhar1982/tiger-field-flora-finch/blob/c8bfd35f38970948dec86f8e41be046ecaa5da55/src/lib/data/company.ts | F52: Source baseline | G52: ₹2 Cr core staged funding
A53: 13 | B53: 12 | D53: Material quantities | E53: This workbook Inputs!A24:G36 | F53: Editable assumption | G53: Replace with approved variant BOM/ply-book quantities
A54: 14 | B54: 12 | D54: Opening inventory | E54: Zero | F54: Business instruction | G54: Requirements shown gross; no stock netting
A55: 15 | B55: 14 | D55: Accounting caution | E55: Planned revenue × collection assumption | F55: Forecast only | G55: Not recognized revenue or actual collection
A56: 16 | B56: 14
A57: 17 | B57: 16
A58: 18 | B58: 16
A59: 19 | B59: 18
A60: 20 | B60: 18
A61: 21 | B61: 20
A62: 22 | B62: 20
A63: 23 | B63: 22
A64: 24 | B64: 22
A67: Key output | B67: Formula / result | C67: Interpretation
A68: Core staged funding | B68: =ROUND(SUM('Monthly Funding'!I6:I41),2) | C68: Excludes optional standby
A69: Optional standby | B69: =ROUND(SUM('Monthly Funding'!J6:J41),2) | C69: Included in monthly cash projection
A70: Additional funding gap | B70: =ROUND(SUM('Monthly Funding'!M6:M41),2) | C70: Extra cash needed to preserve approved floor

Sheet Monthly Funding
A1: Monthly Fund Requirement
A2: Core funding tranches + optional standby + formula-derived additional funding to preserve cash floor
A5: Month | B5: Date | C5: Units | D5: Opex ₹L | E5: Capex ₹L | F5: Net Procurement Cash ₹L | G5: Planned revenue ₹L | H5: Assumed cash inflow ₹L | I5: Core funding ₹L | J5: Standby ₹L | K5: Opening cash ₹L | L5: Pre-extra cash ₹L | M5: Additional fund required ₹L | N5: Closing cash ₹L
A6: 1 | B6: 46266 | C6: ='Monthly Materials'!C6 | D6: =IF(A6<=Inputs!$B$6-11,2.8,IF(A6<=Inputs!$B$6-6,4.2,IF(A6<=Inputs!$B$6-3,6,IF(A6<=Inputs!$B$6,7.8,9.2)))) | E6: =SUMIF(Inputs!$D$41:$D$46,A6,Inputs!$E$41:$E$46) | F6: =ROUND(INDEX('MRP Cash Bridge'!$J$4:$J$39,A6)/100000,2) | G6: =ROUND('Monthly Materials'!D6*Inputs!$F$5+'Monthly Materials'!E6*Inputs!$F$6+'Monthly Materials'!F6*Inputs!$F$7,2) | H6: =ROUND(G6*Inputs!$B$10,2) | I6: =SUMIFS(Inputs!$C$15:$C$20,Inputs!$B$15:$B$20,A6,Inputs!$D$15:$D$20,"No") | J6: =SUMIFS(Inputs!$C$15:$C$20,Inputs!$B$15:$B$20,A6,Inputs!$D$15:$D$20,"Yes") | K6: =Inputs!$B$11 | L6: =ROUND(K6+H6+I6+J6-D6-E6-F6,2) | M6: =ROUND(MAX(0,Inputs!$B$12-L6),2) | N6: =ROUND(L6+M6,2)
A7: 2 | B7: 46296 | C7: ='Monthly Materials'!C7 | D7: =IF(A7<=Inputs!$B$6-11,2.8,IF(A7<=Inputs!$B$6-6,4.2,IF(A7<=Inputs!$B$6-3,6,IF(A7<=Inputs!$B$6,7.8,9.2)))) | E7: =SUMIF(Inputs!$D$41:$D$46,A7,Inputs!$E$41:$E$46) | F7: =ROUND(INDEX('MRP Cash Bridge'!$J$4:$J$39,A7)/100000,2) | G7: =ROUND('Monthly Materials'!D7*Inputs!$F$5+'Monthly Materials'!E7*Inputs!$F$6+'Monthly Materials'!F7*Inputs!$F$7,2) | H7: =ROUND(G7*Inputs!$B$10,2) | I7: =SUMIFS(Inputs!$C$15:$C$20,Inputs!$B$15:$B$20,A7,Inputs!$D$15:$D$20,"No") | J7: =SUMIFS(Inputs!$C$15:$C$20,Inputs!$B$15:$B$20,A7,Inputs!$D$15:$D$20,"Yes") | K7: =N6 | L7: =ROUND(K7+H7+I7+J7-D7-E7-F7,2) | M7: =ROUND(MAX(0,Inputs!$B$12-L7),2) | N7: =ROUND(L7+M7,2)
A8: 3 | B8: 46327 | C8: ='Monthly Materials'!C8 | D8: =IF(A8<=Inputs!$B$6-11,2.8,IF(A8<=Inputs!$B$6-6,4.2,IF(A8<=Inputs!$B$6-3,6,IF(A8<=Inputs!$B$6,7.8,9.2)))) | E8: =SUMIF(Inputs!$D$41:$D$46,A8,Inputs!$E$41:$E$46) | F8: =ROUND(INDEX('MRP Cash Bridge'!$J$4:$J$39,A8)/100000,2) | G8: =ROUND('Monthly Materials'!D8*Inputs!$F$5+'Monthly Materials'!E8*Inputs!$F$6+'Monthly Materials'!F8*Inputs!$F$7,2) | H8: =ROUND(G8*Inputs!$B$10,2) | I8: =SUMIFS(Inputs!$C$15:$C$20,Inputs!$B$15:$B$20,A8,Inputs!$D$15:$D$20,"No") | J8: =SUMIFS(Inputs!$C$15:$C$20,Inputs!$B$15:$B$20,A8,Inputs!$D$15:$D$20,"Yes") | K8: =N7 | L8: =ROUND(K8+H8+I8+J8-D8-E8-F8,2) | M8: =ROUND(MAX(0,Inputs!$B$12-L8),2) | N8: =ROUND(L8+M8,2)
A9: 4 | B9: 46357 | C9: ='Monthly Materials'!C9 | D9: =IF(A9<=Inputs!$B$6-11,2.8,IF(A9<=Inputs!$B$6-6,4.2,IF(A9<=Inputs!$B$6-3,6,IF(A9<=Inputs!$B$6,7.8,9.2)))) | E9: =SUMIF(Inputs!$D$41:$D$46,A9,Inputs!$E$41:$E$46) | F9: =ROUND(INDEX('MRP Cash Bridge'!$J$4:$J$39,A9)/100000,2) | G9: =ROUND('Monthly Materials'!D9*Inputs!$F$5+'Monthly Materials'!E9*Inputs!$F$6+'Monthly Materials'!F9*Inputs!$F$7,2) | H9: =ROUND(G9*Inputs!$B$10,2) | I9: =SUMIFS(Inputs!$C$15:$C$20,Inputs!$B$15:$B$20,A9,Inputs!$D$15:$D$20,"No") | J9: =SUMIFS(Inputs!$C$15:$C$20,Inputs!$B$15:$B$20,A9,Inputs!$D$15:$D$20,"Yes") | K9: =N8 | L9: =ROUND(K9+H9+I9+J9-D9-E9-F9,2) | M9: =ROUND(MAX(0,Inputs!$B$12-L9),2) | N9: =ROUND(L9+M9,2)
A10: 5 | B10: 46388 | C10: ='Monthly Materials'!C10 | D10: =IF(A10<=Inputs!$B$6-11,2.8,IF(A10<=Inputs!$B$6-6,4.2,IF(A10<=Inputs!$B$6-3,6,IF(A10<=Inputs!$B$6,7.8,9.2)))) | E10: =SUMIF(Inputs!$D$41:$D$46,A10,Inputs!$E$41:$E$46) | F10: =ROUND(INDEX('MRP Cash Bridge'!$J$4:$J$39,A10)/100000,2) | G10: =ROUND('Monthly Materials'!D10*Inputs!$F$5+'Monthly Materials'!E10*Inputs!$F$6+'Monthly Materials'!F10*Inputs!$F$7,2) | H10: =ROUND(G10*Inputs!$B$10,2) | I10: =SUMIFS(Inputs!$C$15:$C$20,Inputs!$B$15:$B$20,A10,Inputs!$D$15:$D$20,"No") | J10: =SUMIFS(Inputs!$C$15:$C$20,Inputs!$B$15:$B$20,A10,Inputs!$D$15:$D$20,"Yes") | K10: =N9 | L10: =ROUND(K10+H10+I10+J10-D10-E10-F10,2) | M10: =ROUND(MAX(0,Inputs!$B$12-L10),2) | N10: =ROUND(L10+M10,2)
A11: 6 | B11: 46419 | C11: ='Monthly Materials'!C11 | D11: =IF(A11<=Inputs!$B$6-11,2.8,IF(A11<=Inputs!$B$6-6,4.2,IF(A11<=Inputs!$B$6-3,6,IF(A11<=Inputs!$B$6,7.8,9.2)))) | E11: =SUMIF(Inputs!$D$41:$D$46,A11,Inputs!$E$41:$E$46) | F11: =ROUND(INDEX('MRP Cash Bridge'!$J$4:$J$39,A11)/100000,2) | G11: =ROUND('Monthly Materials'!D11*Inputs!$F$5+'Monthly Materials'!E11*Inputs!$F$6+'Monthly Materials'!F11*Inputs!$F$7,2) | H11: =ROUND(G11*Inputs!$B$10,2) | I11: =SUMIFS(Inputs!$C$15:$C$20,Inputs!$B$15:$B$20,A11,Inputs!$D$15:$D$20,"No") | J11: =SUMIFS(Inputs!$C$15:$C$20,Inputs!$B$15:$B$20,A11,Inputs!$D$15:$D$20,"Yes") | K11: =N10 | L11: =ROUND(K11+H11+I11+J11-D11-E11-F11,2) | M11: =ROUND(MAX(0,Inputs!$B$12-L11),2) | N11: =ROUND(L11+M11,2)
A12: 7 | B12: 46447 | C12: ='Monthly Materials'!C12 | D12: =IF(A12<=Inputs!$B$6-11,2.8,IF(A12<=Inputs!$B$6-6,4.2,IF(A12<=Inputs!$B$6-3,6,IF(A12<=Inputs!$B$6,7.8,9.2)))) | E12: =SUMIF(Inputs!$D$41:$D$46,A12,Inputs!$E$41:$E$46) | F12: =ROUND(INDEX('MRP Cash Bridge'!$J$4:$J$39,A12)/100000,2) | G12: =ROUND('Monthly Materials'!D12*Inputs!$F$5+'Monthly Materials'!E12*Inputs!$F$6+'Monthly Materials'!F12*Inputs!$F$7,2) | H12: =ROUND(G12*Inputs!$B$10,2) | I12: =SUMIFS(Inputs!$C$15:$C$20,Inputs!$B$15:$B$20,A12,Inputs!$D$15:$D$20,"No") | J12: =SUMIFS(Inputs!$C$15:$C$20,Inputs!$B$15:$B$20,A12,Inputs!$D$15:$D$20,"Yes") | K12: =N11 | L12: =ROUND(K12+H12+I12+J12-D12-E12-F12,2) | M12: =ROUND(MAX(0,Inputs!$B$12-L12),2) | N12: =ROUND(L12+M12,2)
A13: 8 | B13: 46478 | C13: ='Monthly Materials'!C13 | D13: =IF(A13<=Inputs!$B$6-11,2.8,IF(A13<=Inputs!$B$6-6,4.2,IF(A13<=Inputs!$B$6-3,6,IF(A13<=Inputs!$B$6,7.8,9.2)))) | E13: =SUMIF(Inputs!$D$41:$D$46,A13,Inputs!$E$41:$E$46) | F13: =ROUND(INDEX('MRP Cash Bridge'!$J$4:$J$39,A13)/100000,2) | G13: =ROUND('Monthly Materials'!D13*Inputs!$F$5+'Monthly Materials'!E13*Inputs!$F$6+'Monthly Materials'!F13*Inputs!$F$7,2) | H13: =ROUND(G13*Inputs!$B$10,2) | I13: =SUMIFS(Inputs!$C$15:$C$20,Inputs!$B$15:$B$20,A13,Inputs!$D$15:$D$20,"No") | J13: =SUMIFS(Inputs!$C$15:$C$20,Inputs!$B$15:$B$20,A13,Inputs!$D$15:$D$20,"Yes") | K13: =N12 | L13: =ROUND(K13+H13+I13+J13-D13-E13-F13,2) | M13: =ROUND(MAX(0,Inputs!$B$12-L13),2) | N13: =ROUND(L13+M13,2)
A14: 9 | B14: 46508 | C14: ='Monthly Materials'!C14 | D14: =IF(A14<=Inputs!$B$6-11,2.8,IF(A14<=Inputs!$B$6-6,4.2,IF(A14<=Inputs!$B$6-3,6,IF(A14<=Inputs!$B$6,7.8,9.2)))) | E14: =SUMIF(Inputs!$D$41:$D$46,A14,Inputs!$E$41:$E$46) | F14: =ROUND(INDEX('MRP Cash Bridge'!$J$4:$J$39,A14)/100000,2) | G14: =ROUND('Monthly Materials'!D14*Inputs!$F$5+'Monthly Materials'!E14*Inputs!$F$6+'Monthly Materials'!F14*Inputs!$F$7,2) | H14: =ROUND(G14*Inputs!$B$10,2) | I14: =SUMIFS(Inputs!$C$15:$C$20,Inputs!$B$15:$B$20,A14,Inputs!$D$15:$D$20,"No") | J14: =SUMIFS(Inputs!$C$15:$C$20,Inputs!$B$15:$B$20,A14,Inputs!$D$15:$D$20,"Yes") | K14: =N13 | L14: =ROUND(K14+H14+I14+J14-D14-E14-F14,2) | M14: =ROUND(MAX(0,Inputs!$B$12-L14),2) | N14: =ROUND(L14+M14,2)
A15: 10 | B15: 46539 | C15: ='Monthly Materials'!C15 | D15: =IF(A15<=Inputs!$B$6-11,2.8,IF(A15<=Inputs!$B$6-6,4.2,IF(A15<=Inputs!$B$6-3,6,IF(A15<=Inputs!$B$6,7.8,9.2)))) | E15: =SUMIF(Inputs!$D$41:$D$46,A15,Inputs!$E$41:$E$46) | F15: =ROUND(INDEX('MRP Cash Bridge'!$J$4:$J$39,A15)/100000,2) | G15: =ROUND('Monthly Materials'!D15*Inputs!$F$5+'Monthly Materials'!E15*Inputs!$F$6+'Monthly Materials'!F15*Inputs!$F$7,2) | H15: =ROUND(G15*Inputs!$B$10,2) | I15: =SUMIFS(Inputs!$C$15:$C$20,Inputs!$B$15:$B$20,A15,Inputs!$D$15:$D$20,"No") | J15: =SUMIFS(Inputs!$C$15:$C$20,Inputs!$B$15:$B$20,A15,Inputs!$D$15:$D$20,"Yes") | K15: =N14 | L15: =ROUND(K15+H15+I15+J15-D15-E15-F15,2) | M15: =ROUND(MAX(0,Inputs!$B$12-L15),2) | N15: =ROUND(L15+M15,2)
A16: 11 | B16: 46569 | C16: ='Monthly Materials'!C16 | D16: =IF(A16<=Inputs!$B$6-11,2.8,IF(A16<=Inputs!$B$6-6,4.2,IF(A16<=Inputs!$B$6-3,6,IF(A16<=Inputs!$B$6,7.8,9.2)))) | E16: =SUMIF(Inputs!$D$41:$D$46,A16,Inputs!$E$41:$E$46) | F16: =ROUND(INDEX('MRP Cash Bridge'!$J$4:$J$39,A16)/100000,2) | G16: =ROUND('Monthly Materials'!D16*Inputs!$F$5+'Monthly Materials'!E16*Inputs!$F$6+'Monthly Materials'!F16*Inputs!$F$7,2) | H16: =ROUND(G16*Inputs!$B$10,2) | I16: =SUMIFS(Inputs!$C$15:$C$20,Inputs!$B$15:$B$20,A16,Inputs!$D$15:$D$20,"No") | J16: =SUMIFS(Inputs!$C$15:$C$20,Inputs!$B$15:$B$20,A16,Inputs!$D$15:$D$20,"Yes") | K16: =N15 | L16: =ROUND(K16+H16+I16+J16-D16-E16-F16,2) | M16: =ROUND(MAX(0,Inputs!$B$12-L16),2) | N16: =ROUND(L16+M16,2)
A17: 12 | B17: 46600 | C17: ='Monthly Materials'!C17 | D17: =IF(A17<=Inputs!$B$6-11,2.8,IF(A17<=Inputs!$B$6-6,4.2,IF(A17<=Inputs!$B$6-3,6,IF(A17<=Inputs!$B$6,7.8,9.2)))) | E17: =SUMIF(Inputs!$D$41:$D$46,A17,Inputs!$E$41:$E$46) | F17: =ROUND(INDEX('MRP Cash Bridge'!$J$4:$J$39,A17)/100000,2) | G17: =ROUND('Monthly Materials'!D17*Inputs!$F$5+'Monthly Materials'!E17*Inputs!$F$6+'Monthly Materials'!F17*Inputs!$F$7,2) | H17: =ROUND(G17*Inputs!$B$10,2) | I17: =SUMIFS(Inputs!$C$15:$C$20,Inputs!$B$15:$B$20,A17,Inputs!$D$15:$D$20,"No") | J17: =SUMIFS(Inputs!$C$15:$C$20,Inputs!$B$15:$B$20,A17,Inputs!$D$15:$D$20,"Yes") | K17: =N16 | L17: =ROUND(K17+H17+I17+J17-D17-E17-F17,2) | M17: =ROUND(MAX(0,Inputs!$B$12-L17),2) | N17: =ROUND(L17+M17,2)
A18: 13 | B18: 46631 | C18: ='Monthly Materials'!C18 | D18: =IF(A18<=Inputs!$B$6-11,2.8,IF(A18<=Inputs!$B$6-6,4.2,IF(A18<=Inputs!$B$6-3,6,IF(A18<=Inputs!$B$6,7.8,9.2)))) | E18: =SUMIF(Inputs!$D$41:$D$46,A18,Inputs!$E$41:$E$46) | F18: =ROUND(INDEX('MRP Cash Bridge'!$J$4:$J$39,A18)/100000,2) | G18: =ROUND('Monthly Materials'!D18*Inputs!$F$5+'Monthly Materials'!E18*Inputs!$F$6+'Monthly Materials'!F18*Inputs!$F$7,2) | H18: =ROUND(G18*Inputs!$B$10,2) | I18: =SUMIFS(Inputs!$C$15:$C$20,Inputs!$B$15:$B$20,A18,Inputs!$D$15:$D$20,"No") | J18: =SUMIFS(Inputs!$C$15:$C$20,Inputs!$B$15:$B$20,A18,Inputs!$D$15:$D$20,"Yes") | K18: =N17 | L18: =ROUND(K18+H18+I18+J18-D18-E18-F18,2) | M18: =ROUND(MAX(0,Inputs!$B$12-L18),2) | N18: =ROUND(L18+M18,2)
... A41: 36 | B41: 47331 | C41: ='Monthly Materials'!C41 | D41: =IF(A41<=Inputs!$B$6-11,2.8,IF(A41<=Inputs!$B$6-6,4.2,IF(A41<=Inputs!$B$6-3,6,IF(A41<=Inputs!$B$6,7.8,9.2)))) | E41: =SUMIF(Inputs!$D$41:$D$46,A41,Inputs!$E$41:$E$46) | F41: =ROUND(INDEX('MRP Cash Bridge'!$J$4:$J$39,A41)/100000,2) | G41: =ROUND('Monthly Materials'!D41*Inputs!$F$5+'Monthly Materials'!E41*Inputs!$F$6+'Monthly Materials'!F41*Inputs!$F$7,2) | H41: =ROUND(G41*Inputs!$B$10,2) | I41: =SUMIFS(Inputs!$C$15:$C$20,Inputs!$B$15:$B$20,A41,Inputs!$D$15:$D$20,"No") | J41: =SUMIFS(Inputs!$C$15:$C$20,Inputs!$B$15:$B$20,A41,Inputs!$D$15:$D$20,"Yes") | K41: =N40 | L41: =ROUND(K41+H41+I41+J41-D41-E41-F41,2) | M41: =ROUND(MAX(0,Inputs!$B$12-L41),2) | N41: =ROUND(L41+M41,2)
A42: 36M TOTAL | C42: =SUM(C6:C41) | D42: =SUM(D6:D41) | E42: =SUM(E6:E41) | F42: =SUM(F6:F41) | G42: =SUM(G6:G41) | H42: =SUM(H6:H41) | I42: =SUM(I6:I41) | J42: =SUM(J6:J41) | M42: =SUM(M6:M41) | N42: =N41

Sheet Monthly Materials
A1: Monthly Raw Materials & Components
A2: Gross requirement including editable material buffer · opening inventory assumed zero
A5: Month | B5: Date | C5: Total units | D5: Longitude | E5: Latitude | F5: Altitude | G5: Aluminium/OEM frameset (set) | H5: T700 prepreg (kg) | I5: T800 prepreg (kg) | J5: Resin & bonding system (kg) | K5: Paint & clear coat (L) | L5: Groupset (set) | M5: Wheelset (set) | N5: Tyres (ea) | O5: Cockpit (set) | P5: Saddle (ea) | Q5: Brake system (set) | R5: Packaging kit (kit) | S5: Material cost ₹ | T5: Material cost ₹L
A6: 1 | B6: 46266 | C6: =IF(A6<Inputs!$B$6,0,INDEX(Inputs!$B$41:$B$64,MIN(A6-Inputs!$B$6+1,24))*Inputs!$B$8) | D6: =IF(C6=0,0,IF(A6<Inputs!$G$7,ROUND(C6*25%,0),ROUND(C6*Inputs!$E$5,0))) | E6: =IF(C6=0,0,IF(A6<Inputs!$G$7,C6-D6,ROUND(C6*Inputs!$E$6,0))) | F6: =C6-D6-E6 | G6: =ROUND((D6*Inputs!$C$25+E6*Inputs!$D$25+F6*Inputs!$E$25)*(1+Inputs!$B$9),2) | H6: =ROUND((D6*Inputs!$C$26+E6*Inputs!$D$26+F6*Inputs!$E$26)*(1+Inputs!$B$9),2) | I6: =ROUND((D6*Inputs!$C$27+E6*Inputs!$D$27+F6*Inputs!$E$27)*(1+Inputs!$B$9),2) | J6: =ROUND((D6*Inputs!$C$28+E6*Inputs!$D$28+F6*Inputs!$E$28)*(1+Inputs!$B$9),2) | K6: =ROUND((D6*Inputs!$C$29+E6*Inputs!$D$29+F6*Inputs!$E$29)*(1+Inputs!$B$9),2) | L6: =ROUND((D6*Inputs!$C$30+E6*Inputs!$D$30+F6*Inputs!$E$30)*(1+Inputs!$B$9),2) | M6: =ROUND((D6*Inputs!$C$31+E6*Inputs!$D$31+F6*Inputs!$E$31)*(1+Inputs!$B$9),2) | N6: =ROUND((D6*Inputs!$C$32+E6*Inputs!$D$32+F6*Inputs!$E$32)*(1+Inputs!$B$9),2) | O6: =ROUND((D6*Inputs!$C$33+E6*Inputs!$D$33+F6*Inputs!$E$33)*(1+Inputs!$B$9),2) | P6: =ROUND((D6*Inputs!$C$34+E6*Inputs!$D$34+F6*Inputs!$E$34)*(1+Inputs!$B$9),2) | Q6: =ROUND((D6*Inputs!$C$35+E6*Inputs!$D$35+F6*Inputs!$E$35)*(1+Inputs!$B$9),2) | R6: =ROUND((D6*Inputs!$C$36+E6*Inputs!$D$36+F6*Inputs!$E$36)*(1+Inputs!$B$9),2) | S6: =ROUND(G6*Inputs!$F$25+H6*Inputs!$F$26+I6*Inputs!$F$27+J6*Inputs!$F$28+K6*Inputs!$F$29+L6*Inputs!$F$30+M6*Inputs!$F$31+N6*Inputs!$F$32+O6*Inputs!$F$33+P6*Inputs!$F$34+Q6*Inputs!$F$35+R6*Inputs!$F$36,2) | T6: =ROUND(S6/100000,2)
A7: 2 | B7: 46296 | C7: =IF(A7<Inputs!$B$6,0,INDEX(Inputs!$B$41:$B$64,MIN(A7-Inputs!$B$6+1,24))*Inputs!$B$8) | D7: =IF(C7=0,0,IF(A7<Inputs!$G$7,ROUND(C7*25%,0),ROUND(C7*Inputs!$E$5,0))) | E7: =IF(C7=0,0,IF(A7<Inputs!$G$7,C7-D7,ROUND(C7*Inputs!$E$6,0))) | F7: =C7-D7-E7 | G7: =ROUND((D7*Inputs!$C$25+E7*Inputs!$D$25+F7*Inputs!$E$25)*(1+Inputs!$B$9),2) | H7: =ROUND((D7*Inputs!$C$26+E7*Inputs!$D$26+F7*Inputs!$E$26)*(1+Inputs!$B$9),2) | I7: =ROUND((D7*Inputs!$C$27+E7*Inputs!$D$27+F7*Inputs!$E$27)*(1+Inputs!$B$9),2) | J7: =ROUND((D7*Inputs!$C$28+E7*Inputs!$D$28+F7*Inputs!$E$28)*(1+Inputs!$B$9),2) | K7: =ROUND((D7*Inputs!$C$29+E7*Inputs!$D$29+F7*Inputs!$E$29)*(1+Inputs!$B$9),2) | L7: =ROUND((D7*Inputs!$C$30+E7*Inputs!$D$30+F7*Inputs!$E$30)*(1+Inputs!$B$9),2) | M7: =ROUND((D7*Inputs!$C$31+E7*Inputs!$D$31+F7*Inputs!$E$31)*(1+Inputs!$B$9),2) | N7: =ROUND((D7*Inputs!$C$32+E7*Inputs!$D$32+F7*Inputs!$E$32)*(1+Inputs!$B$9),2) | O7: =ROUND((D7*Inputs!$C$33+E7*Inputs!$D$33+F7*Inputs!$E$33)*(1+Inputs!$B$9),2) | P7: =ROUND((D7*Inputs!$C$34+E7*Inputs!$D$34+F7*Inputs!$E$34)*(1+Inputs!$B$9),2) | Q7: =ROUND((D7*Inputs!$C$35+E7*Inputs!$D$35+F7*Inputs!$E$35)*(1+Inputs!$B$9),2) | R7: =ROUND((D7*Inputs!$C$36+E7*Inputs!$D$36+F7*Inputs!$E$36)*(1+Inputs!$B$9),2) | S7: =ROUND(G7*Inputs!$F$25+H7*Inputs!$F$26+I7*Inputs!$F$27+J7*Inputs!$F$28+K7*Inputs!$F$29+L7*Inputs!$F$30+M7*Inputs!$F$31+N7*Inputs!$F$32+O7*Inputs!$F$33+P7*Inputs!$F$34+Q7*Inputs!$F$35+R7*Inputs!$F$36,2) | T7: =ROUND(S7/100000,2)
A8: 3 | B8: 46327 | C8: =IF(A8<Inputs!$B$6,0,INDEX(Inputs!$B$41:$B$64,MIN(A8-Inputs!$B$6+1,24))*Inputs!$B$8) | D8: =IF(C8=0,0,IF(A8<Inputs!$G$7,ROUND(C8*25%,0),ROUND(C8*Inputs!$E$5,0))) | E8: =IF(C8=0,0,IF(A8<Inputs!$G$7,C8-D8,ROUND(C8*Inputs!$E$6,0))) | F8: =C8-D8-E8 | G8: =ROUND((D8*Inputs!$C$25+E8*Inputs!$D$25+F8*Inputs!$E$25)*(1+Inputs!$B$9),2) | H8: =ROUND((D8*Inputs!$C$26+E8*Inputs!$D$26+F8*Inputs!$E$26)*(1+Inputs!$B$9),2) | I8: =ROUND((D8*Inputs!$C$27+E8*Inputs!$D$27+F8*Inputs!$E$27)*(1+Inputs!$B$9),2) | J8: =ROUND((D8*Inputs!$C$28+E8*Inputs!$D$28+F8*Inputs!$E$28)*(1+Inputs!$B$9),2) | K8: =ROUND((D8*Inputs!$C$29+E8*Inputs!$D$29+F8*Inputs!$E$29)*(1+Inputs!$B$9),2) | L8: =ROUND((D8*Inputs!$C$30+E8*Inputs!$D$30+F8*Inputs!$E$30)*(1+Inputs!$B$9),2) | M8: =ROUND((D8*Inputs!$C$31+E8*Inputs!$D$31+F8*Inputs!$E$31)*(1+Inputs!$B$9),2) | N8: =ROUND((D8*Inputs!$C$32+E8*Inputs!$D$32+F8*Inputs!$E$32)*(1+Inputs!$B$9),2) | O8: =ROUND((D8*Inputs!$C$33+E8*Inputs!$D$33+F8*Inputs!$E$33)*(1+Inputs!$B$9),2) | P8: =ROUND((D8*Inputs!$C$34+E8*Inputs!$D$34+F8*Inputs!$E$34)*(1+Inputs!$B$9),2) | Q8: =ROUND((D8*Inputs!$C$35+E8*Inputs!$D$35+F8*Inputs!$E$35)*(1+Inputs!$B$9),2) | R8: =ROUND((D8*Inputs!$C$36+E8*Inputs!$D$36+F8*Inputs!$E$36)*(1+Inputs!$B$9),2) | S8: =ROUND(G8*Inputs!$F$25+H8*Inputs!$F$26+I8*Inputs!$F$27+J8*Inputs!$F$28+K8*Inputs!$F$29+L8*Inputs!$F$30+M8*Inputs!$F$31+N8*Inputs!$F$32+O8*Inputs!$F$33+P8*Inputs!$F$34+Q8*Inputs!$F$35+R8*Inputs!$F$36,2) | T8: =ROUND(S8/100000,2)
A9: 4 | B9: 46357 | C9: =IF(A9<Inputs!$B$6,0,INDEX(Inputs!$B$41:$B$64,MIN(A9-Inputs!$B$6+1,24))*Inputs!$B$8) | D9: =IF(C9=0,0,IF(A9<Inputs!$G$7,ROUND(C9*25%,0),ROUND(C9*Inputs!$E$5,0))) | E9: =IF(C9=0,0,IF(A9<Inputs!$G$7,C9-D9,ROUND(C9*Inputs!$E$6,0))) | F9: =C9-D9-E9 | G9: =ROUND((D9*Inputs!$C$25+E9*Inputs!$D$25+F9*Inputs!$E$25)*(1+Inputs!$B$9),2) | H9: =ROUND((D9*Inputs!$C$26+E9*Inputs!$D$26+F9*Inputs!$E$26)*(1+Inputs!$B$9),2) | I9: =ROUND((D9*Inputs!$C$27+E9*Inputs!$D$27+F9*Inputs!$E$27)*(1+Inputs!$B$9),2) | J9: =ROUND((D9*Inputs!$C$28+E9*Inputs!$D$28+F9*Inputs!$E$28)*(1+Inputs!$B$9),2) | K9: =ROUND((D9*Inputs!$C$29+E9*Inputs!$D$29+F9*Inputs!$E$29)*(1+Inputs!$B$9),2) | L9: =ROUND((D9*Inputs!$C$30+E9*Inputs!$D$30+F9*Inputs!$E$30)*(1+Inputs!$B$9),2) | M9: =ROUND((D9*Inputs!$C$31+E9*Inputs!$D$31+F9*Inputs!$E$31)*(1+Inputs!$B$9),2) | N9: =ROUND((D9*Inputs!$C$32+E9*Inputs!$D$32+F9*Inputs!$E$32)*(1+Inputs!$B$9),2) | O9: =ROUND((D9*Inputs!$C$33+E9*Inputs!$D$33+F9*Inputs!$E$33)*(1+Inputs!$B$9),2) | P9: =ROUND((D9*Inputs!$C$34+E9*Inputs!$D$34+F9*Inputs!$E$34)*(1+Inputs!$B$9),2) | Q9: =ROUND((D9*Inputs!$C$35+E9*Inputs!$D$35+F9*Inputs!$E$35)*(1+Inputs!$B$9),2) | R9: =ROUND((D9*Inputs!$C$36+E9*Inputs!$D$36+F9*Inputs!$E$36)*(1+Inputs!$B$9),2) | S9: =ROUND(G9*Inputs!$F$25+H9*Inputs!$F$26+I9*Inputs!$F$27+J9*Inputs!$F$28+K9*Inputs!$F$29+L9*Inputs!$F$30+M9*Inputs!$F$31+N9*Inputs!$F$32+O9*Inputs!$F$33+P9*Inputs!$F$34+Q9*Inputs!$F$35+R9*Inputs!$F$36,2) | T9: =ROUND(S9/100000,2)
A10: 5 | B10: 46388 | C10: =IF(A10<Inputs!$B$6,0,INDEX(Inputs!$B$41:$B$64,MIN(A10-Inputs!$B$6+1,24))*Inputs!$B$8) | D10: =IF(C10=0,0,IF(A10<Inputs!$G$7,ROUND(C10*25%,0),ROUND(C10*Inputs!$E$5,0))) | E10: =IF(C10=0,0,IF(A10<Inputs!$G$7,C10-D10,ROUND(C10*Inputs!$E$6,0))) | F10: =C10-D10-E10 | G10: =ROUND((D10*Inputs!$C$25+E10*Inputs!$D$25+F10*Inputs!$E$25)*(1+Inputs!$B$9),2) | H10: =ROUND((D10*Inputs!$C$26+E10*Inputs!$D$26+F10*Inputs!$E$26)*(1+Inputs!$B$9),2) | I10: =ROUND((D10*Inputs!$C$27+E10*Inputs!$D$27+F10*Inputs!$E$27)*(1+Inputs!$B$9),2) | J10: =ROUND((D10*Inputs!$C$28+E10*Inputs!$D$28+F10*Inputs!$E$28)*(1+Inputs!$B$9),2) | K10: =ROUND((D10*Inputs!$C$29+E10*Inputs!$D$29+F10*Inputs!$E$29)*(1+Inputs!$B$9),2) | L10: =ROUND((D10*Inputs!$C$30+E10*Inputs!$D$30+F10*Inputs!$E$30)*(1+Inputs!$B$9),2) | M10: =ROUND((D10*Inputs!$C$31+E10*Inputs!$D$31+F10*Inputs!$E$31)*(1+Inputs!$B$9),2) | N10: =ROUND((D10*Inputs!$C$32+E10*Inputs!$D$32+F10*Inputs!$E$32)*(1+Inputs!$B$9),2) | O10: =ROUND((D10*Inputs!$C$33+E10*Inputs!$D$33+F10*Inputs!$E$33)*(1+Inputs!$B$9),2) | P10: =ROUND((D10*Inputs!$C$34+E10*Inputs!$D$34+F10*Inputs!$E$34)*(1+Inputs!$B$9),2) | Q10: =ROUND((D10*Inputs!$C$35+E10*Inputs!$D$35+F10*Inputs!$E$35)*(1+Inputs!$B$9),2) | R10: =ROUND((D10*Inputs!$C$36+E10*Inputs!$D$36+F10*Inputs!$E$36)*(1+Inputs!$B$9),2) | S10: =ROUND(G10*Inputs!$F$25+H10*Inputs!$F$26+I10*Inputs!$F$27+J10*Inputs!$F$28+K10*Inputs!$F$29+L10*Inputs!$F$30+M10*Inputs!$F$31+N10*Inputs!$F$32+O10*Inputs!$F$33+P10*Inputs!$F$34+Q10*Inputs!$F$35+R10*Inputs!$F$36,2) | T10: =ROUND(S10/100000,2)
A11: 6 | B11: 46419 | C11: =IF(A11<Inputs!$B$6,0,INDEX(Inputs!$B$41:$B$64,MIN(A11-Inputs!$B$6+1,24))*Inputs!$B$8) | D11: =IF(C11=0,0,IF(A11<Inputs!$G$7,ROUND(C11*25%,0),ROUND(C11*Inputs!$E$5,0))) | E11: =IF(C11=0,0,IF(A11<Inputs!$G$7,C11-D11,ROUND(C11*Inputs!$E$6,0))) | F11: =C11-D11-E11 | G11: =ROUND((D11*Inputs!$C$25+E11*Inputs!$D$25+F11*Inputs!$E$25)*(1+Inputs!$B$9),2) | H11: =ROUND((D11*Inputs!$C$26+E11*Inputs!$D$26+F11*Inputs!$E$26)*(1+Inputs!$B$9),2) | I11: =ROUND((D11*Inputs!$C$27+E11*Inputs!$D$27+F11*Inputs!$E$27)*(1+Inputs!$B$9),2) | J11: =ROUND((D11*Inputs!$C$28+E11*Inputs!$D$28+F11*Inputs!$E$28)*(1+Inputs!$B$9),2) | K11: =ROUND((D11*Inputs!$C$29+E11*Inputs!$D$29+F11*Inputs!$E$29)*(1+Inputs!$B$9),2) | L11: =ROUND((D11*Inputs!$C$30+E11*Inputs!$D$30+F11*Inputs!$E$30)*(1+Inputs!$B$9),2) | M11: =ROUND((D11*Inputs!$C$31+E11*Inputs!$D$31+F11*Inputs!$E$31)*(1+Inputs!$B$9),2) | N11: =ROUND((D11*Inputs!$C$32+E11*Inputs!$D$32+F11*Inputs!$E$32)*(1+Inputs!$B$9),2) | O11: =ROUND((D11*Inputs!$C$33+E11*Inputs!$D$33+F11*Inputs!$E$33)*(1+Inputs!$B$9),2) | P11: =ROUND((D11*Inputs!$C$34+E11*Inputs!$D$34+F11*Inputs!$E$34)*(1+Inputs!$B$9),2) | Q11: =ROUND((D11*Inputs!$C$35+E11*Inputs!$D$35+F11*Inputs!$E$35)*(1+Inputs!$B$9),2) | R11: =ROUND((D11*Inputs!$C$36+E11*Inputs!$D$36+F11*Inputs!$E$36)*(1+Inputs!$B$9),2) | S11: =ROUND(G11*Inputs!$F$25+H11*Inputs!$F$26+I11*Inputs!$F$27+J11*Inputs!$F$28+K11*Inputs!$F$29+L11*Inputs!$F$30+M11*Inputs!$F$31+N11*Inputs!$F$32+O11*Inputs!$F$33+P11*Inputs!$F$34+Q11*Inputs!$F$35+R11*Inputs!$F$36,2) | T11: =ROUND(S11/100000,2)
A12: 7 | B12: 46447 | C12: =IF(A12<Inputs!$B$6,0,INDEX(Inputs!$B$41:$B$64,MIN(A12-Inputs!$B$6+1,24))*Inputs!$B$8) | D12: =IF(C12=0,0,IF(A12<Inputs!$G$7,ROUND(C12*25%,0),ROUND(C12*Inputs!$E$5,0))) | E12: =IF(C12=0,0,IF(A12<Inputs!$G$7,C12-D12,ROUND(C12*Inputs!$E$6,0))) | F12: =C12-D12-E12 | G12: =ROUND((D12*Inputs!$C$25+E12*Inputs!$D$25+F12*Inputs!$E$25)*(1+Inputs!$B$9),2) | H12: =ROUND((D12*Inputs!$C$26+E12*Inputs!$D$26+F12*Inputs!$E$26)*(1+Inputs!$B$9),2) | I12: =ROUND((D12*Inputs!$C$27+E12*Inputs!$D$27+F12*Inputs!$E$27)*(1+Inputs!$B$9),2) | J12: =ROUND((D12*Inputs!$C$28+E12*Inputs!$D$28+F12*Inputs!$E$28)*(1+Inputs!$B$9),2) | K12: =ROUND((D12*Inputs!$C$29+E12*Inputs!$D$29+F12*Inputs!$E$29)*(1+Inputs!$B$9),2) | L12: =ROUND((D12*Inputs!$C$30+E12*Inputs!$D$30+F12*Inputs!$E$30)*(1+Inputs!$B$9),2) | M12: =ROUND((D12*Inputs!$C$31+E12*Inputs!$D$31+F12*Inputs!$E$31)*(1+Inputs!$B$9),2) | N12: =ROUND((D12*Inputs!$C$32+E12*Inputs!$D$32+F12*Inputs!$E$32)*(1+Inputs!$B$9),2) | O12: =ROUND((D12*Inputs!$C$33+E12*Inputs!$D$33+F12*Inputs!$E$33)*(1+Inputs!$B$9),2) | P12: =ROUND((D12*Inputs!$C$34+E12*Inputs!$D$34+F12*Inputs!$E$34)*(1+Inputs!$B$9),2) | Q12: =ROUND((D12*Inputs!$C$35+E12*Inputs!$D$35+F12*Inputs!$E$35)*(1+Inputs!$B$9),2) | R12: =ROUND((D12*Inputs!$C$36+E12*Inputs!$D$36+F12*Inputs!$E$36)*(1+Inputs!$B$9),2) | S12: =ROUND(G12*Inputs!$F$25+H12*Inputs!$F$26+I12*Inputs!$F$27+J12*Inputs!$F$28+K12*Inputs!$F$29+L12*Inputs!$F$30+M12*Inputs!$F$31+N12*Inputs!$F$32+O12*Inputs!$F$33+P12*Inputs!$F$34+Q12*Inputs!$F$35+R12*Inputs!$F$36,2) | T12: =ROUND(S12/100000,2)
A13: 8 | B13: 46478 | C13: =IF(A13<Inputs!$B$6,0,INDEX(Inputs!$B$41:$B$64,MIN(A13-Inputs!$B$6+1,24))*Inputs!$B$8) | D13: =IF(C13=0,0,IF(A13<Inputs!$G$7,ROUND(C13*25%,0),ROUND(C13*Inputs!$E$5,0))) | E13: =IF(C13=0,0,IF(A13<Inputs!$G$7,C13-D13,ROUND(C13*Inputs!$E$6,0))) | F13: =C13-D13-E13 | G13: =ROUND((D13*Inputs!$C$25+E13*Inputs!$D$25+F13*Inputs!$E$25)*(1+Inputs!$B$9),2) | H13: =ROUND((D13*Inputs!$C$26+E13*Inputs!$D$26+F13*Inputs!$E$26)*(1+Inputs!$B$9),2) | I13: =ROUND((D13*Inputs!$C$27+E13*Inputs!$D$27+F13*Inputs!$E$27)*(1+Inputs!$B$9),2) | J13: =ROUND((D13*Inputs!$C$28+E13*Inputs!$D$28+F13*Inputs!$E$28)*(1+Inputs!$B$9),2) | K13: =ROUND((D13*Inputs!$C$29+E13*Inputs!$D$29+F13*Inputs!$E$29)*(1+Inputs!$B$9),2) | L13: =ROUND((D13*Inputs!$C$30+E13*Inputs!$D$30+F13*Inputs!$E$30)*(1+Inputs!$B$9),2) | M13: =ROUND((D13*Inputs!$C$31+E13*Inputs!$D$31+F13*Inputs!$E$31)*(1+Inputs!$B$9),2) | N13: =ROUND((D13*Inputs!$C$32+E13*Inputs!$D$32+F13*Inputs!$E$32)*(1+Inputs!$B$9),2) | O13: =ROUND((D13*Inputs!$C$33+E13*Inputs!$D$33+F13*Inputs!$E$33)*(1+Inputs!$B$9),2) | P13: =ROUND((D13*Inputs!$C$34+E13*Inputs!$D$34+F13*Inputs!$E$34)*(1+Inputs!$B$9),2) | Q13: =ROUND((D13*Inputs!$C$35+E13*Inputs!$D$35+F13*Inputs!$E$35)*(1+Inputs!$B$9),2) | R13: =ROUND((D13*Inputs!$C$36+E13*Inputs!$D$36+F13*Inputs!$E$36)*(1+Inputs!$B$9),2) | S13: =ROUND(G13*Inputs!$F$25+H13*Inputs!$F$26+I13*Inputs!$F$27+J13*Inputs!$F$28+K13*Inputs!$F$29+L13*Inputs!$F$30+M13*Inputs!$F$31+N13*Inputs!$F$32+O13*Inputs!$F$33+P13*Inputs!$F$34+Q13*Inputs!$F$35+R13*Inputs!$F$36,2) | T13: =ROUND(S13/100000,2)
A14: 9 | B14: 46508 | C14: =IF(A14<Inputs!$B$6,0,INDEX(Inputs!$B$41:$B$64,MIN(A14-Inputs!$B$6+1,24))*Inputs!$B$8) | D14: =IF(C14=0,0,IF(A14<Inputs!$G$7,ROUND(C14*25%,0),ROUND(C14*Inputs!$E$5,0))) | E14: =IF(C14=0,0,IF(A14<Inputs!$G$7,C14-D14,ROUND(C14*Inputs!$E$6,0))) | F14: =C14-D14-E14 | G14: =ROUND((D14*Inputs!$C$25+E14*Inputs!$D$25+F14*Inputs!$E$25)*(1+Inputs!$B$9),2) | H14: =ROUND((D14*Inputs!$C$26+E14*Inputs!$D$26+F14*Inputs!$E$26)*(1+Inputs!$B$9),2) | I14: =ROUND((D14*Inputs!$C$27+E14*Inputs!$D$27+F14*Inputs!$E$27)*(1+Inputs!$B$9),2) | J14: =ROUND((D14*Inputs!$C$28+E14*Inputs!$D$28+F14*Inputs!$E$28)*(1+Inputs!$B$9),2) | K14: =ROUND((D14*Inputs!$C$29+E14*Inputs!$D$29+F14*Inputs!$E$29)*(1+Inputs!$B$9),2) | L14: =ROUND((D14*Inputs!$C$30+E14*Inputs!$D$30+F14*Inputs!$E$30)*(1+Inputs!$B$9),2) | M14: =ROUND((D14*Inputs!$C$31+E14*Inputs!$D$31+F14*Inputs!$E$31)*(1+Inputs!$B$9),2) | N14: =ROUND((D14*Inputs!$C$32+E14*Inputs!$D$32+F14*Inputs!$E$32)*(1+Inputs!$B$9),2) | O14: =ROUND((D14*Inputs!$C$33+E14*Inputs!$D$33+F14*Inputs!$E$33)*(1+Inputs!$B$9),2) | P14: =ROUND((D14*Inputs!$C$34+E14*Inputs!$D$34+F14*Inputs!$E$34)*(1+Inputs!$B$9),2) | Q14: =ROUND((D14*Inputs!$C$35+E14*Inputs!$D$35+F14*Inputs!$E$35)*(1+Inputs!$B$9),2) | R14: =ROUND((D14*Inputs!$C$36+E14*Inputs!$D$36+F14*Inputs!$E$36)*(1+Inputs!$B$9),2) | S14: =ROUND(G14*Inputs!$F$25+H14*Inputs!$F$26+I14*Inputs!$F$27+J14*Inputs!$F$28+K14*Inputs!$F$29+L14*Inputs!$F$30+M14*Inputs!$F$31+N14*Inputs!$F$32+O14*Inputs!$F$33+P14*Inputs!$F$34+Q14*Inputs!$F$35+R14*Inputs!$F$36,2) | T14: =ROUND(S14/100000,2)
A15: 10 | B15: 46539 | C15: =IF(A15<Inputs!$B$6,0,INDEX(Inputs!$B$41:$B$64,MIN(A15-Inputs!$B$6+1,24))*Inputs!$B$8) | D15: =IF(C15=0,0,IF(A15<Inputs!$G$7,ROUND(C15*25%,0),ROUND(C15*Inputs!$E$5,0))) | E15: =IF(C15=0,0,IF(A15<Inputs!$G$7,C15-D15,ROUND(C15*Inputs!$E$6,0))) | F15: =C15-D15-E15 | G15: =ROUND((D15*Inputs!$C$25+E15*Inputs!$D$25+F15*Inputs!$E$25)*(1+Inputs!$B$9),2) | H15: =ROUND((D15*Inputs!$C$26+E15*Inputs!$D$26+F15*Inputs!$E$26)*(1+Inputs!$B$9),2) | I15: =ROUND((D15*Inputs!$C$27+E15*Inputs!$D$27+F15*Inputs!$E$27)*(1+Inputs!$B$9),2) | J15: =ROUND((D15*Inputs!$C$28+E15*Inputs!$D$28+F15*Inputs!$E$28)*(1+Inputs!$B$9),2) | K15: =ROUND((D15*Inputs!$C$29+E15*Inputs!$D$29+F15*Inputs!$E$29)*(1+Inputs!$B$9),2) | L15: =ROUND((D15*Inputs!$C$30+E15*Inputs!$D$30+F15*Inputs!$E$30)*(1+Inputs!$B$9),2) | M15: =ROUND((D15*Inputs!$C$31+E15*Inputs!$D$31+F15*Inputs!$E$31)*(1+Inputs!$B$9),2) | N15: =ROUND((D15*Inputs!$C$32+E15*Inputs!$D$32+F15*Inputs!$E$32)*(1+Inputs!$B$9),2) | O15: =ROUND((D15*Inputs!$C$33+E15*Inputs!$D$33+F15*Inputs!$E$33)*(1+Inputs!$B$9),2) | P15: =ROUND((D15*Inputs!$C$34+E15*Inputs!$D$34+F15*Inputs!$E$34)*(1+Inputs!$B$9),2) | Q15: =ROUND((D15*Inputs!$C$35+E15*Inputs!$D$35+F15*Inputs!$E$35)*(1+Inputs!$B$9),2) | R15: =ROUND((D15*Inputs!$C$36+E15*Inputs!$D$36+F15*Inputs!$E$36)*(1+Inputs!$B$9),2) | S15: =ROUND(G15*Inputs!$F$25+H15*Inputs!$F$26+I15*Inputs!$F$27+J15*Inputs!$F$28+K15*Inputs!$F$29+L15*Inputs!$F$30+M15*Inputs!$F$31+N15*Inputs!$F$32+O15*Inputs!$F$33+P15*Inputs!$F$34+Q15*Inputs!$F$35+R15*Inputs!$F$36,2) | T15: =ROUND(S15/100000,2)
A16: 11 | B16: 46569 | C16: =IF(A16<Inputs!$B$6,0,INDEX(Inputs!$B$41:$B$64,MIN(A16-Inputs!$B$6+1,24))*Inputs!$B$8) | D16: =IF(C16=0,0,IF(A16<Inputs!$G$7,ROUND(C16*25%,0),ROUND(C16*Inputs!$E$5,0))) | E16: =IF(C16=0,0,IF(A16<Inputs!$G$7,C16-D16,ROUND(C16*Inputs!$E$6,0))) | F16: =C16-D16-E16 | G16: =ROUND((D16*Inputs!$C$25+E16*Inputs!$D$25+F16*Inputs!$E$25)*(1+Inputs!$B$9),2) | H16: =ROUND((D16*Inputs!$C$26+E16*Inputs!$D$26+F16*Inputs!$E$26)*(1+Inputs!$B$9),2) | I16: =ROUND((D16*Inputs!$C$27+E16*Inputs!$D$27+F16*Inputs!$E$27)*(1+Inputs!$B$9),2) | J16: =ROUND((D16*Inputs!$C$28+E16*Inputs!$D$28+F16*Inputs!$E$28)*(1+Inputs!$B$9),2) | K16: =ROUND((D16*Inputs!$C$29+E16*Inputs!$D$29+F16*Inputs!$E$29)*(1+Inputs!$B$9),2) | L16: =ROUND((D16*Inputs!$C$30+E16*Inputs!$D$30+F16*Inputs!$E$30)*(1+Inputs!$B$9),2) | M16: =ROUND((D16*Inputs!$C$31+E16*Inputs!$D$31+F16*Inputs!$E$31)*(1+Inputs!$B$9),2) | N16: =ROUND((D16*Inputs!$C$32+E16*Inputs!$D$32+F16*Inputs!$E$32)*(1+Inputs!$B$9),2) | O16: =ROUND((D16*Inputs!$C$33+E16*Inputs!$D$33+F16*Inputs!$E$33)*(1+Inputs!$B$9),2) | P16: =ROUND((D16*Inputs!$C$34+E16*Inputs!$D$34+F16*Inputs!$E$34)*(1+Inputs!$B$9),2) | Q16: =ROUND((D16*Inputs!$C$35+E16*Inputs!$D$35+F16*Inputs!$E$35)*(1+Inputs!$B$9),2) | R16: =ROUND((D16*Inputs!$C$36+E16*Inputs!$D$36+F16*Inputs!$E$36)*(1+Inputs!$B$9),2) | S16: =ROUND(G16*Inputs!$F$25+H16*Inputs!$F$26+I16*Inputs!$F$27+J16*Inputs!$F$28+K16*Inputs!$F$29+L16*Inputs!$F$30+M16*Inputs!$F$31+N16*Inputs!$F$32+O16*Inputs!$F$33+P16*Inputs!$F$34+Q16*Inputs!$F$35+R16*Inputs!$F$36,2) | T16: =ROUND(S16/100000,2)
A17: 12 | B17: 46600 | C17: =IF(A17<Inputs!$B$6,0,INDEX(Inputs!$B$41:$B$64,MIN(A17-Inputs!$B$6+1,24))*Inputs!$B$8) | D17: =IF(C17=0,0,IF(A17<Inputs!$G$7,ROUND(C17*25%,0),ROUND(C17*Inputs!$E$5,0))) | E17: =IF(C17=0,0,IF(A17<Inputs!$G$7,C17-D17,ROUND(C17*Inputs!$E$6,0))) | F17: =C17-D17-E17 | G17: =ROUND((D17*Inputs!$C$25+E17*Inputs!$D$25+F17*Inputs!$E$25)*(1+Inputs!$B$9),2) | H17: =ROUND((D17*Inputs!$C$26+E17*Inputs!$D$26+F17*Inputs!$E$26)*(1+Inputs!$B$9),2) | I17: =ROUND((D17*Inputs!$C$27+E17*Inputs!$D$27+F17*Inputs!$E$27)*(1+Inputs!$B$9),2) | J17: =ROUND((D17*Inputs!$C$28+E17*Inputs!$D$28+F17*Inputs!$E$28)*(1+Inputs!$B$9),2) | K17: =ROUND((D17*Inputs!$C$29+E17*Inputs!$D$29+F17*Inputs!$E$29)*(1+Inputs!$B$9),2) | L17: =ROUND((D17*Inputs!$C$30+E17*Inputs!$D$30+F17*Inputs!$E$30)*(1+Inputs!$B$9),2) | M17: =ROUND((D17*Inputs!$C$31+E17*Inputs!$D$31+F17*Inputs!$E$31)*(1+Inputs!$B$9),2) | N17: =ROUND((D17*Inputs!$C$32+E17*Inputs!$D$32+F17*Inputs!$E$32)*(1+Inputs!$B$9),2) | O17: =ROUND((D17*Inputs!$C$33+E17*Inputs!$D$33+F17*Inputs!$E$33)*(1+Inputs!$B$9),2) | P17: =ROUND((D17*Inputs!$C$34+E17*Inputs!$D$34+F17*Inputs!$E$34)*(1+Inputs!$B$9),2) | Q17: =ROUND((D17*Inputs!$C$35+E17*Inputs!$D$35+F17*Inputs!$E$35)*(1+Inputs!$B$9),2) | R17: =ROUND((D17*Inputs!$C$36+E17*Inputs!$D$36+F17*Inputs!$E$36)*(1+Inputs!$B$9),2) | S17: =ROUND(G17*Inputs!$F$25+H17*Inputs!$F$26+I17*Inputs!$F$27+J17*Inputs!$F$28+K17*Inputs!$F$29+L17*Inputs!$F$30+M17*Inputs!$F$31+N17*Inputs!$F$32+O17*Inputs!$F$33+P17*Inputs!$F$34+Q17*Inputs!$F$35+R17*Inputs!$F$36,2) | T17: =ROUND(S17/100000,2)
... A41: 36 | B41: 47331 | C41: =IF(A41<Inputs!$B$6,0,INDEX(Inputs!$B$41:$B$64,MIN(A41-Inputs!$B$6+1,24))*Inputs!$B$8) | D41: =IF(C41=0,0,IF(A41<Inputs!$G$7,ROUND(C41*25%,0),ROUND(C41*Inputs!$E$5,0))) | E41: =IF(C41=0,0,IF(A41<Inputs!$G$7,C41-D41,ROUND(C41*Inputs!$E$6,0))) | F41: =C41-D41-E41 | G41: =ROUND((D41*Inputs!$C$25+E41*Inputs!$D$25+F41*Inputs!$E$25)*(1+Inputs!$B$9),2) | H41: =ROUND((D41*Inputs!$C$26+E41*Inputs!$D$26+F41*Inputs!$E$26)*(1+Inputs!$B$9),2) | I41: =ROUND((D41*Inputs!$C$27+E41*Inputs!$D$27+F41*Inputs!$E$27)*(1+Inputs!$B$9),2) | J41: =ROUND((D41*Inputs!$C$28+E41*Inputs!$D$28+F41*Inputs!$E$28)*(1+Inputs!$B$9),2) | K41: =ROUND((D41*Inputs!$C$29+E41*Inputs!$D$29+F41*Inputs!$E$29)*(1+Inputs!$B$9),2) | L41: =ROUND((D41*Inputs!$C$30+E41*Inputs!$D$30+F41*Inputs!$E$30)*(1+Inputs!$B$9),2) | M41: =ROUND((D41*Inputs!$C$31+E41*Inputs!$D$31+F41*Inputs!$E$31)*(1+Inputs!$B$9),2) | N41: =ROUND((D41*Inputs!$C$32+E41*Inputs!$D$32+F41*Inputs!$E$32)*(1+Inputs!$B$9),2) | O41: =ROUND((D41*Inputs!$C$33+E41*Inputs!$D$33+F41*Inputs!$E$33)*(1+Inputs!$B$9),2) | P41: =ROUND((D41*Inputs!$C$34+E41*Inputs!$D$34+F41*Inputs!$E$34)*(1+Inputs!$B$9),2) | Q41: =ROUND((D41*Inputs!$C$35+E41*Inputs!$D$35+F41*Inputs!$E$35)*(1+Inputs!$B$9),2) | R41: =ROUND((D41*Inputs!$C$36+E41*Inputs!$D$36+F41*Inputs!$E$36)*(1+Inputs!$B$9),2) | S41: =ROUND(G41*Inputs!$F$25+H41*Inputs!$F$26+I41*Inputs!$F$27+J41*Inputs!$F$28+K41*Inputs!$F$29+L41*Inputs!$F$30+M41*Inputs!$F$31+N41*Inputs!$F$32+O41*Inputs!$F$33+P41*Inputs!$F$34+Q41*Inputs!$F$35+R41*Inputs!$F$36,2) | T41: =ROUND(S41/100000,2)
A42: 36M TOTAL | C42: =SUM(C6:C41) | D42: =SUM(D6:D41) | E42: =SUM(E6:E41) | F42: =SUM(F6:F41) | G42: =SUM(G6:G41) | H42: =SUM(H6:H41) | I42: =SUM(I6:I41) | J42: =SUM(J6:J41) | ... T42: =SUM(T6:T41)

Sheet Component Catalogue
A1: VYNDI Component Catalogue · 66 controlled catalogue items
A2: Catalogue/pricing only. Physical stock remains movement-ledger truth. Procurement parameters P:T are editable planning controls.
A4: Item ID | B4: Category | C4: Subcategory | D4: Brand | E4: Model | F4: Detail | G4: SKU | H4: Unit Price ₹ | I4: Opening Stock | J4: MSL / Reorder | K4: Longitude | L4: Latitude | M4: Altitude | N4: Source | O4: Control Note | P4: Lead Time (mo) | Q4: MOQ | R4: Order Multiple | S4: Payment Lag (mo) | T4: Preferred Supplier | U4: Safety Stock | V4: Supplier Part No. | W4: Currency | X4: GST Rate | Y4: Payment Terms | Z4: Quality Inspection Required? | AA4: Lot Controlled? | AB4: Serial Controlled?
A5: gs-tiagra-4700 | B5: groupset | C5: Mechanical | D5: Shimano | E5: Tiagra 4700 | F5: 2x10 mechanical | G5: SHI-TIA-4700 | H5: 45000 | I5: 0 | J5: 2 | K5: Yes | L5: No | M5: No | N5: GitHub src/lib/data/inventory.ts | O5: Opening stock forced to 0; catalogue is not ledger truth | P5: 2 | Q5: 1 | R5: 1 | S5: 1 | U5: =J5 | W5: INR | Z5: No | AA5: No | AB5: No
A6: gs-105-r7000 | B6: groupset | C6: Mechanical | D6: Shimano | E6: 105 R7000 | F6: 2x11 mechanical | G6: SHI-105-R7000 | H6: 70000 | I6: 0 | J6: 2 | K6: Yes | L6: Yes | M6: No | N6: GitHub src/lib/data/inventory.ts | O6: Opening stock forced to 0; catalogue is not ledger truth | P6: 2 | Q6: 1 | R6: 1 | S6: 1 | U6: =J6 | W6: INR | Z6: No | AA6: No | AB6: No
A7: gs-105-r7150 | B7: groupset | C7: Electronic | D7: Shimano | E7: 105 R7150 Di2 | F7: 2x12 electronic | G7: SHI-105-R7150 | H7: 138000 | I7: 0 | J7: 1 | K7: No | L7: Yes | M7: No | N7: GitHub src/lib/data/inventory.ts | O7: Opening stock forced to 0; catalogue is not ledger truth | P7: 2 | Q7: 1 | R7: 1 | S7: 1 | U7: =J7 | W7: INR | Z7: No | AA7: No | AB7: No
A8: gs-ultegra-r8170 | B8: groupset | C8: Electronic | D8: Shimano | E8: Ultegra R8170 Di2 | F8: 2x12 electronic | G8: SHI-ULT-R8170 | H8: 210000 | I8: 0 | J8: 1 | K8: No | L8: Yes | M8: Yes | N8: GitHub src/lib/data/inventory.ts | O8: Opening stock forced to 0; catalogue is not ledger truth | P8: 2 | Q8: 1 | R8: 1 | S8: 1 | U8: =J8 | W8: INR | Z8: No | AA8: No | AB8: No
A9: gs-duraace-r9270 | B9: groupset | C9: Electronic | D9: Shimano | E9: Dura-Ace R9270 Di2 | F9: 2x12 electronic flagship | G9: SHI-DA-R9270 | H9: 353000 | I9: 0 | J9: 1 | K9: No | L9: No | M9: Yes | N9: GitHub src/lib/data/inventory.ts | O9: Opening stock forced to 0; catalogue is not ledger truth | P9: 2 | Q9: 1 | R9: 1 | S9: 1 | U9: =J9 | W9: INR | Z9: No | AA9: No | AB9: No
A10: gs-rival-axs | B10: groupset | C10: Electronic | D10: SRAM | E10: Rival AXS | F10: 2x12 wireless electronic | G10: SRAM-RIV-AXS | H10: 175000 | I10: 0 | J10: 1 | K10: No | L10: Yes | M10: No | N10: GitHub src/lib/data/inventory.ts | O10: Opening stock forced to 0; catalogue is not ledger truth | P10: 2 | Q10: 1 | R10: 1 | S10: 1 | U10: =J10 | W10: INR | Z10: No | AA10: No | AB10: No
A11: gs-force-axs | B11: groupset | C11: Electronic | D11: SRAM | E11: Force AXS | F11: 2x12 wireless electronic | G11: SRAM-FORCE-AXS | H11: 250000 | I11: 0 | J11: 1 | K11: No | L11: Yes | M11: Yes | N11: GitHub src/lib/data/inventory.ts | O11: Opening stock forced to 0; catalogue is not ledger truth | P11: 2 | Q11: 1 | R11: 1 | S11: 1 | U11: =J11 | W11: INR | Z11: No | AA11: No | AB11: No
A12: gs-red-axs | B12: groupset | C12: Electronic | D12: SRAM | E12: RED AXS | F12: 2x12 wireless flagship | G12: SRAM-RED-AXS | H12: 380000 | I12: 0 | J12: 1 | K12: No | L12: No | M12: Yes | N12: GitHub src/lib/data/inventory.ts | O12: Opening stock forced to 0; catalogue is not ledger truth | P12: 2 | Q12: 1 | R12: 1 | S12: 1 | U12: =J12 | W12: INR | Z12: No | AA12: No | AB12: No
A13: ws-alloy | B13: wheelset | C13: Aluminium | D13: Performance | E13: Performance Alloy | F13: Training / everyday | G13: WH-ALLOY-01 | H13: 30000 | I13: 0 | J13: 3 | K13: Yes | L13: No | M13: No | N13: GitHub src/lib/data/inventory.ts | O13: Opening stock forced to 0; catalogue is not ledger truth | P13: 2 | Q13: 1 | R13: 1 | S13: 1 | U13: =J13 | W13: INR | Z13: No | AA13: No | AB13: No
A14: ws-alloy-30 | B14: wheelset | C14: Aluminium | D14: Light Alloy | E14: 30 Tubeless | F14: 30 mm tubeless-ready | G14: WH-ALLOY-30 | H14: 45000 | I14: 0 | J14: 2 | K14: Yes | L14: Yes | M14: No | N14: GitHub src/lib/data/inventory.ts | O14: Opening stock forced to 0; catalogue is not ledger truth | P14: 2 | Q14: 1 | R14: 1 | S14: 1 | U14: =J14 | W14: INR | Z14: No | AA14: No | AB14: No
A15: ws-alloy-35 | B15: wheelset | C15: Aluminium | D15: Vision | E15: Team 35 | F15: 35 mm alloy aero | G15: WH-VIS-TEAM35 | H15: 55000 | I15: 0 | J15: 1 | K15: Yes | L15: Yes | M15: No | N15: GitHub src/lib/data/inventory.ts | O15: Opening stock forced to 0; catalogue is not ledger truth | P15: 2 | Q15: 1 | R15: 1 | S15: 1 | U15: =J15 | W15: INR | Z15: No | AA15: No | AB15: No
A16: ws-carbon-38 | B16: wheelset | C16: Carbon Aero | D16: Zipp | E16: 303 S | F16: 40 mm carbon tubeless-ready | G16: WH-ZIP-303S | H16: 85000 | I16: 0 | J16: 1 | K16: No | L16: Yes | M16: No | N16: GitHub src/lib/data/inventory.ts | O16: Opening stock forced to 0; catalogue is not ledger truth | P16: 2 | Q16: 1 | R16: 1 | S16: 1 | U16: =J16 | W16: INR | Z16: No | AA16: No | AB16: No
... A71: rm-frame-al-oem | B71: raw-material | C71: Frameset | D71: OEM | E71: Aluminium/OEM frameset | F71: Purchased frameset | G71: FRAMESET-AL-OEM | H71: 45000 | I71: 0 | J71: 0 | K71: Yes | L71: No | M71: No | N71: Inputs!25 | O71: Canonical BOM raw item | P71: 2 | Q71: 1 | R71: 1 | S71: 1 | U71: =J71 | W71: INR | Z71: No | AA71: No | AB71: No
A72: rm-t700 | B72: raw-material | C72: Prepreg | E72: T700 prepreg | F72: Carbon prepreg | G72: RM-T700-PREPREG | H72: 3500 | I72: 0 | J72: 0 | K72: No | L72: Yes | M72: Yes | N72: Inputs!26 | O72: Engineering-controlled | P72: 1 | Q72: 1 | R72: 1 | S72: 1 | U72: =J72 | W72: INR | Z72: No | AA72: No | AB72: No
A73: rm-t800 | B73: raw-material | C73: Prepreg | E73: T800 prepreg | F73: Carbon prepreg | G73: RM-T800-PREPREG | H73: 6500 | I73: 0 | J73: 0 | K73: No | L73: Yes | M73: Yes | N73: Inputs!27 | O73: Engineering-controlled | P73: 1 | Q73: 1 | R73: 1 | S73: 1 | U73: =J73 | W73: INR | Z73: No | AA73: No | AB73: No
A74: rm-resin | B74: raw-material | C74: Resin | E74: Resin & bonding system | F74: Resin / adhesive | G74: RM-RESIN-BOND | H74: 1800 | I74: 0 | J74: 0 | K74: No | L74: Yes | M74: Yes | N74: Inputs!28 | O74: Engineering-controlled | P74: 1 | Q74: 1 | R74: 1 | S74: 1 | U74: =J74 | W74: INR | Z74: No | AA74: No | AB74: No
A75: rm-paint | B75: raw-material | C75: Finishing | E75: Paint & clear coat | F75: Paint system | G75: RM-PAINT-CLEAR | H75: 2200 | I75: 0 | J75: 0 | K75: Yes | L75: Yes | M75: Yes | N75: Inputs!29 | O75: Engineering-controlled | P75: 1 | Q75: 1 | R75: 1 | S75: 1 | U75: =J75 | W75: INR | Z75: No | AA75: No | AB75: No
A76: pkg-kit | B76: packaging | C76: Shipment | E76: Packaging kit | F76: Shipment packaging | G76: PKG-KIT | H76: 2500 | I76: 0 | J76: 0 | K76: Yes | L76: Yes | M76: Yes | N76: Inputs!36 | O76: Canonical BOM packaging | P76: 1 | Q76: 1 | R76: 1 | S76: 1 | U76: =J76 | W76: INR | Z76: No | AA76: No | AB76: No

Sheet Inventory Movements
A1: Inventory Movement Ledger · FIFO-supporting source of physical stock truth
A3: Movement ID | B3: Date | C3: SKU | D3: Type | E3: Qty In | F3: Qty Out | G3: Unit Cost ₹ | H3: Lot / PO | I3: Job Card | J3: Quality Status | K3: Posted? | L3: Evidence / Note | M3: Truth Class | N3: Revision | O3: Source Ref | P3: Posted At | Q3: Posted By
A4: =IF(C4="","","MOV-"&TEXT(ROW()-3,"0000")) | J4: Released | K4: No | M4: =IF(A4="","",IF(K4="Yes","Actual","Plan")) | N4: 1
A5: =IF(C5="","","MOV-"&TEXT(ROW()-3,"0000")) | J5: Released | K5: No | M5: =IF(A5="","",IF(K5="Yes","Actual","Plan")) | N5: 1
A6: =IF(C6="","","MOV-"&TEXT(ROW()-3,"0000")) | J6: Released | K6: No | M6: =IF(A6="","",IF(K6="Yes","Actual","Plan")) | N6: 1
A7: =IF(C7="","","MOV-"&TEXT(ROW()-3,"0000")) | J7: Released | K7: No | M7: =IF(A7="","",IF(K7="Yes","Actual","Plan")) | N7: 1
A8: =IF(C8="","","MOV-"&TEXT(ROW()-3,"0000")) | J8: Released | K8: No | M8: =IF(A8="","",IF(K8="Yes","Actual","Plan")) | N8: 1
A9: =IF(C9="","","MOV-"&TEXT(ROW()-3,"0000")) | J9: Released | K9: No | M9: =IF(A9="","",IF(K9="Yes","Actual","Plan")) | N9: 1
A10: =IF(C10="","","MOV-"&TEXT(ROW()-3,"0000")) | J10: Released | K10: No | M10: =IF(A10="","",IF(K10="Yes","Actual","Plan")) | N10: 1
A11: =IF(C11="","","MOV-"&TEXT(ROW()-3,"0000")) | J11: Released | K11: No | M11: =IF(A11="","",IF(K11="Yes","Actual","Plan")) | N11: 1
A12: =IF(C12="","","MOV-"&TEXT(ROW()-3,"0000")) | J12: Released | K12: No | M12: =IF(A12="","",IF(K12="Yes","Actual","Plan")) | N12: 1
A13: =IF(C13="","","MOV-"&TEXT(ROW()-3,"0000")) | J13: Released | K13: No | M13: =IF(A13="","",IF(K13="Yes","Actual","Plan")) | N13: 1
A14: =IF(C14="","","MOV-"&TEXT(ROW()-3,"0000")) | J14: Released | K14: No | M14: =IF(A14="","",IF(K14="Yes","Actual","Plan")) | N14: 1
A15: =IF(C15="","","MOV-"&TEXT(ROW()-3,"0000")) | J15: Released | K15: No | M15: =IF(A15="","",IF(K15="Yes","Actual","Plan")) | N15: 1
... A203: =IF(C203="","","MOV-"&TEXT(ROW()-3,"0000")) | J203: Released | K203: No | M203: =IF(A203="","",IF(K203="Yes","Actual","Plan")) | N203: 1

Sheet Reservations
A1: Reservation Ledger · committed demand allocation before FIFO issue
A3: Reservation ID | B3: Order ID | C3: Order Rev | D3: Job Card | E3: SKU | F3: Qty Required | G3: Qty Reserved | H3: Status | I3: Release / Issue Ref | J3: Note | K3: Truth Class | L3: Revision | M3: Created At | N3: Approved By
A4: =IF(E4="","","RES-"&TEXT(ROW()-3,"0000")) | H4: Draft | K4: =IF(A4="","",IF(H4="Consumed","Actual",IF(H4="Active","Committed","Plan"))) | L4: 1
A5: =IF(E5="","","RES-"&TEXT(ROW()-3,"0000")) | H5: Draft | K5: =IF(A5="","",IF(H5="Consumed","Actual",IF(H5="Active","Committed","Plan"))) | L5: 1
A6: =IF(E6="","","RES-"&TEXT(ROW()-3,"0000")) | H6: Draft | K6: =IF(A6="","",IF(H6="Consumed","Actual",IF(H6="Active","Committed","Plan"))) | L6: 1
A7: =IF(E7="","","RES-"&TEXT(ROW()-3,"0000")) | H7: Draft | K7: =IF(A7="","",IF(H7="Consumed","Actual",IF(H7="Active","Committed","Plan"))) | L7: 1
A8: =IF(E8="","","RES-"&TEXT(ROW()-3,"0000")) | H8: Draft | K8: =IF(A8="","",IF(H8="Consumed","Actual",IF(H8="Active","Committed","Plan"))) | L8: 1
A9: =IF(E9="","","RES-"&TEXT(ROW()-3,"0000")) | H9: Draft | K9: =IF(A9="","",IF(H9="Consumed","Actual",IF(H9="Active","Committed","Plan"))) | L9: 1
A10: =IF(E10="","","RES-"&TEXT(ROW()-3,"0000")) | H10: Draft | K10: =IF(A10="","",IF(H10="Consumed","Actual",IF(H10="Active","Committed","Plan"))) | L10: 1
A11: =IF(E11="","","RES-"&TEXT(ROW()-3,"0000")) | H11: Draft | K11: =IF(A11="","",IF(H11="Consumed","Actual",IF(H11="Active","Committed","Plan"))) | L11: 1
A12: =IF(E12="","","RES-"&TEXT(ROW()-3,"0000")) | H12: Draft | K12: =IF(A12="","",IF(H12="Consumed","Actual",IF(H12="Active","Committed","Plan"))) | L12: 1
A13: =IF(E13="","","RES-"&TEXT(ROW()-3,"0000")) | H13: Draft | K13: =IF(A13="","",IF(H13="Consumed","Actual",IF(H13="Active","Committed","Plan"))) | L13: 1
A14: =IF(E14="","","RES-"&TEXT(ROW()-3,"0000")) | H14: Draft | K14: =IF(A14="","",IF(H14="Consumed","Actual",IF(H14="Active","Committed","Plan"))) | L14: 1
A15: =IF(E15="","","RES-"&TEXT(ROW()-3,"0000")) | H15: Draft | K15: =IF(A15="","",IF(H15="Consumed","Actual",IF(H15="Active","Committed","Plan"))) | L15: 1
... A103: =IF(E103="","","RES-"&TEXT(ROW()-3,"0000")) | H103: Draft | K103: =IF(A103="","",IF(H103="Consumed","Actual",IF(H103="Active","Committed","Plan"))) | L103: 1

Sheet Master Inventory
A1: Master Inventory · canonical balance, ATP, MSL and procurement signal
A3: SKU | B3: Category | C3: Item | D3: Unit Price ₹ | E3: MSL | F3: Receipts | G3: Issues | H3: On Hand | I3: Active Reservations | J3: ATP | K3: Shortage to MSL | L3: Health | M3: Suggested Order Qty | N3: Inventory Value ₹
A4: ='Component Catalogue'!G5 | B4: ='Component Catalogue'!B5 | C4: ='Component Catalogue'!E5 | D4: ='Component Catalogue'!H5 | E4: ='Component Catalogue'!J5 | F4: =SUMIFS('Inventory Movements'!$E$4:$E$5003,'Inventory Movements'!$C$4:$C$5003,$A4,'Inventory Movements'!$K$4:$K$5003,"Yes",'Inventory Movements'!$J$4:$J$5003,"Released") | G4: =SUMIFS('Inventory Movements'!$F$4:$F$5003,'Inventory Movements'!$C$4:$C$5003,$A4,'Inventory Movements'!$K$4:$K$5003,"Yes") | H4: =F4-G4 | I4: =SUMIFS(Reservations!$G$4:$G$2003,Reservations!$E$4:$E$2003,$A4,Reservations!$H$4:$H$2003,"Active") | J4: =MAX(0,H4-I4) | K4: =MAX(0,E4-J4) | L4: =IF(J4=0,"OUT",IF(J4<E4,"LOW","OK")) | M4: =K4 | N4: =H4*D4
A5: ='Component Catalogue'!G6 | B5: ='Component Catalogue'!B6 | C5: ='Component Catalogue'!E6 | D5: ='Component Catalogue'!H6 | E5: ='Component Catalogue'!J6 | F5: =SUMIFS('Inventory Movements'!$E$4:$E$5003,'Inventory Movements'!$C$4:$C$5003,$A5,'Inventory Movements'!$K$4:$K$5003,"Yes",'Inventory Movements'!$J$4:$J$5003,"Released") | G5: =SUMIFS('Inventory Movements'!$F$4:$F$5003,'Inventory Movements'!$C$4:$C$5003,$A5,'Inventory Movements'!$K$4:$K$5003,"Yes") | H5: =F5-G5 | I5: =SUMIFS(Reservations!$G$4:$G$2003,Reservations!$E$4:$E$2003,$A5,Reservations!$H$4:$H$2003,"Active") | J5: =MAX(0,H5-I5) | K5: =MAX(0,E5-J5) | L5: =IF(J5=0,"OUT",IF(J5<E5,"LOW","OK")) | M5: =K5 | N5: =H5*D5
A6: ='Component Catalogue'!G7 | B6: ='Component Catalogue'!B7 | C6: ='Component Catalogue'!E7 | D6: ='Component Catalogue'!H7 | E6: ='Component Catalogue'!J7 | F6: =SUMIFS('Inventory Movements'!$E$4:$E$5003,'Inventory Movements'!$C$4:$C$5003,$A6,'Inventory Movements'!$K$4:$K$5003,"Yes",'Inventory Movements'!$J$4:$J$5003,"Released") | G6: =SUMIFS('Inventory Movements'!$F$4:$F$5003,'Inventory Movements'!$C$4:$C$5003,$A6,'Inventory Movements'!$K$4:$K$5003,"Yes") | H6: =F6-G6 | I6: =SUMIFS(Reservations!$G$4:$G$2003,Reservations!$E$4:$E$2003,$A6,Reservations!$H$4:$H$2003,"Active") | J6: =MAX(0,H6-I6) | K6: =MAX(0,E6-J6) | L6: =IF(J6=0,"OUT",IF(J6<E6,"LOW","OK")) | M6: =K6 | N6: =H6*D6
A7: ='Component Catalogue'!G8 | B7: ='Component Catalogue'!B8 | C7: ='Component Catalogue'!E8 | D7: ='Component Catalogue'!H8 | E7: ='Component Catalogue'!J8 | F7: =SUMIFS('Inventory Movements'!$E$4:$E$5003,'Inventory Movements'!$C$4:$C$5003,$A7,'Inventory Movements'!$K$4:$K$5003,"Yes",'Inventory Movements'!$J$4:$J$5003,"Released") | G7: =SUMIFS('Inventory Movements'!$F$4:$F$5003,'Inventory Movements'!$C$4:$C$5003,$A7,'Inventory Movements'!$K$4:$K$5003,"Yes") | H7: =F7-G7 | I7: =SUMIFS(Reservations!$G$4:$G$2003,Reservations!$E$4:$E$2003,$A7,Reservations!$H$4:$H$2003,"Active") | J7: =MAX(0,H7-I7) | K7: =MAX(0,E7-J7) | L7: =IF(J7=0,"OUT",IF(J7<E7,"LOW","OK")) | M7: =K7 | N7: =H7*D7
A8: ='Component Catalogue'!G9 | B8: ='Component Catalogue'!B9 | C8: ='Component Catalogue'!E9 | D8: ='Component Catalogue'!H9 | E8: ='Component Catalogue'!J9 | F8: =SUMIFS('Inventory Movements'!$E$4:$E$5003,'Inventory Movements'!$C$4:$C$5003,$A8,'Inventory Movements'!$K$4:$K$5003,"Yes",'Inventory Movements'!$J$4:$J$5003,"Released") | G8: =SUMIFS('Inventory Movements'!$F$4:$F$5003,'Inventory Movements'!$C$4:$C$5003,$A8,'Inventory Movements'!$K$4:$K$5003,"Yes") | H8: =F8-G8 | I8: =SUMIFS(Reservations!$G$4:$G$2003,Reservations!$E$4:$E$2003,$A8,Reservations!$H$4:$H$2003,"Active") | J8: =MAX(0,H8-I8) | K8: =MAX(0,E8-J8) | L8: =IF(J8=0,"OUT",IF(J8<E8,"LOW","OK")) | M8: =K8 | N8: =H8*D8
A9: ='Component Catalogue'!G10 | B9: ='Component Catalogue'!B10 | C9: ='Component Catalogue'!E10 | D9: ='Component Catalogue'!H10 | E9: ='Component Catalogue'!J10 | F9: =SUMIFS('Inventory Movements'!$E$4:$E$5003,'Inventory Movements'!$C$4:$C$5003,$A9,'Inventory Movements'!$K$4:$K$5003,"Yes",'Inventory Movements'!$J$4:$J$5003,"Released") | G9: =SUMIFS('Inventory Movements'!$F$4:$F$5003,'Inventory Movements'!$C$4:$C$5003,$A9,'Inventory Movements'!$K$4:$K$5003,"Yes") | H9: =F9-G9 | I9: =SUMIFS(Reservations!$G$4:$G$2003,Reservations!$E$4:$E$2003,$A9,Reservations!$H$4:$H$2003,"Active") | J9: =MAX(0,H9-I9) | K9: =MAX(0,E9-J9) | L9: =IF(J9=0,"OUT",IF(J9<E9,"LOW","OK")) | M9: =K9 | N9: =H9*D9
A10: ='Component Catalogue'!G11 | B10: ='Component Catalogue'!B11 | C10: ='Component Catalogue'!E11 | D10: ='Component Catalogue'!H11 | E10: ='Component Catalogue'!J11 | F10: =SUMIFS('Inventory Movements'!$E$4:$E$5003,'Inventory Movements'!$C$4:$C$5003,$A10,'Inventory Movements'!$K$4:$K$5003,"Yes",'Inventory Movements'!$J$4:$J$5003,"Released") | G10: =SUMIFS('Inventory Movements'!$F$4:$F$5003,'Inventory Movements'!$C$4:$C$5003,$A10,'Inventory Movements'!$K$4:$K$5003,"Yes") | H10: =F10-G10 | I10: =SUMIFS(Reservations!$G$4:$G$2003,Reservations!$E$4:$E$2003,$A10,Reservations!$H$4:$H$2003,"Active") | J10: =MAX(0,H10-I10) | K10: =MAX(0,E10-J10) | L10: =IF(J10=0,"OUT",IF(J10<E10,"LOW","OK")) | M10: =K10 | N10: =H10*D10
A11: ='Component Catalogue'!G12 | B11: ='Component Catalogue'!B12 | C11: ='Component Catalogue'!E12 | D11: ='Component Catalogue'!H12 | E11: ='Component Catalogue'!J12 | F11: =SUMIFS('Inventory Movements'!$E$4:$E$5003,'Inventory Movements'!$C$4:$C$5003,$A11,'Inventory Movements'!$K$4:$K$5003,"Yes",'Inventory Movements'!$J$4:$J$5003,"Released") | G11: =SUMIFS('Inventory Movements'!$F$4:$F$5003,'Inventory Movements'!$C$4:$C$5003,$A11,'Inventory Movements'!$K$4:$K$5003,"Yes") | H11: =F11-G11 | I11: =SUMIFS(Reservations!$G$4:$G$2003,Reservations!$E$4:$E$2003,$A11,Reservations!$H$4:$H$2003,"Active") | J11: =MAX(0,H11-I11) | K11: =MAX(0,E11-J11) | L11: =IF(J11=0,"OUT",IF(J11<E11,"LOW","OK")) | M11: =K11 | N11: =H11*D11
A12: ='Component Catalogue'!G13 | B12: ='Component Catalogue'!B13 | C12: ='Component Catalogue'!E13 | D12: ='Component Catalogue'!H13 | E12: ='Component Catalogue'!J13 | F12: =SUMIFS('Inventory Movements'!$E$4:$E$5003,'Inventory Movements'!$C$4:$C$5003,$A12,'Inventory Movements'!$K$4:$K$5003,"Yes",'Inventory Movements'!$J$4:$J$5003,"Released") | G12: =SUMIFS('Inventory Movements'!$F$4:$F$5003,'Inventory Movements'!$C$4:$C$5003,$A12,'Inventory Movements'!$K$4:$K$5003,"Yes") | H12: =F12-G12 | I12: =SUMIFS(Reservations!$G$4:$G$2003,Reservations!$E$4:$E$2003,$A12,Reservations!$H$4:$H$2003,"Active") | J12: =MAX(0,H12-I12) | K12: =MAX(0,E12-J12) | L12: =IF(J12=0,"OUT",IF(J12<E12,"LOW","OK")) | M12: =K12 | N12: =H12*D12
A13: ='Component Catalogue'!G14 | B13: ='Component Catalogue'!B14 | C13: ='Component Catalogue'!E14 | D13: ='Component Catalogue'!H14 | E13: ='Component Catalogue'!J14 | F13: =SUMIFS('Inventory Movements'!$E$4:$E$5003,'Inventory Movements'!$C$4:$C$5003,$A13,'Inventory Movements'!$K$4:$K$5003,"Yes",'Inventory Movements'!$J$4:$J$5003,"Released") | G13: =SUMIFS('Inventory Movements'!$F$4:$F$5003,'Inventory Movements'!$C$4:$C$5003,$A13,'Inventory Movements'!$K$4:$K$5003,"Yes") | H13: =F13-G13 | I13: =SUMIFS(Reservations!$G$4:$G$2003,Reservations!$E$4:$E$2003,$A13,Reservations!$H$4:$H$2003,"Active") | J13: =MAX(0,H13-I13) | K13: =MAX(0,E13-J13) | L13: =IF(J13=0,"OUT",IF(J13<E13,"LOW","OK")) | M13: =K13 | N13: =H13*D13
A14: ='Component Catalogue'!G15 | B14: ='Component Catalogue'!B15 | C14: ='Component Catalogue'!E15 | D14: ='Component Catalogue'!H15 | E14: ='Component Catalogue'!J15 | F14: =SUMIFS('Inventory Movements'!$E$4:$E$5003,'Inventory Movements'!$C$4:$C$5003,$A14,'Inventory Movements'!$K$4:$K$5003,"Yes",'Inventory Movements'!$J$4:$J$5003,"Released") | G14: =SUMIFS('Inventory Movements'!$F$4:$F$5003,'Inventory Movements'!$C$4:$C$5003,$A14,'Inventory Movements'!$K$4:$K$5003,"Yes") | H14: =F14-G14 | I14: =SUMIFS(Reservations!$G$4:$G$2003,Reservations!$E$4:$E$2003,$A14,Reservations!$H$4:$H$2003,"Active") | J14: =MAX(0,H14-I14) | K14: =MAX(0,E14-J14) | L14: =IF(J14=0,"OUT",IF(J14<E14,"LOW","OK")) | M14: =K14 | N14: =H14*D14
A15: ='Component Catalogue'!G16 | B15: ='Component Catalogue'!B16 | C15: ='Component Catalogue'!E16 | D15: ='Component Catalogue'!H16 | E15: ='Component Catalogue'!J16 | F15: =SUMIFS('Inventory Movements'!$E$4:$E$5003,'Inventory Movements'!$C$4:$C$5003,$A15,'Inventory Movements'!$K$4:$K$5003,"Yes",'Inventory Movements'!$J$4:$J$5003,"Released") | G15: =SUMIFS('Inventory Movements'!$F$4:$F$5003,'Inventory Movements'!$C$4:$C$5003,$A15,'Inventory Movements'!$K$4:$K$5003,"Yes") | H15: =F15-G15 | I15: =SUMIFS(Reservations!$G$4:$G$2003,Reservations!$E$4:$E$2003,$A15,Reservations!$H$4:$H$2003,"Active") | J15: =MAX(0,H15-I15) | K15: =MAX(0,E15-J15) | L15: =IF(J15=0,"OUT",IF(J15<E15,"LOW","OK")) | M15: =K15 | N15: =H15*D15
... A75: ='Component Catalogue'!G76 | B75: ='Component Catalogue'!B76 | C75: ='Component Catalogue'!E76 | D75: ='Component Catalogue'!H76 | E75: ='Component Catalogue'!J76 | F75: =SUMIFS('Inventory Movements'!$E$4:$E$5003,'Inventory Movements'!$C$4:$C$5003,$A75,'Inventory Movements'!$K$4:$K$5003,"Yes",'Inventory Movements'!$J$4:$J$5003,"Released") | G75: =SUMIFS('Inventory Movements'!$F$4:$F$5003,'Inventory Movements'!$C$4:$C$5003,$A75,'Inventory Movements'!$K$4:$K$5003,"Yes") | H75: =F75-G75 | I75: =SUMIFS(Reservations!$G$4:$G$2003,Reservations!$E$4:$E$2003,$A75,Reservations!$H$4:$H$2003,"Active") | J75: =MAX(0,H75-I75) | K75: =MAX(0,E75-J75) | L75: =IF(J75=0,"OUT",IF(J75<E75,"LOW","OK")) | M75: =K75 | N75: =H75*D75

Sheet BOM Mapping
A1: Approved BOM → SKU Mapping · planning defaults for Longitude / Latitude / Altitude
A2: CANONICAL BOM AUTHORITY. J:L hold model-specific Qty/Bike; MRP/procurement/job material logic must reference this sheet only.
A3: BOM Line | B3: Category | C3: Longitude SKU | D3: Latitude SKU | E3: Altitude SKU | F3: Qty / bike | G3: Unit | H3: Revision | I3: Status | J3: Qty Longitude | K3: Qty Latitude | L3: Qty Altitude
A4: Drivetrain | B4: groupset | C4: SHI-105-R7000 | D4: SHI-105-R7150 | E4: SHI-ULT-R8170 | F4: 1 | G4: set | H4: BOM-PLAN-1 | I4: Approved | J4: =F4 | K4: =F4 | L4: =F4
A5: Wheelset | B5: wheelset | C5: WH-ALLOY-30 | D5: WH-ZIP-303S | E5: WH-CARB-50 | F5: 1 | G5: set | H5: BOM-PLAN-1 | I5: Approved | J5: =F5 | K5: =F5 | L5: =F5
A6: Tyres | B6: tyre | C6: TY-RUBINO-PRO-PAIR | D6: TY-GP5000-PAIR | E6: TY-CORSA-PRO-PAIR | F6: 1 | G6: pair | H6: BOM-PLAN-1 | I6: Approved | J6: =F6 | K6: =F6 | L6: =F6
A7: Handlebar | B7: handlebar | C7: HB-AL-420 | D7: HB-CB-420 | E7: HB-CB-420 | F7: 1 | G7: ea | H7: BOM-PLAN-1 | I7: Approved | J7: =F7 | K7: =F7 | L7: =F7
A8: Stem | B8: stem | C8: ST-AL-090 | D8: ST-AL-100 | E8: ST-INT-100 | F8: 1 | G8: ea | H8: BOM-PLAN-1 | I8: Approved | J8: =F8 | K8: =F8 | L8: =F8
A9: Saddle | B9: saddle | C9: SD-M-BL | D9: SD-M-NL | E9: SD-M-NS | F9: 1 | G9: ea | H9: BOM-PLAN-1 | I9: Approved | J9: =F9 | K9: =F9 | L9: =F9
A10: Thru axle | B10: thruaxle | C10: TA-ROAD-CORE | D10: TA-ROAD-CORE | E10: TA-TI-ROAD | F10: 1 | G10: set | H10: BOM-PLAN-1 | I10: Approved | J10: =F10 | K10: =F10 | L10: =F10
A11: Bottom bracket | B11: bottom-bracket | C11: BB-BSA-ROAD | D11: BB-T47I-855 | E11: BB-T47I-855 | F11: 1 | G11: ea | H11: BOM-PLAN-1 | I11: Approved | J11: =F11 | K11: =F11 | L11: =F11
A12: Bottle cages | B12: bottle-cage | C12: BC-PLASTIC-01 | D12: BC-CARBON-01 | E12: BC-CARBON-01 | F12: 2 | G12: ea | H12: BOM-PLAN-1 | I12: Approved | J12: =F12 | K12: =F12 | L12: =F12
A13: Tool pouch | B13: tool-pouch | C13: TP-INTEGRATED-01 | D13: TP-INTEGRATED-01 | E13: TP-INTEGRATED-01 | F13: 1 | G13: ea | H13: BOM-PLAN-1 | I13: Approved | J13: =F13 | K13: =F13 | L13: =F13
A14: Computer bracket | B14: bracket | C14: BR-COMP-01 | D14: BR-COMP-01 | E14: BR-COMP-01 | F14: 1 | G14: ea | H14: BOM-PLAN-1 | I14: Approved | J14: =F14 | K14: =F14 | L14: =F14
A15: Light bracket | B15: bracket | C15: BR-LIGHT-01 | D15: BR-LIGHT-01 | E15: BR-LIGHT-01 | F15: 1 | G15: ea | H15: BOM-PLAN-1 | I15: Approved | J15: =F15 | K15: =F15 | L15: =F15
... A17: M6 fasteners | B17: fastener | C17: HW-ALLEN-M6 | D17: HW-ALLEN-M6 | E17: HW-ALLEN-M6 | F17: 2 | G17: ea | H17: BOM-PLAN-1 | I17: Approved | J17: =F17 | K17: =F17 | L17: =F17
A18: Aluminium/OEM frameset | B18: raw-material | C18: FRAMESET-AL-OEM | F18: 1 | G18: set | H18: BOM-PLAN-1 | I18: Approved | J18: 1 | K18: 0 | L18: 0
A19: T700 prepreg | B19: raw-material | D19: RM-T700-PREPREG | E19: RM-T700-PREPREG | F19: 1 | G19: kg | H19: BOM-PLAN-1 | I19: Approved | J19: 0 | K19: 3.2 | L19: 2.5
A20: T800 prepreg | B20: raw-material | D20: RM-T800-PREPREG | E20: RM-T800-PREPREG | F20: 1 | G20: kg | H20: BOM-PLAN-1 | I20: Approved | J20: 0 | K20: 1.3 | L20: 2.2
A21: Resin & bonding system | B21: raw-material | D21: RM-RESIN-BOND | E21: RM-RESIN-BOND | F21: 1 | G21: kg | H21: BOM-PLAN-1 | I21: Approved | J21: 0 | K21: 0.8 | L21: 0.9
A22: Paint & clear coat | B22: raw-material | C22: RM-PAINT-CLEAR | D22: RM-PAINT-CLEAR | E22: RM-PAINT-CLEAR | F22: 1 | G22: L | H22: BOM-PLAN-1 | I22: Approved | J22: 0.35 | K22: 0.35 | L22: 0.35
A23: Packaging kit | B23: packaging | C23: PKG-KIT | D23: PKG-KIT | E23: PKG-KIT | F23: 1 | G23: kit | H23: BOM-PLAN-1 | I23: Approved | J23: 1 | K23: 1 | L23: 1

Sheet Sales Orders
A1: Commercial Order Register · confirmed orders become committed demand
A3: Order ID | B3: Revision | C3: Order Date | D3: Customer | E3: Model | F3: Variant | G3: Qty | H3: Unit Price ₹L | I3: Order Value ₹L | J3: Status | K3: Required Date | L3: BOM Revision | M3: Job Release? | N3: Note | O3: Truth Class | P3: Created At | Q3: Approved At | R3: Approved By | S3: Source Ref
A4: =IF(E4="","","SO-"&TEXT(ROW()-3,"0000")) | B4: 1 | I4: =IF(OR(G4="",H4=""),0,G4*H4) | L4: BOM-PLAN-1 | M4: =IF(AND(J4="Confirmed",L4<>"",G4>0),"YES","NO") | O4: =IF(A4="","",IF(J4="Fulfilled","Actual",IF(J4="Confirmed","Committed","Plan")))
A5: =IF(E5="","","SO-"&TEXT(ROW()-3,"0000")) | B5: 1 | I5: =IF(OR(G5="",H5=""),0,G5*H5) | L5: BOM-PLAN-1 | M5: =IF(AND(J5="Confirmed",L5<>"",G5>0),"YES","NO") | O5: =IF(A5="","",IF(J5="Fulfilled","Actual",IF(J5="Confirmed","Committed","Plan")))
A6: =IF(E6="","","SO-"&TEXT(ROW()-3,"0000")) | B6: 1 | I6: =IF(OR(G6="",H6=""),0,G6*H6) | L6: BOM-PLAN-1 | M6: =IF(AND(J6="Confirmed",L6<>"",G6>0),"YES","NO") | O6: =IF(A6="","",IF(J6="Fulfilled","Actual",IF(J6="Confirmed","Committed","Plan")))
A7: =IF(E7="","","SO-"&TEXT(ROW()-3,"0000")) | B7: 1 | I7: =IF(OR(G7="",H7=""),0,G7*H7) | L7: BOM-PLAN-1 | M7: =IF(AND(J7="Confirmed",L7<>"",G7>0),"YES","NO") | O7: =IF(A7="","",IF(J7="Fulfilled","Actual",IF(J7="Confirmed","Committed","Plan")))
A8: =IF(E8="","","SO-"&TEXT(ROW()-3,"0000")) | B8: 1 | I8: =IF(OR(G8="",H8=""),0,G8*H8) | L8: BOM-PLAN-1 | M8: =IF(AND(J8="Confirmed",L8<>"",G8>0),"YES","NO") | O8: =IF(A8="","",IF(J8="Fulfilled","Actual",IF(J8="Confirmed","Committed","Plan")))
A9: =IF(E9="","","SO-"&TEXT(ROW()-3,"0000")) | B9: 1 | I9: =IF(OR(G9="",H9=""),0,G9*H9) | L9: BOM-PLAN-1 | M9: =IF(AND(J9="Confirmed",L9<>"",G9>0),"YES","NO") | O9: =IF(A9="","",IF(J9="Fulfilled","Actual",IF(J9="Confirmed","Committed","Plan")))
A10: =IF(E10="","","SO-"&TEXT(ROW()-3,"0000")) | B10: 1 | I10: =IF(OR(G10="",H10=""),0,G10*H10) | L10: BOM-PLAN-1 | M10: =IF(AND(J10="Confirmed",L10<>"",G10>0),"YES","NO") | O10: =IF(A10="","",IF(J10="Fulfilled","Actual",IF(J10="Confirmed","Committed","Plan")))
A11: =IF(E11="","","SO-"&TEXT(ROW()-3,"0000")) | B11: 1 | I11: =IF(OR(G11="",H11=""),0,G11*H11) | L11: BOM-PLAN-1 | M11: =IF(AND(J11="Confirmed",L11<>"",G11>0),"YES","NO") | O11: =IF(A11="","",IF(J11="Fulfilled","Actual",IF(J11="Confirmed","Committed","Plan")))
A12: =IF(E12="","","SO-"&TEXT(ROW()-3,"0000")) | B12: 1 | I12: =IF(OR(G12="",H12=""),0,G12*H12) | L12: BOM-PLAN-1 | M12: =IF(AND(J12="Confirmed",L12<>"",G12>0),"YES","NO") | O12: =IF(A12="","",IF(J12="Fulfilled","Actual",IF(J12="Confirmed","Committed","Plan")))
A13: =IF(E13="","","SO-"&TEXT(ROW()-3,"0000")) | B13: 1 | I13: =IF(OR(G13="",H13=""),0,G13*H13) | L13: BOM-PLAN-1 | M13: =IF(AND(J13="Confirmed",L13<>"",G13>0),"YES","NO") | O13: =IF(A13="","",IF(J13="Fulfilled","Actual",IF(J13="Confirmed","Committed","Plan")))
A14: =IF(E14="","","SO-"&TEXT(ROW()-3,"0000")) | B14: 1 | I14: =IF(OR(G14="",H14=""),0,G14*H14) | L14: BOM-PLAN-1 | M14: =IF(AND(J14="Confirmed",L14<>"",G14>0),"YES","NO") | O14: =IF(A14="","",IF(J14="Fulfilled","Actual",IF(J14="Confirmed","Committed","Plan")))
A15: =IF(E15="","","SO-"&TEXT(ROW()-3,"0000")) | B15: 1 | I15: =IF(OR(G15="",H15=""),0,G15*H15) | L15: BOM-PLAN-1 | M15: =IF(AND(J15="Confirmed",L15<>"",G15>0),"YES","NO") | O15: =IF(A15="","",IF(J15="Fulfilled","Actual",IF(J15="Confirmed","Committed","Plan")))
... A53: =IF(E53="","","SO-"&TEXT(ROW()-3,"0000")) | B53: 1 | I53: =IF(OR(G53="",H53=""),0,G53*H53) | L53: BOM-PLAN-1 | M53: =IF(AND(J53="Confirmed",L53<>"",G53>0),"YES","NO") | O53: =IF(A53="","",IF(J53="Fulfilled","Actual",IF(J53="Confirmed","Committed","Plan")))

Sheet Job Cards
A1: Production Job Cards · controlled release from confirmed order + approved BOM
A3: Job Card | B3: Order ID | C3: Order Rev | D3: Model | E3: Qty | F3: BOM Revision | G3: Release Status | H3: Material Status | I3: Planned Start | J3: Planned Finish | K3: Traveller ID | L3: Control Note | M3: Release Gate | N3: Plan Month | O3: Truth Class | P3: Revision | Q3: Created At | R3: Approved At | S3: Approved By
A4: =IF('Sales Orders'!M4="YES","JC-"&TEXT(ROW()-3,"0000"),"") | B4: =IF(A4="","",'Sales Orders'!A4) | C4: =IF(A4="","",'Sales Orders'!B4) | D4: =IF(A4="","",'Sales Orders'!E4) | E4: =IF(A4="","",'Sales Orders'!G4) | F4: =IF(A4="","",'Sales Orders'!L4) | G4: =IF(A4="","","RELEASED") | H4: =IF(A4="","",IF(COUNTIFS('Job Material Req'!$A:$A,A4,'Job Material Req'!$L:$L,"SHORTAGE")>0,"SHORTAGE",IF(COUNTIFS('Job Material Req'!$A:$A,A4,'Job Material Req'!$L:$L,"READY TO RESERVE")>0,"READY TO RESERVE","RESERVED"))) | K4: =IF(A4="","","TRV-"&TEXT(ROW()-3,"0000")) | L4: =IF(A4="","","Material status summarized from Job Material Req") | M4: =IF(A4="","",IF(H4<>"RESERVED","HOLD - MATERIAL","READY FOR RELEASE")) | N4: =IF(I4="","",12*(YEAR(I4)-YEAR(Inputs!$B$5))+MONTH(I4)-MONTH(Inputs!$B$5)+1) | O4: =IF(A4="","",IF(G4="Closed","Actual",IF(G4="Released","Committed","Plan"))) | P4: 1
A5: =IF('Sales Orders'!M5="YES","JC-"&TEXT(ROW()-3,"0000"),"") | B5: =IF(A5="","",'Sales Orders'!A5) | C5: =IF(A5="","",'Sales Orders'!B5) | D5: =IF(A5="","",'Sales Orders'!E5) | E5: =IF(A5="","",'Sales Orders'!G5) | F5: =IF(A5="","",'Sales Orders'!L5) | G5: =IF(A5="","","RELEASED") | H5: =IF(A5="","",IF(COUNTIFS('Job Material Req'!$A:$A,A5,'Job Material Req'!$L:$L,"SHORTAGE")>0,"SHORTAGE",IF(COUNTIFS('Job Material Req'!$A:$A,A5,'Job Material Req'!$L:$L,"READY TO RESERVE")>0,"READY TO RESERVE","RESERVED"))) | K5: =IF(A5="","","TRV-"&TEXT(ROW()-3,"0000")) | L5: =IF(A5="","","Material status summarized from Job Material Req") | M5: =IF(A5="","",IF(H5<>"RESERVED","HOLD - MATERIAL","READY FOR RELEASE")) | N5: =IF(I5="","",12*(YEAR(I5)-YEAR(Inputs!$B$5))+MONTH(I5)-MONTH(Inputs!$B$5)+1) | O5: =IF(A5="","",IF(G5="Closed","Actual",IF(G5="Released","Committed","Plan"))) | P5: 1
A6: =IF('Sales Orders'!M6="YES","JC-"&TEXT(ROW()-3,"0000"),"") | B6: =IF(A6="","",'Sales Orders'!A6) | C6: =IF(A6="","",'Sales Orders'!B6) | D6: =IF(A6="","",'Sales Orders'!E6) | E6: =IF(A6="","",'Sales Orders'!G6) | F6: =IF(A6="","",'Sales Orders'!L6) | G6: =IF(A6="","","RELEASED") | H6: =IF(A6="","",IF(COUNTIFS('Job Material Req'!$A:$A,A6,'Job Material Req'!$L:$L,"SHORTAGE")>0,"SHORTAGE",IF(COUNTIFS('Job Material Req'!$A:$A,A6,'Job Material Req'!$L:$L,"READY TO RESERVE")>0,"READY TO RESERVE","RESERVED"))) | K6: =IF(A6="","","TRV-"&TEXT(ROW()-3,"0000")) | L6: =IF(A6="","","Material status summarized from Job Material Req") | M6: =IF(A6="","",IF(H6<>"RESERVED","HOLD - MATERIAL","READY FOR RELEASE")) | N6: =IF(I6="","",12*(YEAR(I6)-YEAR(Inputs!$B$5))+MONTH(I6)-MONTH(Inputs!$B$5)+1) | O6: =IF(A6="","",IF(G6="Closed","Actual",IF(G6="Released","Committed","Plan"))) | P6: 1
A7: =IF('Sales Orders'!M7="YES","JC-"&TEXT(ROW()-3,"0000"),"") | B7: =IF(A7="","",'Sales Orders'!A7) | C7: =IF(A7="","",'Sales Orders'!B7) | D7: =IF(A7="","",'Sales Orders'!E7) | E7: =IF(A7="","",'Sales Orders'!G7) | F7: =IF(A7="","",'Sales Orders'!L7) | G7: =IF(A7="","","RELEASED") | H7: =IF(A7="","",IF(COUNTIFS('Job Material Req'!$A:$A,A7,'Job Material Req'!$L:$L,"SHORTAGE")>0,"SHORTAGE",IF(COUNTIFS('Job Material Req'!$A:$A,A7,'Job Material Req'!$L:$L,"READY TO RESERVE")>0,"READY TO RESERVE","RESERVED"))) | K7: =IF(A7="","","TRV-"&TEXT(ROW()-3,"0000")) | L7: =IF(A7="","","Material status summarized from Job Material Req") | M7: =IF(A7="","",IF(H7<>"RESERVED","HOLD - MATERIAL","READY FOR RELEASE")) | N7: =IF(I7="","",12*(YEAR(I7)-YEAR(Inputs!$B$5))+MONTH(I7)-MONTH(Inputs!$B$5)+1) | O7: =IF(A7="","",IF(G7="Closed","Actual",IF(G7="Released","Committed","Plan"))) | P7: 1
A8: =IF('Sales Orders'!M8="YES","JC-"&TEXT(ROW()-3,"0000"),"") | B8: =IF(A8="","",'Sales Orders'!A8) | C8: =IF(A8="","",'Sales Orders'!B8) | D8: =IF(A8="","",'Sales Orders'!E8) | E8: =IF(A8="","",'Sales Orders'!G8) | F8: =IF(A8="","",'Sales Orders'!L8) | G8: =IF(A8="","","RELEASED") | H8: =IF(A8="","",IF(COUNTIFS('Job Material Req'!$A:$A,A8,'Job Material Req'!$L:$L,"SHORTAGE")>0,"SHORTAGE",IF(COUNTIFS('Job Material Req'!$A:$A,A8,'Job Material Req'!$L:$L,"READY TO RESERVE")>0,"READY TO RESERVE","RESERVED"))) | K8: =IF(A8="","","TRV-"&TEXT(ROW()-3,"0000")) | L8: =IF(A8="","","Material status summarized from Job Material Req") | M8: =IF(A8="","",IF(H8<>"RESERVED","HOLD - MATERIAL","READY FOR RELEASE")) | N8: =IF(I8="","",12*(YEAR(I8)-YEAR(Inputs!$B$5))+MONTH(I8)-MONTH(Inputs!$B$5)+1) | O8: =IF(A8="","",IF(G8="Closed","Actual",IF(G8="Released","Committed","Plan"))) | P8: 1
A9: =IF('Sales Orders'!M9="YES","JC-"&TEXT(ROW()-3,"0000"),"") | B9: =IF(A9="","",'Sales Orders'!A9) | C9: =IF(A9="","",'Sales Orders'!B9) | D9: =IF(A9="","",'Sales Orders'!E9) | E9: =IF(A9="","",'Sales Orders'!G9) | F9: =IF(A9="","",'Sales Orders'!L9) | G9: =IF(A9="","","RELEASED") | H9: =IF(A9="","",IF(COUNTIFS('Job Material Req'!$A:$A,A9,'Job Material Req'!$L:$L,"SHORTAGE")>0,"SHORTAGE",IF(COUNTIFS('Job Material Req'!$A:$A,A9,'Job Material Req'!$L:$L,"READY TO RESERVE")>0,"READY TO RESERVE","RESERVED"))) | K9: =IF(A9="","","TRV-"&TEXT(ROW()-3,"0000")) | L9: =IF(A9="","","Material status summarized from Job Material Req") | M9: =IF(A9="","",IF(H9<>"RESERVED","HOLD - MATERIAL","READY FOR RELEASE")) | N9: =IF(I9="","",12*(YEAR(I9)-YEAR(Inputs!$B$5))+MONTH(I9)-MONTH(Inputs!$B$5)+1) | O9: =IF(A9="","",IF(G9="Closed","Actual",IF(G9="Released","Committed","Plan"))) | P9: 1
A10: =IF('Sales Orders'!M10="YES","JC-"&TEXT(ROW()-3,"0000"),"") | B10: =IF(A10="","",'Sales Orders'!A10) | C10: =IF(A10="","",'Sales Orders'!B10) | D10: =IF(A10="","",'Sales Orders'!E10) | E10: =IF(A10="","",'Sales Orders'!G10) | F10: =IF(A10="","",'Sales Orders'!L10) | G10: =IF(A10="","","RELEASED") | H10: =IF(A10="","",IF(COUNTIFS('Job Material Req'!$A:$A,A10,'Job Material Req'!$L:$L,"SHORTAGE")>0,"SHORTAGE",IF(COUNTIFS('Job Material Req'!$A:$A,A10,'Job Material Req'!$L:$L,"READY TO RESERVE")>0,"READY TO RESERVE","RESERVED"))) | K10: =IF(A10="","","TRV-"&TEXT(ROW()-3,"0000")) | L10: =IF(A10="","","Material status summarized from Job Material Req") | M10: =IF(A10="","",IF(H10<>"RESERVED","HOLD - MATERIAL","READY FOR RELEASE")) | N10: =IF(I10="","",12*(YEAR(I10)-YEAR(Inputs!$B$5))+MONTH(I10)-MONTH(Inputs!$B$5)+1) | O10: =IF(A10="","",IF(G10="Closed","Actual",IF(G10="Released","Committed","Plan"))) | P10: 1
A11: =IF('Sales Orders'!M11="YES","JC-"&TEXT(ROW()-3,"0000"),"") | B11: =IF(A11="","",'Sales Orders'!A11) | C11: =IF(A11="","",'Sales Orders'!B11) | D11: =IF(A11="","",'Sales Orders'!E11) | E11: =IF(A11="","",'Sales Orders'!G11) | F11: =IF(A11="","",'Sales Orders'!L11) | G11: =IF(A11="","","RELEASED") | H11: =IF(A11="","",IF(COUNTIFS('Job Material Req'!$A:$A,A11,'Job Material Req'!$L:$L,"SHORTAGE")>0,"SHORTAGE",IF(COUNTIFS('Job Material Req'!$A:$A,A11,'Job Material Req'!$L:$L,"READY TO RESERVE")>0,"READY TO RESERVE","RESERVED"))) | K11: =IF(A11="","","TRV-"&TEXT(ROW()-3,"0000")) | L11: =IF(A11="","","Material status summarized from Job Material Req") | M11: =IF(A11="","",IF(H11<>"RESERVED","HOLD - MATERIAL","READY FOR RELEASE")) | N11: =IF(I11="","",12*(YEAR(I11)-YEAR(Inputs!$B$5))+MONTH(I11)-MONTH(Inputs!$B$5)+1) | O11: =IF(A11="","",IF(G11="Closed","Actual",IF(G11="Released","Committed","Plan"))) | P11: 1
A12: =IF('Sales Orders'!M12="YES","JC-"&TEXT(ROW()-3,"0000"),"") | B12: =IF(A12="","",'Sales Orders'!A12) | C12: =IF(A12="","",'Sales Orders'!B12) | D12: =IF(A12="","",'Sales Orders'!E12) | E12: =IF(A12="","",'Sales Orders'!G12) | F12: =IF(A12="","",'Sales Orders'!L12) | G12: =IF(A12="","","RELEASED") | H12: =IF(A12="","",IF(COUNTIFS('Job Material Req'!$A:$A,A12,'Job Material Req'!$L:$L,"SHORTAGE")>0,"SHORTAGE",IF(COUNTIFS('Job Material Req'!$A:$A,A12,'Job Material Req'!$L:$L,"READY TO RESERVE")>0,"READY TO RESERVE","RESERVED"))) | K12: =IF(A12="","","TRV-"&TEXT(ROW()-3,"0000")) | L12: =IF(A12="","","Material status summarized from Job Material Req") | M12: =IF(A12="","",IF(H12<>"RESERVED","HOLD - MATERIAL","READY FOR RELEASE")) | N12: =IF(I12="","",12*(YEAR(I12)-YEAR(Inputs!$B$5))+MONTH(I12)-MONTH(Inputs!$B$5)+1) | O12: =IF(A12="","",IF(G12="Closed","Actual",IF(G12="Released","Committed","Plan"))) | P12: 1
A13: =IF('Sales Orders'!M13="YES","JC-"&TEXT(ROW()-3,"0000"),"") | B13: =IF(A13="","",'Sales Orders'!A13) | C13: =IF(A13="","",'Sales Orders'!B13) | D13: =IF(A13="","",'Sales Orders'!E13) | E13: =IF(A13="","",'Sales Orders'!G13) | F13: =IF(A13="","",'Sales Orders'!L13) | G13: =IF(A13="","","RELEASED") | H13: =IF(A13="","",IF(COUNTIFS('Job Material Req'!$A:$A,A13,'Job Material Req'!$L:$L,"SHORTAGE")>0,"SHORTAGE",IF(COUNTIFS('Job Material Req'!$A:$A,A13,'Job Material Req'!$L:$L,"READY TO RESERVE")>0,"READY TO RESERVE","RESERVED"))) | K13: =IF(A13="","","TRV-"&TEXT(ROW()-3,"0000")) | L13: =IF(A13="","","Material status summarized from Job Material Req") | M13: =IF(A13="","",IF(H13<>"RESERVED","HOLD - MATERIAL","READY FOR RELEASE")) | N13: =IF(I13="","",12*(YEAR(I13)-YEAR(Inputs!$B$5))+MONTH(I13)-MONTH(Inputs!$B$5)+1) | O13: =IF(A13="","",IF(G13="Closed","Actual",IF(G13="Released","Committed","Plan"))) | P13: 1
A14: =IF('Sales Orders'!M14="YES","JC-"&TEXT(ROW()-3,"0000"),"") | B14: =IF(A14="","",'Sales Orders'!A14) | C14: =IF(A14="","",'Sales Orders'!B14) | D14: =IF(A14="","",'Sales Orders'!E14) | E14: =IF(A14="","",'Sales Orders'!G14) | F14: =IF(A14="","",'Sales Orders'!L14) | G14: =IF(A14="","","RELEASED") | H14: =IF(A14="","",IF(COUNTIFS('Job Material Req'!$A:$A,A14,'Job Material Req'!$L:$L,"SHORTAGE")>0,"SHORTAGE",IF(COUNTIFS('Job Material Req'!$A:$A,A14,'Job Material Req'!$L:$L,"READY TO RESERVE")>0,"READY TO RESERVE","RESERVED"))) | K14: =IF(A14="","","TRV-"&TEXT(ROW()-3,"0000")) | L14: =IF(A14="","","Material status summarized from Job Material Req") | M14: =IF(A14="","",IF(H14<>"RESERVED","HOLD - MATERIAL","READY FOR RELEASE")) | N14: =IF(I14="","",12*(YEAR(I14)-YEAR(Inputs!$B$5))+MONTH(I14)-MONTH(Inputs!$B$5)+1) | O14: =IF(A14="","",IF(G14="Closed","Actual",IF(G14="Released","Committed","Plan"))) | P14: 1
A15: =IF('Sales Orders'!M15="YES","JC-"&TEXT(ROW()-3,"0000"),"") | B15: =IF(A15="","",'Sales Orders'!A15) | C15: =IF(A15="","",'Sales Orders'!B15) | D15: =IF(A15="","",'Sales Orders'!E15) | E15: =IF(A15="","",'Sales Orders'!G15) | F15: =IF(A15="","",'Sales Orders'!L15) | G15: =IF(A15="","","RELEASED") | H15: =IF(A15="","",IF(COUNTIFS('Job Material Req'!$A:$A,A15,'Job Material Req'!$L:$L,"SHORTAGE")>0,"SHORTAGE",IF(COUNTIFS('Job Material Req'!$A:$A,A15,'Job Material Req'!$L:$L,"READY TO RESERVE")>0,"READY TO RESERVE","RESERVED"))) | K15: =IF(A15="","","TRV-"&TEXT(ROW()-3,"0000")) | L15: =IF(A15="","","Material status summarized from Job Material Req") | M15: =IF(A15="","",IF(H15<>"RESERVED","HOLD - MATERIAL","READY FOR RELEASE")) | N15: =IF(I15="","",12*(YEAR(I15)-YEAR(Inputs!$B$5))+MONTH(I15)-MONTH(Inputs!$B$5)+1) | O15: =IF(A15="","",IF(G15="Closed","Actual",IF(G15="Released","Committed","Plan"))) | P15: 1
... A23: =IF('Sales Orders'!M23="YES","JC-"&TEXT(ROW()-3,"0000"),"") | B23: =IF(A23="","",'Sales Orders'!A23) | C23: =IF(A23="","",'Sales Orders'!B23) | D23: =IF(A23="","",'Sales Orders'!E23) | E23: =IF(A23="","",'Sales Orders'!G23) | F23: =IF(A23="","",'Sales Orders'!L23) | G23: =IF(A23="","","RELEASED") | H23: =IF(A23="","",IF(COUNTIFS('Job Material Req'!$A:$A,A23,'Job Material Req'!$L:$L,"SHORTAGE")>0,"SHORTAGE",IF(COUNTIFS('Job Material Req'!$A:$A,A23,'Job Material Req'!$L:$L,"READY TO RESERVE")>0,"READY TO RESERVE","RESERVED"))) | K23: =IF(A23="","","TRV-"&TEXT(ROW()-3,"0000")) | L23: =IF(A23="","","Material status summarized from Job Material Req") | M23: =IF(A23="","",IF(H23<>"RESERVED","HOLD - MATERIAL","READY FOR RELEASE")) | N23: =IF(I23="","",12*(YEAR(I23)-YEAR(Inputs!$B$5))+MONTH(I23)-MONTH(Inputs!$B$5)+1) | O23: =IF(A23="","",IF(G23="Closed","Actual",IF(G23="Released","Committed","Plan"))) | P23: 1
A24: =IF('Sales Orders'!M24="YES","JC-"&TEXT(ROW()-3,"0000"),"") | B24: =IF(A24="","",'Sales Orders'!A24) | C24: =IF(A24="","",'Sales Orders'!B24) | D24: =IF(A24="","",'Sales Orders'!E24) | E24: =IF(A24="","",'Sales Orders'!G24) | F24: =IF(A24="","",'Sales Orders'!L24) | G24: =IF(A24="","","RELEASED") | H24: =IF(A24="","",IF(COUNTIFS('Job Material Req'!$A$4:$A$703,A24,'Job Material Req'!$J$4:$J$703,">0")>0,"SHORTAGE","READY")) | K24: =IF(A24="","","TRV-"&TEXT(ROW()-3,"0000")) | L24: =IF(A24="","","Material status summarized from Job Material Req") | N24: =IF(I24="","",12*(YEAR(I24)-YEAR(Inputs!$B$5))+MONTH(I24)-MONTH(Inputs!$B$5)+1) | O24: =IF(A24="","",IF(G24="Closed","Actual",IF(G24="Released","Committed","Plan"))) | P24: 1
A25: =IF('Sales Orders'!M25="YES","JC-"&TEXT(ROW()-3,"0000"),"") | B25: =IF(A25="","",'Sales Orders'!A25) | C25: =IF(A25="","",'Sales Orders'!B25) | D25: =IF(A25="","",'Sales Orders'!E25) | E25: =IF(A25="","",'Sales Orders'!G25) | F25: =IF(A25="","",'Sales Orders'!L25) | G25: =IF(A25="","","RELEASED") | H25: =IF(A25="","",IF(COUNTIFS('Job Material Req'!$A$4:$A$703,A25,'Job Material Req'!$J$4:$J$703,">0")>0,"SHORTAGE","READY")) | K25: =IF(A25="","","TRV-"&TEXT(ROW()-3,"0000")) | L25: =IF(A25="","","Material status summarized from Job Material Req") | N25: =IF(I25="","",12*(YEAR(I25)-YEAR(Inputs!$B$5))+MONTH(I25)-MONTH(Inputs!$B$5)+1) | O25: =IF(A25="","",IF(G25="Closed","Actual",IF(G25="Released","Committed","Plan"))) | P25: 1
A26: =IF('Sales Orders'!M26="YES","JC-"&TEXT(ROW()-3,"0000"),"") | B26: =IF(A26="","",'Sales Orders'!A26) | C26: =IF(A26="","",'Sales Orders'!B26) | D26: =IF(A26="","",'Sales Orders'!E26) | E26: =IF(A26="","",'Sales Orders'!G26) | F26: =IF(A26="","",'Sales Orders'!L26) | G26: =IF(A26="","","RELEASED") | H26: =IF(A26="","",IF(COUNTIFS('Job Material Req'!$A$4:$A$703,A26,'Job Material Req'!$J$4:$J$703,">0")>0,"SHORTAGE","READY")) | K26: =IF(A26="","","TRV-"&TEXT(ROW()-3,"0000")) | L26: =IF(A26="","","Material status summarized from Job Material Req") | N26: =IF(I26="","",12*(YEAR(I26)-YEAR(Inputs!$B$5))+MONTH(I26)-MONTH(Inputs!$B$5)+1) | O26: =IF(A26="","",IF(G26="Closed","Actual",IF(G26="Released","Committed","Plan"))) | P26: 1
A27: =IF('Sales Orders'!M27="YES","JC-"&TEXT(ROW()-3,"0000"),"") | B27: =IF(A27="","",'Sales Orders'!A27) | C27: =IF(A27="","",'Sales Orders'!B27) | D27: =IF(A27="","",'Sales Orders'!E27) | E27: =IF(A27="","",'Sales Orders'!G27) | F27: =IF(A27="","",'Sales Orders'!L27) | G27: =IF(A27="","","RELEASED") | H27: =IF(A27="","",IF(COUNTIFS('Job Material Req'!$A$4:$A$703,A27,'Job Material Req'!$J$4:$J$703,">0")>0,"SHORTAGE","READY")) | K27: =IF(A27="","","TRV-"&TEXT(ROW()-3,"0000")) | L27: =IF(A27="","","Material status summarized from Job Material Req") | N27: =IF(I27="","",12*(YEAR(I27)-YEAR(Inputs!$B$5))+MONTH(I27)-MONTH(Inputs!$B$5)+1) | O27: =IF(A27="","",IF(G27="Closed","Actual",IF(G27="Released","Committed","Plan"))) | P27: 1
A28: =IF('Sales Orders'!M28="YES","JC-"&TEXT(ROW()-3,"0000"),"") | B28: =IF(A28="","",'Sales Orders'!A28) | C28: =IF(A28="","",'Sales Orders'!B28) | D28: =IF(A28="","",'Sales Orders'!E28) | E28: =IF(A28="","",'Sales Orders'!G28) | F28: =IF(A28="","",'Sales Orders'!L28) | G28: =IF(A28="","","RELEASED") | H28: =IF(A28="","",IF(COUNTIFS('Job Material Req'!$A$4:$A$703,A28,'Job Material Req'!$J$4:$J$703,">0")>0,"SHORTAGE","READY")) | K28: =IF(A28="","","TRV-"&TEXT(ROW()-3,"0000")) | L28: =IF(A28="","","Material status summarized from Job Material Req") | N28: =IF(I28="","",12*(YEAR(I28)-YEAR(Inputs!$B$5))+MONTH(I28)-MONTH(Inputs!$B$5)+1) | O28: =IF(A28="","",IF(G28="Closed","Actual",IF(G28="Released","Committed","Plan"))) | P28: 1
A29: =IF('Sales Orders'!M29="YES","JC-"&TEXT(ROW()-3,"0000"),"") | B29: =IF(A29="","",'Sales Orders'!A29) | C29: =IF(A29="","",'Sales Orders'!B29) | D29: =IF(A29="","",'Sales Orders'!E29) | E29: =IF(A29="","",'Sales Orders'!G29) | F29: =IF(A29="","",'Sales Orders'!L29) | G29: =IF(A29="","","RELEASED") | H29: =IF(A29="","",IF(COUNTIFS('Job Material Req'!$A$4:$A$703,A29,'Job Material Req'!$J$4:$J$703,">0")>0,"SHORTAGE","READY")) | K29: =IF(A29="","","TRV-"&TEXT(ROW()-3,"0000")) | L29: =IF(A29="","","Material status summarized from Job Material Req") | N29: =IF(I29="","",12*(YEAR(I29)-YEAR(Inputs!$B$5))+MONTH(I29)-MONTH(Inputs!$B$5)+1) | O29: =IF(A29="","",IF(G29="Closed","Actual",IF(G29="Released","Committed","Plan"))) | P29: 1
A30: =IF('Sales Orders'!M30="YES","JC-"&TEXT(ROW()-3,"0000"),"") | B30: =IF(A30="","",'Sales Orders'!A30) | C30: =IF(A30="","",'Sales Orders'!B30) | D30: =IF(A30="","",'Sales Orders'!E30) | E30: =IF(A30="","",'Sales Orders'!G30) | F30: =IF(A30="","",'Sales Orders'!L30) | G30: =IF(A30="","","RELEASED") | H30: =IF(A30="","",IF(COUNTIFS('Job Material Req'!$A$4:$A$703,A30,'Job Material Req'!$J$4:$J$703,">0")>0,"SHORTAGE","READY")) | K30: =IF(A30="","","TRV-"&TEXT(ROW()-3,"0000")) | L30: =IF(A30="","","Material status summarized from Job Material Req") | N30: =IF(I30="","",12*(YEAR(I30)-YEAR(Inputs!$B$5))+MONTH(I30)-MONTH(Inputs!$B$5)+1) | O30: =IF(A30="","",IF(G30="Closed","Actual",IF(G30="Released","Committed","Plan"))) | P30: 1
A31: =IF('Sales Orders'!M31="YES","JC-"&TEXT(ROW()-3,"0000"),"") | B31: =IF(A31="","",'Sales Orders'!A31) | C31: =IF(A31="","",'Sales Orders'!B31) | D31: =IF(A31="","",'Sales Orders'!E31) | E31: =IF(A31="","",'Sales Orders'!G31) | F31: =IF(A31="","",'Sales Orders'!L31) | G31: =IF(A31="","","RELEASED") | H31: =IF(A31="","",IF(COUNTIFS('Job Material Req'!$A$4:$A$703,A31,'Job Material Req'!$J$4:$J$703,">0")>0,"SHORTAGE","READY")) | K31: =IF(A31="","","TRV-"&TEXT(ROW()-3,"0000")) | L31: =IF(A31="","","Material status summarized from Job Material Req") | N31: =IF(I31="","",12*(YEAR(I31)-YEAR(Inputs!$B$5))+MONTH(I31)-MONTH(Inputs!$B$5)+1) | O31: =IF(A31="","",IF(G31="Closed","Actual",IF(G31="Released","Committed","Plan"))) | P31: 1
A32: =IF('Sales Orders'!M32="YES","JC-"&TEXT(ROW()-3,"0000"),"") | B32: =IF(A32="","",'Sales Orders'!A32) | C32: =IF(A32="","",'Sales Orders'!B32) | D32: =IF(A32="","",'Sales Orders'!E32) | E32: =IF(A32="","",'Sales Orders'!G32) | F32: =IF(A32="","",'Sales Orders'!L32) | G32: =IF(A32="","","RELEASED") | H32: =IF(A32="","",IF(COUNTIFS('Job Material Req'!$A$4:$A$703,A32,'Job Material Req'!$J$4:$J$703,">0")>0,"SHORTAGE","READY")) | K32: =IF(A32="","","TRV-"&TEXT(ROW()-3,"0000")) | L32: =IF(A32="","","Material status summarized from Job Material Req") | N32: =IF(I32="","",12*(YEAR(I32)-YEAR(Inputs!$B$5))+MONTH(I32)-MONTH(Inputs!$B$5)+1) | O32: =IF(A32="","",IF(G32="Closed","Actual",IF(G32="Released","Committed","Plan"))) | P32: 1
A33: =IF('Sales Orders'!M33="YES","JC-"&TEXT(ROW()-3,"0000"),"") | B33: =IF(A33="","",'Sales Orders'!A33) | C33: =IF(A33="","",'Sales Orders'!B33) | D33: =IF(A33="","",'Sales Orders'!E33) | E33: =IF(A33="","",'Sales Orders'!G33) | F33: =IF(A33="","",'Sales Orders'!L33) | G33: =IF(A33="","","RELEASED") | H33: =IF(A33="","",IF(COUNTIFS('Job Material Req'!$A$4:$A$703,A33,'Job Material Req'!$J$4:$J$703,">0")>0,"SHORTAGE","READY")) | K33: =IF(A33="","","TRV-"&TEXT(ROW()-3,"0000")) | L33: =IF(A33="","","Material status summarized from Job Material Req") | N33: =IF(I33="","",12*(YEAR(I33)-YEAR(Inputs!$B$5))+MONTH(I33)-MONTH(Inputs!$B$5)+1) | O33: =IF(A33="","",IF(G33="Closed","Actual",IF(G33="Released","Committed","Plan"))) | P33: 1
A34: =IF('Sales Orders'!M34="YES","JC-"&TEXT(ROW()-3,"0000"),"") | B34: =IF(A34="","",'Sales Orders'!A34) | C34: =IF(A34="","",'Sales Orders'!B34) | D34: =IF(A34="","",'Sales Orders'!E34) | E34: =IF(A34="","",'Sales Orders'!G34) | F34: =IF(A34="","",'Sales Orders'!L34) | G34: =IF(A34="","","RELEASED") | H34: =IF(A34="","",IF(COUNTIFS('Job Material Req'!$A$4:$A$703,A34,'Job Material Req'!$J$4:$J$703,">0")>0,"SHORTAGE","READY")) | K34: =IF(A34="","","TRV-"&TEXT(ROW()-3,"0000")) | L34: =IF(A34="","","Material status summarized from Job Material Req") | N34: =IF(I34="","",12*(YEAR(I34)-YEAR(Inputs!$B$5))+MONTH(I34)-MONTH(Inputs!$B$5)+1) | O34: =IF(A34="","",IF(G34="Closed","Actual",IF(G34="Released","Committed","Plan"))) | P34: 1
A35: =IF('Sales Orders'!M35="YES","JC-"&TEXT(ROW()-3,"0000"),"") | B35: =IF(A35="","",'Sales Orders'!A35) | C35: =IF(A35="","",'Sales Orders'!B35) | D35: =IF(A35="","",'Sales Orders'!E35) | E35: =IF(A35="","",'Sales Orders'!G35) | F35: =IF(A35="","",'Sales Orders'!L35) | G35: =IF(A35="","","RELEASED") | H35: =IF(A35="","",IF(COUNTIFS('Job Material Req'!$A$4:$A$703,A35,'Job Material Req'!$J$4:$J$703,">0")>0,"SHORTAGE","READY")) | K35: =IF(A35="","","TRV-"&TEXT(ROW()-3,"0000")) | L35: =IF(A35="","","Material status summarized from Job Material Req") | N35: =IF(I35="","",12*(YEAR(I35)-YEAR(Inputs!$B$5))+MONTH(I35)-MONTH(Inputs!$B$5)+1) | O35: =IF(A35="","",IF(G35="Closed","Actual",IF(G35="Released","Committed","Plan"))) | P35: 1
... A53: =IF('Sales Orders'!M53="YES","JC-"&TEXT(ROW()-3,"0000"),"") | B53: =IF(A53="","",'Sales Orders'!A53) | C53: =IF(A53="","",'Sales Orders'!B53) | D53: =IF(A53="","",'Sales Orders'!E53) | E53: =IF(A53="","",'Sales Orders'!G53) | F53: =IF(A53="","",'Sales Orders'!L53) | G53: =IF(A53="","","RELEASED") | H53: =IF(A53="","",IF(COUNTIFS('Job Material Req'!$A$4:$A$703,A53,'Job Material Req'!$J$4:$J$703,">0")>0,"SHORTAGE","READY")) | K53: =IF(A53="","","TRV-"&TEXT(ROW()-3,"0000")) | L53: =IF(A53="","","Material status summarized from Job Material Req") | N53: =IF(I53="","",12*(YEAR(I53)-YEAR(Inputs!$B$5))+MONTH(I53)-MONTH(Inputs!$B$5)+1) | O53: =IF(A53="","",IF(G53="Closed","Actual",IF(G53="Released","Committed","Plan"))) | P53: 1

Sheet Traveller
A1: Production Traveller · order/BOM/job traceability and operation sign-off
A3: Traveller ID | B3: Job Card | C3: Order ID | D3: Model | E3: Qty | F3: Operation | G3: Sequence | H3: Work Centre | I3: Status | J3: Inspector / Operator | K3: Date | L3: Quality Gate | M3: Evidence | N3: Remarks
A4: =IF('Job Cards'!A4="","",'Job Cards'!K4) | B4: =IF(A4="","",'Job Cards'!A4) | C4: =IF(A4="","",'Job Cards'!B4) | D4: =IF(A4="","",'Job Cards'!D4) | E4: =IF(A4="","",'Job Cards'!E4) | F4: Kitting | G4: 10 | H4: Kitting | I4: Not Started | L4: Open
A5: =IF('Job Cards'!A4="","",'Job Cards'!K4) | B5: =IF(A5="","",'Job Cards'!A4) | C5: =IF(A5="","",'Job Cards'!B4) | D5: =IF(A5="","",'Job Cards'!D4) | E5: =IF(A5="","",'Job Cards'!E4) | F5: Frame / frameset receipt | G5: 20 | H5: Frame / frameset receipt | I5: Not Started | L5: Open
A6: =IF('Job Cards'!A4="","",'Job Cards'!K4) | B6: =IF(A6="","",'Job Cards'!A4) | C6: =IF(A6="","",'Job Cards'!B4) | D6: =IF(A6="","",'Job Cards'!D4) | E6: =IF(A6="","",'Job Cards'!E4) | F6: Drivetrain assembly | G6: 30 | H6: Drivetrain assembly | I6: Not Started | L6: Open
A7: =IF('Job Cards'!A4="","",'Job Cards'!K4) | B7: =IF(A7="","",'Job Cards'!A4) | C7: =IF(A7="","",'Job Cards'!B4) | D7: =IF(A7="","",'Job Cards'!D4) | E7: =IF(A7="","",'Job Cards'!E4) | F7: Cockpit & controls | G7: 40 | H7: Cockpit & controls | I7: Not Started | L7: Open
A8: =IF('Job Cards'!A4="","",'Job Cards'!K4) | B8: =IF(A8="","",'Job Cards'!A4) | C8: =IF(A8="","",'Job Cards'!B4) | D8: =IF(A8="","",'Job Cards'!D4) | E8: =IF(A8="","",'Job Cards'!E4) | F8: Wheel / tyre fitment | G8: 50 | H8: Wheel / tyre fitment | I8: Not Started | L8: Open
A9: =IF('Job Cards'!A4="","",'Job Cards'!K4) | B9: =IF(A9="","",'Job Cards'!A4) | C9: =IF(A9="","",'Job Cards'!B4) | D9: =IF(A9="","",'Job Cards'!D4) | E9: =IF(A9="","",'Job Cards'!E4) | F9: Torque & fit inspection | G9: 60 | H9: Torque & fit inspection | I9: Not Started | L9: Open
A10: =IF('Job Cards'!A4="","",'Job Cards'!K4) | B10: =IF(A10="","",'Job Cards'!A4) | C10: =IF(A10="","",'Job Cards'!B4) | D10: =IF(A10="","",'Job Cards'!D4) | E10: =IF(A10="","",'Job Cards'!E4) | F10: Final quality | G10: 70 | H10: Final quality | I10: Not Started | L10: Open
A11: =IF('Job Cards'!A4="","",'Job Cards'!K4) | B11: =IF(A11="","",'Job Cards'!A4) | C11: =IF(A11="","",'Job Cards'!B4) | D11: =IF(A11="","",'Job Cards'!D4) | E11: =IF(A11="","",'Job Cards'!E4) | F11: Pack & release | G11: 80 | H11: Pack & release | I11: Not Started | L11: Open
A12: =IF('Job Cards'!A5="","",'Job Cards'!K5) | B12: =IF(A12="","",'Job Cards'!A5) | C12: =IF(A12="","",'Job Cards'!B5) | D12: =IF(A12="","",'Job Cards'!D5) | E12: =IF(A12="","",'Job Cards'!E5) | F12: Kitting | G12: 10 | H12: Kitting | I12: Not Started | L12: Open
A13: =IF('Job Cards'!A5="","",'Job Cards'!K5) | B13: =IF(A13="","",'Job Cards'!A5) | C13: =IF(A13="","",'Job Cards'!B5) | D13: =IF(A13="","",'Job Cards'!D5) | E13: =IF(A13="","",'Job Cards'!E5) | F13: Frame / frameset receipt | G13: 20 | H13: Frame / frameset receipt | I13: Not Started | L13: Open
A14: =IF('Job Cards'!A5="","",'Job Cards'!K5) | B14: =IF(A14="","",'Job Cards'!A5) | C14: =IF(A14="","",'Job Cards'!B5) | D14: =IF(A14="","",'Job Cards'!D5) | E14: =IF(A14="","",'Job Cards'!E5) | F14: Drivetrain assembly | G14: 30 | H14: Drivetrain assembly | I14: Not Started | L14: Open
A15: =IF('Job Cards'!A5="","",'Job Cards'!K5) | B15: =IF(A15="","",'Job Cards'!A5) | C15: =IF(A15="","",'Job Cards'!B5) | D15: =IF(A15="","",'Job Cards'!D5) | E15: =IF(A15="","",'Job Cards'!E5) | F15: Cockpit & controls | G15: 40 | H15: Cockpit & controls | I15: Not Started | L15: Open
A16: =IF('Job Cards'!A5="","",'Job Cards'!K5) | B16: =IF(A16="","",'Job Cards'!A5) | C16: =IF(A16="","",'Job Cards'!B5) | D16: =IF(A16="","",'Job Cards'!D5) | E16: =IF(A16="","",'Job Cards'!E5) | F16: Wheel / tyre fitment | G16: 50 | H16: Wheel / tyre fitment | I16: Not Started | L16: Open
A17: =IF('Job Cards'!A5="","",'Job Cards'!K5) | B17: =IF(A17="","",'Job Cards'!A5) | C17: =IF(A17="","",'Job Cards'!B5) | D17: =IF(A17="","",'Job Cards'!D5) | E17: =IF(A17="","",'Job Cards'!E5) | F17: Torque & fit inspection | G17: 60 | H17: Torque & fit inspection | I17: Not Started | L17: Open
A18: =IF('Job Cards'!A5="","",'Job Cards'!K5) | B18: =IF(A18="","",'Job Cards'!A5) | C18: =IF(A18="","",'Job Cards'!B5) | D18: =IF(A18="","",'Job Cards'!D5) | E18: =IF(A18="","",'Job Cards'!E5) | F18: Final quality | G18: 70 | H18: Final quality | I18: Not Started | L18: Open
A19: =IF('Job Cards'!A5="","",'Job Cards'!K5) | B19: =IF(A19="","",'Job Cards'!A5) | C19: =IF(A19="","",'Job Cards'!B5) | D19: =IF(A19="","",'Job Cards'!D5) | E19: =IF(A19="","",'Job Cards'!E5) | F19: Pack & release | G19: 80 | H19: Pack & release | I19: Not Started | L19: Open
A20: =IF('Job Cards'!A6="","",'Job Cards'!K6) | B20: =IF(A20="","",'Job Cards'!A6) | C20: =IF(A20="","",'Job Cards'!B6) | D20: =IF(A20="","",'Job Cards'!D6) | E20: =IF(A20="","",'Job Cards'!E6) | F20: Kitting | G20: 10 | H20: Kitting | I20: Not Started | L20: Open
A21: =IF('Job Cards'!A6="","",'Job Cards'!K6) | B21: =IF(A21="","",'Job Cards'!A6) | C21: =IF(A21="","",'Job Cards'!B6) | D21: =IF(A21="","",'Job Cards'!D6) | E21: =IF(A21="","",'Job Cards'!E6) | F21: Frame / frameset receipt | G21: 20 | H21: Frame / frameset receipt | I21: Not Started | L21: Open
A22: =IF('Job Cards'!A6="","",'Job Cards'!K6) | B22: =IF(A22="","",'Job Cards'!A6) | C22: =IF(A22="","",'Job Cards'!B6) | D22: =IF(A22="","",'Job Cards'!D6) | E22: =IF(A22="","",'Job Cards'!E6) | F22: Drivetrain assembly | G22: 30 | H22: Drivetrain assembly | I22: Not Started | L22: Open
A23: =IF('Job Cards'!A6="","",'Job Cards'!K6) | B23: =IF(A23="","",'Job Cards'!A6) | C23: =IF(A23="","",'Job Cards'!B6) | D23: =IF(A23="","",'Job Cards'!D6) | E23: =IF(A23="","",'Job Cards'!E6) | F23: Cockpit & controls | G23: 40 | H23: Cockpit & controls | I23: Not Started | L23: Open
A24: =IF('Job Cards'!A6="","",'Job Cards'!K6) | B24: =IF(A24="","",'Job Cards'!A6) | C24: =IF(A24="","",'Job Cards'!B6) | D24: =IF(A24="","",'Job Cards'!D6) | E24: =IF(A24="","",'Job Cards'!E6) | F24: Wheel / tyre fitment | G24: 50 | H24: Wheel / tyre fitment | I24: Not Started | L24: Open
A25: =IF('Job Cards'!A6="","",'Job Cards'!K6) | B25: =IF(A25="","",'Job Cards'!A6) | C25: =IF(A25="","",'Job Cards'!B6) | D25: =IF(A25="","",'Job Cards'!D6) | E25: =IF(A25="","",'Job Cards'!E6) | F25: Torque & fit inspection | G25: 60 | H25: Torque & fit inspection | I25: Not Started | L25: Open
A26: =IF('Job Cards'!A6="","",'Job Cards'!K6) | B26: =IF(A26="","",'Job Cards'!A6) | C26: =IF(A26="","",'Job Cards'!B6) | D26: =IF(A26="","",'Job Cards'!D6) | E26: =IF(A26="","",'Job Cards'!E6) | F26: Final quality | G26: 70 | H26: Final quality | I26: Not Started | L26: Open
A27: =IF('Job Cards'!A6="","",'Job Cards'!K6) | B27: =IF(A27="","",'Job Cards'!A6) | C27: =IF(A27="","",'Job Cards'!B6) | D27: =IF(A27="","",'Job Cards'!D6) | E27: =IF(A27="","",'Job Cards'!E6) | F27: Pack & release | G27: 80 | H27: Pack & release | I27: Not Started | L27: Open
A28: =IF('Job Cards'!A7="","",'Job Cards'!K7) | B28: =IF(A28="","",'Job Cards'!A7) | C28: =IF(A28="","",'Job Cards'!B7) | D28: =IF(A28="","",'Job Cards'!D7) | E28: =IF(A28="","",'Job Cards'!E7) | F28: Kitting | G28: 10 | H28: Kitting | I28: Not Started | L28: Open
A29: =IF('Job Cards'!A7="","",'Job Cards'!K7) | B29: =IF(A29="","",'Job Cards'!A7) | C29: =IF(A29="","",'Job Cards'!B7) | D29: =IF(A29="","",'Job Cards'!D7) | E29: =IF(A29="","",'Job Cards'!E7) | F29: Frame / frameset receipt | G29: 20 | H29: Frame / frameset receipt | I29: Not Started | L29: Open
A30: =IF('Job Cards'!A7="","",'Job Cards'!K7) | B30: =IF(A30="","",'Job Cards'!A7) | C30: =IF(A30="","",'Job Cards'!B7) | D30: =IF(A30="","",'Job Cards'!D7) | E30: =IF(A30="","",'Job Cards'!E7) | F30: Drivetrain assembly | G30: 30 | H30: Drivetrain assembly | I30: Not Started | L30: Open
A31: =IF('Job Cards'!A7="","",'Job Cards'!K7) | B31: =IF(A31="","",'Job Cards'!A7) | C31: =IF(A31="","",'Job Cards'!B7) | D31: =IF(A31="","",'Job Cards'!D7) | E31: =IF(A31="","",'Job Cards'!E7) | F31: Cockpit & controls | G31: 40 | H31: Cockpit & controls | I31: Not Started | L31: Open
A32: =IF('Job Cards'!A7="","",'Job Cards'!K7) | B32: =IF(A32="","",'Job Cards'!A7) | C32: =IF(A32="","",'Job Cards'!B7) | D32: =IF(A32="","",'Job Cards'!D7) | E32: =IF(A32="","",'Job Cards'!E7) | F32: Wheel / tyre fitment | G32: 50 | H32: Wheel / tyre fitment | I32: Not Started | L32: Open
A33: =IF('Job Cards'!A7="","",'Job Cards'!K7) | B33: =IF(A33="","",'Job Cards'!A7) | C33: =IF(A33="","",'Job Cards'!B7) | D33: =IF(A33="","",'Job Cards'!D7) | E33: =IF(A33="","",'Job Cards'!E7) | F33: Torque & fit inspection | G33: 60 | H33: Torque & fit inspection | I33: Not Started | L33: Open
A34: =IF('Job Cards'!A7="","",'Job Cards'!K7) | B34: =IF(A34="","",'Job Cards'!A7) | C34: =IF(A34="","",'Job Cards'!B7) | D34: =IF(A34="","",'Job Cards'!D7) | E34: =IF(A34="","",'Job Cards'!E7) | F34: Final quality | G34: 70 | H34: Final quality | I34: Not Started | L34: Open
A35: =IF('Job Cards'!A7="","",'Job Cards'!K7) | B35: =IF(A35="","",'Job Cards'!A7) | C35: =IF(A35="","",'Job Cards'!B7) | D35: =IF(A35="","",'Job Cards'!D7) | E35: =IF(A35="","",'Job Cards'!E7) | F35: Pack & release | G35: 80 | H35: Pack & release | I35: Not Started | L35: Open
A36: =IF('Job Cards'!A8="","",'Job Cards'!K8) | B36: =IF(A36="","",'Job Cards'!A8) | C36: =IF(A36="","",'Job Cards'!B8) | D36: =IF(A36="","",'Job Cards'!D8) | E36: =IF(A36="","",'Job Cards'!E8) | F36: Kitting | G36: 10 | H36: Kitting | I36: Not Started | L36: Open
A37: =IF('Job Cards'!A8="","",'Job Cards'!K8) | B37: =IF(A37="","",'Job Cards'!A8) | C37: =IF(A37="","",'Job Cards'!B8) | D37: =IF(A37="","",'Job Cards'!D8) | E37: =IF(A37="","",'Job Cards'!E8) | F37: Frame / frameset receipt | G37: 20 | H37: Frame / frameset receipt | I37: Not Started | L37: Open
A38: =IF('Job Cards'!A8="","",'Job Cards'!K8) | B38: =IF(A38="","",'Job Cards'!A8) | C38: =IF(A38="","",'Job Cards'!B8) | D38: =IF(A38="","",'Job Cards'!D8) | E38: =IF(A38="","",'Job Cards'!E8) | F38: Drivetrain assembly | G38: 30 | H38: Drivetrain assembly | I38: Not Started | L38: Open
A39: =IF('Job Cards'!A8="","",'Job Cards'!K8) | B39: =IF(A39="","",'Job Cards'!A8) | C39: =IF(A39="","",'Job Cards'!B8) | D39: =IF(A39="","",'Job Cards'!D8) | E39: =IF(A39="","",'Job Cards'!E8) | F39: Cockpit & controls | G39: 40 | H39: Cockpit & controls | I39: Not Started | L39: Open
A40: =IF('Job Cards'!A8="","",'Job Cards'!K8) | B40: =IF(A40="","",'Job Cards'!A8) | C40: =IF(A40="","",'Job Cards'!B8) | D40: =IF(A40="","",'Job Cards'!D8) | E40: =IF(A40="","",'Job Cards'!E8) | F40: Wheel / tyre fitment | G40: 50 | H40: Wheel / tyre fitment | I40: Not Started | L40: Open
A41: =IF('Job Cards'!A8="","",'Job Cards'!K8) | B41: =IF(A41="","",'Job Cards'!A8) | C41: =IF(A41="","",'Job Cards'!B8) | D41: =IF(A41="","",'Job Cards'!D8) | E41: =IF(A41="","",'Job Cards'!E8) | F41: Torque & fit inspection | G41: 60 | H41: Torque & fit inspection | I41: Not Started | L41: Open
A42: =IF('Job Cards'!A8="","",'Job Cards'!K8) | B42: =IF(A42="","",'Job Cards'!A8) | C42: =IF(A42="","",'Job Cards'!B8) | D42: =IF(A42="","",'Job Cards'!D8) | E42: =IF(A42="","",'Job Cards'!E8) | F42: Final quality | G42: 70 | H42: Final quality | I42: Not Started | L42: Open
A43: =IF('Job Cards'!A8="","",'Job Cards'!K8) | B43: =IF(A43="","",'Job Cards'!A8) | C43: =IF(A43="","",'Job Cards'!B8) | D43: =IF(A43="","",'Job Cards'!D8) | E43: =IF(A43="","",'Job Cards'!E8) | F43: Pack & release | G43: 80 | H43: Pack & release | I43: Not Started | L43: Open
A44: =IF('Job Cards'!A9="","",'Job Cards'!K9) | B44: =IF(A44="","",'Job Cards'!A9) | C44: =IF(A44="","",'Job Cards'!B9) | D44: =IF(A44="","",'Job Cards'!D9) | E44: =IF(A44="","",'Job Cards'!E9) | F44: Kitting | G44: 10 | H44: Kitting | I44: Not Started | L44: Open
A45: =IF('Job Cards'!A9="","",'Job Cards'!K9) | B45: =IF(A45="","",'Job Cards'!A9) | C45: =IF(A45="","",'Job Cards'!B9) | D45: =IF(A45="","",'Job Cards'!D9) | E45: =IF(A45="","",'Job Cards'!E9) | F45: Frame / frameset receipt | G45: 20 | H45: Frame / frameset receipt | I45: Not Started | L45: Open
A46: =IF('Job Cards'!A9="","",'Job Cards'!K9) | B46: =IF(A46="","",'Job Cards'!A9) | C46: =IF(A46="","",'Job Cards'!B9) | D46: =IF(A46="","",'Job Cards'!D9) | E46: =IF(A46="","",'Job Cards'!E9) | F46: Drivetrain assembly | G46: 30 | H46: Drivetrain assembly | I46: Not Started | L46: Open
A47: =IF('Job Cards'!A9="","",'Job Cards'!K9) | B47: =IF(A47="","",'Job Cards'!A9) | C47: =IF(A47="","",'Job Cards'!B9) | D47: =IF(A47="","",'Job Cards'!D9) | E47: =IF(A47="","",'Job Cards'!E9) | F47: Cockpit & controls | G47: 40 | H47: Cockpit & controls | I47: Not Started | L47: Open
A48: =IF('Job Cards'!A9="","",'Job Cards'!K9) | B48: =IF(A48="","",'Job Cards'!A9) | C48: =IF(A48="","",'Job Cards'!B9) | D48: =IF(A48="","",'Job Cards'!D9) | E48: =IF(A48="","",'Job Cards'!E9) | F48: Wheel / tyre fitment | G48: 50 | H48: Wheel / tyre fitment | I48: Not Started | L48: Open
A49: =IF('Job Cards'!A9="","",'Job Cards'!K9) | B49: =IF(A49="","",'Job Cards'!A9) | C49: =IF(A49="","",'Job Cards'!B9) | D49: =IF(A49="","",'Job Cards'!D9) | E49: =IF(A49="","",'Job Cards'!E9) | F49: Torque & fit inspection | G49: 60 | H49: Torque & fit inspection | I49: Not Started | L49: Open
A50: =IF('Job Cards'!A9="","",'Job Cards'!K9) | B50: =IF(A50="","",'Job Cards'!A9) | C50: =IF(A50="","",'Job Cards'!B9) | D50: =IF(A50="","",'Job Cards'!D9) | E50: =IF(A50="","",'Job Cards'!E9) | F50: Final quality | G50: 70 | H50: Final quality | I50: Not Started | L50: Open
A51: =IF('Job Cards'!A9="","",'Job Cards'!K9) | B51: =IF(A51="","",'Job Cards'!A9) | C51: =IF(A51="","",'Job Cards'!B9) | D51: =IF(A51="","",'Job Cards'!D9) | E51: =IF(A51="","",'Job Cards'!E9) | F51: Pack & release | G51: 80 | H51: Pack & release | I51: Not Started | L51: Open
A52: =IF('Job Cards'!A10="","",'Job Cards'!K10) | B52: =IF(A52="","",'Job Cards'!A10) | C52: =IF(A52="","",'Job Cards'!B10) | D52: =IF(A52="","",'Job Cards'!D10) | E52: =IF(A52="","",'Job Cards'!E10) | F52: Kitting | G52: 10 | H52: Kitting | I52: Not Started | L52: Open
A53: =IF('Job Cards'!A10="","",'Job Cards'!K10) | B53: =IF(A53="","",'Job Cards'!A10) | C53: =IF(A53="","",'Job Cards'!B10) | D53: =IF(A53="","",'Job Cards'!D10) | E53: =IF(A53="","",'Job Cards'!E10) | F53: Frame / frameset receipt | G53: 20 | H53: Frame / frameset receipt | I53: Not Started | L53: Open
A54: =IF('Job Cards'!A10="","",'Job Cards'!K10) | B54: =IF(A54="","",'Job Cards'!A10) | C54: =IF(A54="","",'Job Cards'!B10) | D54: =IF(A54="","",'Job Cards'!D10) | E54: =IF(A54="","",'Job Cards'!E10) | F54: Drivetrain assembly | G54: 30 | H54: Drivetrain assembly | I54: Not Started | L54: Open
A55: =IF('Job Cards'!A10="","",'Job Cards'!K10) | B55: =IF(A55="","",'Job Cards'!A10) | C55: =IF(A55="","",'Job Cards'!B10) | D55: =IF(A55="","",'Job Cards'!D10) | E55: =IF(A55="","",'Job Cards'!E10) | F55: Cockpit & controls | G55: 40 | H55: Cockpit & controls | I55: Not Started | L55: Open
A56: =IF('Job Cards'!A10="","",'Job Cards'!K10) | B56: =IF(A56="","",'Job Cards'!A10) | C56: =IF(A56="","",'Job Cards'!B10) | D56: =IF(A56="","",'Job Cards'!D10) | E56: =IF(A56="","",'Job Cards'!E10) | F56: Wheel / tyre fitment | G56: 50 | H56: Wheel / tyre fitment | I56: Not Started | L56: Open
A57: =IF('Job Cards'!A10="","",'Job Cards'!K10) | B57: =IF(A57="","",'Job Cards'!A10) | C57: =IF(A57="","",'Job Cards'!B10) | D57: =IF(A57="","",'Job Cards'!D10) | E57: =IF(A57="","",'Job Cards'!E10) | F57: Torque & fit inspection | G57: 60 | H57: Torque & fit inspection | I57: Not Started | L57: Open
A58: =IF('Job Cards'!A10="","",'Job Cards'!K10) | B58: =IF(A58="","",'Job Cards'!A10) | C58: =IF(A58="","",'Job Cards'!B10) | D58: =IF(A58="","",'Job Cards'!D10) | E58: =IF(A58="","",'Job Cards'!E10) | F58: Final quality | G58: 70 | H58: Final quality | I58: Not Started | L58: Open
A59: =IF('Job Cards'!A10="","",'Job Cards'!K10) | B59: =IF(A59="","",'Job Cards'!A10) | C59: =IF(A59="","",'Job Cards'!B10) | D59: =IF(A59="","",'Job Cards'!D10) | E59: =IF(A59="","",'Job Cards'!E10) | F59: Pack & release | G59: 80 | H59: Pack & release | I59: Not Started | L59: Open
A60: =IF('Job Cards'!A11="","",'Job Cards'!K11) | B60: =IF(A60="","",'Job Cards'!A11) | C60: =IF(A60="","",'Job Cards'!B11) | D60: =IF(A60="","",'Job Cards'!D11) | E60: =IF(A60="","",'Job Cards'!E11) | F60: Kitting | G60: 10 | H60: Kitting | I60: Not Started | L60: Open
A61: =IF('Job Cards'!A11="","",'Job Cards'!K11) | B61: =IF(A61="","",'Job Cards'!A11) | C61: =IF(A61="","",'Job Cards'!B11) | D61: =IF(A61="","",'Job Cards'!D11) | E61: =IF(A61="","",'Job Cards'!E11) | F61: Frame / frameset receipt | G61: 20 | H61: Frame / frameset receipt | I61: Not Started | L61: Open
A62: =IF('Job Cards'!A11="","",'Job Cards'!K11) | B62: =IF(A62="","",'Job Cards'!A11) | C62: =IF(A62="","",'Job Cards'!B11) | D62: =IF(A62="","",'Job Cards'!D11) | E62: =IF(A62="","",'Job Cards'!E11) | F62: Drivetrain assembly | G62: 30 | H62: Drivetrain assembly | I62: Not Started | L62: Open
A63: =IF('Job Cards'!A11="","",'Job Cards'!K11) | B63: =IF(A63="","",'Job Cards'!A11) | C63: =IF(A63="","",'Job Cards'!B11) | D63: =IF(A63="","",'Job Cards'!D11) | E63: =IF(A63="","",'Job Cards'!E11) | F63: Cockpit & controls | G63: 40 | H63: Cockpit & controls | I63: Not Started | L63: Open
A64: =IF('Job Cards'!A11="","",'Job Cards'!K11) | B64: =IF(A64="","",'Job Cards'!A11) | C64: =IF(A64="","",'Job Cards'!B11) | D64: =IF(A64="","",'Job Cards'!D11) | E64: =IF(A64="","",'Job Cards'!E11) | F64: Wheel / tyre fitment | G64: 50 | H64: Wheel / tyre fitment | I64: Not Started | L64: Open
A65: =IF('Job Cards'!A11="","",'Job Cards'!K11) | B65: =IF(A65="","",'Job Cards'!A11) | C65: =IF(A65="","",'Job Cards'!B11) | D65: =IF(A65="","",'Job Cards'!D11) | E65: =IF(A65="","",'Job Cards'!E11) | F65: Torque & fit inspection | G65: 60 | H65: Torque & fit inspection | I65: Not Started | L65: Open
A66: =IF('Job Cards'!A11="","",'Job Cards'!K11) | B66: =IF(A66="","",'Job Cards'!A11) | C66: =IF(A66="","",'Job Cards'!B11) | D66: =IF(A66="","",'Job Cards'!D11) | E66: =IF(A66="","",'Job Cards'!E11) | F66: Final quality | G66: 70 | H66: Final quality | I66: Not Started | L66: Open
A67: =IF('Job Cards'!A11="","",'Job Cards'!K11) | B67: =IF(A67="","",'Job Cards'!A11) | C67: =IF(A67="","",'Job Cards'!B11) | D67: =IF(A67="","",'Job Cards'!D11) | E67: =IF(A67="","",'Job Cards'!E11) | F67: Pack & release | G67: 80 | H67: Pack & release | I67: Not Started | L67: Open
A68: =IF('Job Cards'!A12="","",'Job Cards'!K12) | B68: =IF(A68="","",'Job Cards'!A12) | C68: =IF(A68="","",'Job Cards'!B12) | D68: =IF(A68="","",'Job Cards'!D12) | E68: =IF(A68="","",'Job Cards'!E12) | F68: Kitting | G68: 10 | H68: Kitting | I68: Not Started | L68: Open
A69: =IF('Job Cards'!A12="","",'Job Cards'!K12) | B69: =IF(A69="","",'Job Cards'!A12) | C69: =IF(A69="","",'Job Cards'!B12) | D69: =IF(A69="","",'Job Cards'!D12) | E69: =IF(A69="","",'Job Cards'!E12) | F69: Frame / frameset receipt | G69: 20 | H69: Frame / frameset receipt | I69: Not Started | L69: Open
A70: =IF('Job Cards'!A12="","",'Job Cards'!K12) | B70: =IF(A70="","",'Job Cards'!A12) | C70: =IF(A70="","",'Job Cards'!B12) | D70: =IF(A70="","",'Job Cards'!D12) | E70: =IF(A70="","",'Job Cards'!E12) | F70: Drivetrain assembly | G70: 30 | H70: Drivetrain assembly | I70: Not Started | L70: Open
A71: =IF('Job Cards'!A12="","",'Job Cards'!K12) | B71: =IF(A71="","",'Job Cards'!A12) | C71: =IF(A71="","",'Job Cards'!B12) | D71: =IF(A71="","",'Job Cards'!D12) | E71: =IF(A71="","",'Job Cards'!E12) | F71: Cockpit & controls | G71: 40 | H71: Cockpit & controls | I71: Not Started | L71: Open
A72: =IF('Job Cards'!A12="","",'Job Cards'!K12) | B72: =IF(A72="","",'Job Cards'!A12) | C72: =IF(A72="","",'Job Cards'!B12) | D72: =IF(A72="","",'Job Cards'!D12) | E72: =IF(A72="","",'Job Cards'!E12) | F72: Wheel / tyre fitment | G72: 50 | H72: Wheel / tyre fitment | I72: Not Started | L72: Open
A73: =IF('Job Cards'!A12="","",'Job Cards'!K12) | B73: =IF(A73="","",'Job Cards'!A12) | C73: =IF(A73="","",'Job Cards'!B12) | D73: =IF(A73="","",'Job Cards'!D12) | E73: =IF(A73="","",'Job Cards'!E12) | F73: Torque & fit inspection | G73: 60 | H73: Torque & fit inspection | I73: Not Started | L73: Open
A74: =IF('Job Cards'!A12="","",'Job Cards'!K12) | B74: =IF(A74="","",'Job Cards'!A12) | C74: =IF(A74="","",'Job Cards'!B12) | D74: =IF(A74="","",'Job Cards'!D12) | E74: =IF(A74="","",'Job Cards'!E12) | F74: Final quality | G74: 70 | H74: Final quality | I74: Not Started | L74: Open
A75: =IF('Job Cards'!A12="","",'Job Cards'!K12) | B75: =IF(A75="","",'Job Cards'!A12) | C75: =IF(A75="","",'Job Cards'!B12) | D75: =IF(A75="","",'Job Cards'!D12) | E75: =IF(A75="","",'Job Cards'!E12) | F75: Pack & release | G75: 80 | H75: Pack & release | I75: Not Started | L75: Open
A76: =IF('Job Cards'!A13="","",'Job Cards'!K13) | B76: =IF(A76="","",'Job Cards'!A13) | C76: =IF(A76="","",'Job Cards'!B13) | D76: =IF(A76="","",'Job Cards'!D13) | E76: =IF(A76="","",'Job Cards'!E13) | F76: Kitting | G76: 10 | H76: Kitting | I76: Not Started | L76: Open
A77: =IF('Job Cards'!A13="","",'Job Cards'!K13) | B77: =IF(A77="","",'Job Cards'!A13) | C77: =IF(A77="","",'Job Cards'!B13) | D77: =IF(A77="","",'Job Cards'!D13) | E77: =IF(A77="","",'Job Cards'!E13) | F77: Frame / frameset receipt | G77: 20 | H77: Frame / frameset receipt | I77: Not Started | L77: Open
A78: =IF('Job Cards'!A13="","",'Job Cards'!K13) | B78: =IF(A78="","",'Job Cards'!A13) | C78: =IF(A78="","",'Job Cards'!B13) | D78: =IF(A78="","",'Job Cards'!D13) | E78: =IF(A78="","",'Job Cards'!E13) | F78: Drivetrain assembly | G78: 30 | H78: Drivetrain assembly | I78: Not Started | L78: Open
A79: =IF('Job Cards'!A13="","",'Job Cards'!K13) | B79: =IF(A79="","",'Job Cards'!A13) | C79: =IF(A79="","",'Job Cards'!B13) | D79: =IF(A79="","",'Job Cards'!D13) | E79: =IF(A79="","",'Job Cards'!E13) | F79: Cockpit & controls | G79: 40 | H79: Cockpit & controls | I79: Not Started | L79: Open
A80: =IF('Job Cards'!A13="","",'Job Cards'!K13) | B80: =IF(A80="","",'Job Cards'!A13) | C80: =IF(A80="","",'Job Cards'!B13) | D80: =IF(A80="","",'Job Cards'!D13) | E80: =IF(A80="","",'Job Cards'!E13) | F80: Wheel / tyre fitment | G80: 50 | H80: Wheel / tyre fitment | I80: Not Started | L80: Open
A81: =IF('Job Cards'!A13="","",'Job Cards'!K13) | B81: =IF(A81="","",'Job Cards'!A13) | C81: =IF(A81="","",'Job Cards'!B13) | D81: =IF(A81="","",'Job Cards'!D13) | E81: =IF(A81="","",'Job Cards'!E13) | F81: Torque & fit inspection | G81: 60 | H81: Torque & fit inspection | I81: Not Started | L81: Open
A82: =IF('Job Cards'!A13="","",'Job Cards'!K13) | B82: =IF(A82="","",'Job Cards'!A13) | C82: =IF(A82="","",'Job Cards'!B13) | D82: =IF(A82="","",'Job Cards'!D13) | E82: =IF(A82="","",'Job Cards'!E13) | F82: Final quality | G82: 70 | H82: Final quality | I82: Not Started | L82: Open
A83: =IF('Job Cards'!A13="","",'Job Cards'!K13) | B83: =IF(A83="","",'Job Cards'!A13) | C83: =IF(A83="","",'Job Cards'!B13) | D83: =IF(A83="","",'Job Cards'!D13) | E83: =IF(A83="","",'Job Cards'!E13) | F83: Pack & release | G83: 80 | H83: Pack & release | I83: Not Started | L83: Open
A84: =IF('Job Cards'!A14="","",'Job Cards'!K14) | B84: =IF(A84="","",'Job Cards'!A14) | C84: =IF(A84="","",'Job Cards'!B14) | D84: =IF(A84="","",'Job Cards'!D14) | E84: =IF(A84="","",'Job Cards'!E14) | F84: Kitting | G84: 10 | H84: Kitting | I84: Not Started | L84: Open
A85: =IF('Job Cards'!A14="","",'Job Cards'!K14) | B85: =IF(A85="","",'Job Cards'!A14) | C85: =IF(A85="","",'Job Cards'!B14) | D85: =IF(A85="","",'Job Cards'!D14) | E85: =IF(A85="","",'Job Cards'!E14) | F85: Frame / frameset receipt | G85: 20 | H85: Frame / frameset receipt | I85: Not Started | L85: Open
A86: =IF('Job Cards'!A14="","",'Job Cards'!K14) | B86: =IF(A86="","",'Job Cards'!A14) | C86: =IF(A86="","",'Job Cards'!B14) | D86: =IF(A86="","",'Job Cards'!D14) | E86: =IF(A86="","",'Job Cards'!E14) | F86: Drivetrain assembly | G86: 30 | H86: Drivetrain assembly | I86: Not Started | L86: Open
A87: =IF('Job Cards'!A14="","",'Job Cards'!K14) | B87: =IF(A87="","",'Job Cards'!A14) | C87: =IF(A87="","",'Job Cards'!B14) | D87: =IF(A87="","",'Job Cards'!D14) | E87: =IF(A87="","",'Job Cards'!E14) | F87: Cockpit & controls | G87: 40 | H87: Cockpit & controls | I87: Not Started | L87: Open
A88: =IF('Job Cards'!A14="","",'Job Cards'!K14) | B88: =IF(A88="","",'Job Cards'!A14) | C88: =IF(A88="","",'Job Cards'!B14) | D88: =IF(A88="","",'Job Cards'!D14) | E88: =IF(A88="","",'Job Cards'!E14) | F88: Wheel / tyre fitment | G88: 50 | H88: Wheel / tyre fitment | I88: Not Started | L88: Open
A89: =IF('Job Cards'!A14="","",'Job Cards'!K14) | B89: =IF(A89="","",'Job Cards'!A14) | C89: =IF(A89="","",'Job Cards'!B14) | D89: =IF(A89="","",'Job Cards'!D14) | E89: =IF(A89="","",'Job Cards'!E14) | F89: Torque & fit inspection | G89: 60 | H89: Torque & fit inspection | I89: Not Started | L89: Open
A90: =IF('Job Cards'!A14="","",'Job Cards'!K14) | B90: =IF(A90="","",'Job Cards'!A14) | C90: =IF(A90="","",'Job Cards'!B14) | D90: =IF(A90="","",'Job Cards'!D14) | E90: =IF(A90="","",'Job Cards'!E14) | F90: Final quality | G90: 70 | H90: Final quality | I90: Not Started | L90: Open
A91: =IF('Job Cards'!A14="","",'Job Cards'!K14) | B91: =IF(A91="","",'Job Cards'!A14) | C91: =IF(A91="","",'Job Cards'!B14) | D91: =IF(A91="","",'Job Cards'!D14) | E91: =IF(A91="","",'Job Cards'!E14) | F91: Pack & release | G91: 80 | H91: Pack & release | I91: Not Started | L91: Open
A92: =IF('Job Cards'!A15="","",'Job Cards'!K15) | B92: =IF(A92="","",'Job Cards'!A15) | C92: =IF(A92="","",'Job Cards'!B15) | D92: =IF(A92="","",'Job Cards'!D15) | E92: =IF(A92="","",'Job Cards'!E15) | F92: Kitting | G92: 10 | H92: Kitting | I92: Not Started | L92: Open
A93: =IF('Job Cards'!A15="","",'Job Cards'!K15) | B93: =IF(A93="","",'Job Cards'!A15) | C93: =IF(A93="","",'Job Cards'!B15) | D93: =IF(A93="","",'Job Cards'!D15) | E93: =IF(A93="","",'Job Cards'!E15) | F93: Frame / frameset receipt | G93: 20 | H93: Frame / frameset receipt | I93: Not Started | L93: Open
A94: =IF('Job Cards'!A15="","",'Job Cards'!K15) | B94: =IF(A94="","",'Job Cards'!A15) | C94: =IF(A94="","",'Job Cards'!B15) | D94: =IF(A94="","",'Job Cards'!D15) | E94: =IF(A94="","",'Job Cards'!E15) | F94: Drivetrain assembly | G94: 30 | H94: Drivetrain assembly | I94: Not Started | L94: Open
A95: =IF('Job Cards'!A15="","",'Job Cards'!K15) | B95: =IF(A95="","",'Job Cards'!A15) | C95: =IF(A95="","",'Job Cards'!B15) | D95: =IF(A95="","",'Job Cards'!D15) | E95: =IF(A95="","",'Job Cards'!E15) | F95: Cockpit & controls | G95: 40 | H95: Cockpit & controls | I95: Not Started | L95: Open
A96: =IF('Job Cards'!A15="","",'Job Cards'!K15) | B96: =IF(A96="","",'Job Cards'!A15) | C96: =IF(A96="","",'Job Cards'!B15) | D96: =IF(A96="","",'Job Cards'!D15) | E96: =IF(A96="","",'Job Cards'!E15) | F96: Wheel / tyre fitment | G96: 50 | H96: Wheel / tyre fitment | I96: Not Started | L96: Open
A97: =IF('Job Cards'!A15="","",'Job Cards'!K15) | B97: =IF(A97="","",'Job Cards'!A15) | C97: =IF(A97="","",'Job Cards'!B15) | D97: =IF(A97="","",'Job Cards'!D15) | E97: =IF(A97="","",'Job Cards'!E15) | F97: Torque & fit inspection | G97: 60 | H97: Torque & fit inspection | I97: Not Started | L97: Open
A98: =IF('Job Cards'!A15="","",'Job Cards'!K15) | B98: =IF(A98="","",'Job Cards'!A15) | C98: =IF(A98="","",'Job Cards'!B15) | D98: =IF(A98="","",'Job Cards'!D15) | E98: =IF(A98="","",'Job Cards'!E15) | F98: Final quality | G98: 70 | H98: Final quality | I98: Not Started | L98: Open
A99: =IF('Job Cards'!A15="","",'Job Cards'!K15) | B99: =IF(A99="","",'Job Cards'!A15) | C99: =IF(A99="","",'Job Cards'!B15) | D99: =IF(A99="","",'Job Cards'!D15) | E99: =IF(A99="","",'Job Cards'!E15) | F99: Pack & release | G99: 80 | H99: Pack & release | I99: Not Started | L99: Open
A100: =IF('Job Cards'!A16="","",'Job Cards'!K16) | B100: =IF(A100="","",'Job Cards'!A16) | C100: =IF(A100="","",'Job Cards'!B16) | D100: =IF(A100="","",'Job Cards'!D16) | E100: =IF(A100="","",'Job Cards'!E16) | F100: Kitting | G100: 10 | H100: Kitting | I100: Not Started | L100: Open
A101: =IF('Job Cards'!A16="","",'Job Cards'!K16) | B101: =IF(A101="","",'Job Cards'!A16) | C101: =IF(A101="","",'Job Cards'!B16) | D101: =IF(A101="","",'Job Cards'!D16) | E101: =IF(A101="","",'Job Cards'!E16) | F101: Frame / frameset receipt | G101: 20 | H101: Frame / frameset receipt | I101: Not Started | L101: Open
...

Sheet Procurement Plan
A1: Procurement Plan · planned demand + committed demand + ATP + open PO reconciliation
A3: SKU | B3: Item | C3: MSL | D3: ATP | E3: 36M Planned Qty | F3: Committed Qty | G3: Open PO Qty | H3: Gross Requirement | I3: Net Buy Qty | J3: Unit Price ₹ | K3: Net Buy Value ₹ | L3: Priority | M3: Decision | N3: Lead-time flag | O3: 36M Net Buy Cash ₹
A4: ='Master Inventory'!A4 | B4: ='Master Inventory'!C4 | C4: ='Master Inventory'!E4 | D4: ='Master Inventory'!J4 | E4: =SUMIFS('BOM Mapping'!$J$4:$J$23,'BOM Mapping'!$C$4:$C$23,$A4,'BOM Mapping'!$I$4:$I$23,"Approved")*SUM('Monthly Materials'!$D$6:$D$41)+SUMIFS('BOM Mapping'!$K$4:$K$23,'BOM Mapping'!$D$4:$D$23,$A4,'BOM Mapping'!$I$4:$I$23,"Approved")*SUM('Monthly Materials'!$E$6:$E$41)+SUMIFS('BOM Mapping'!$L$4:$L$23,'BOM Mapping'!$E$4:$E$23,$A4,'BOM Mapping'!$I$4:$I$23,"Approved")*SUM('Monthly Materials'!$F$6:$F$41) | F4: =SUMPRODUCT(('Sales Orders'!$E$4:$E$203="Longitude")*('Sales Orders'!$J$4:$J$203="Confirmed")*'Sales Orders'!$G$4:$G$203)*SUMIFS('BOM Mapping'!$J$4:$J$23,'BOM Mapping'!$C$4:$C$23,$A4)+SUMPRODUCT(('Sales Orders'!$E$4:$E$203="Latitude")*('Sales Orders'!$J$4:$J$203="Confirmed")*'Sales Orders'!$G$4:$G$203)*SUMIFS('BOM Mapping'!$K$4:$K$23,'BOM Mapping'!$D$4:$D$23,$A4)+SUMPRODUCT(('Sales Orders'!$E$4:$E$203="Altitude")*('Sales Orders'!$J$4:$J$203="Confirmed")*'Sales Orders'!$G$4:$G$203)*SUMIFS('BOM Mapping'!$L$4:$L$23,'BOM Mapping'!$E$4:$E$23,$A4) | G4: 0 | H4: =MAX(E4,F4)+C4 | I4: =MAX(0,H4-D4-G4) | J4: ='Master Inventory'!D4 | K4: =I4*J4 | L4: =IF(F4>0,"P1 COMMITTED",IF(E4>0,"P2 PLAN",IF(C4>0,"P3 MSL","NONE"))) | M4: =IF(I4>0,"BUY / RFQ","NO BUY") | N4: =IF(I4=0,"",IF(IFERROR(VLOOKUP(A4,'Component Catalogue'!$G$5:$T$76,10,FALSE),1)>1,"PLAN EARLY","NORMAL")) | O4: =K4
A5: ='Master Inventory'!A5 | B5: ='Master Inventory'!C5 | C5: ='Master Inventory'!E5 | D5: ='Master Inventory'!J5 | E5: =SUMIFS('BOM Mapping'!$J$4:$J$23,'BOM Mapping'!$C$4:$C$23,$A5,'BOM Mapping'!$I$4:$I$23,"Approved")*SUM('Monthly Materials'!$D$6:$D$41)+SUMIFS('BOM Mapping'!$K$4:$K$23,'BOM Mapping'!$D$4:$D$23,$A5,'BOM Mapping'!$I$4:$I$23,"Approved")*SUM('Monthly Materials'!$E$6:$E$41)+SUMIFS('BOM Mapping'!$L$4:$L$23,'BOM Mapping'!$E$4:$E$23,$A5,'BOM Mapping'!$I$4:$I$23,"Approved")*SUM('Monthly Materials'!$F$6:$F$41) | F5: =SUMPRODUCT(('Sales Orders'!$E$4:$E$203="Longitude")*('Sales Orders'!$J$4:$J$203="Confirmed")*'Sales Orders'!$G$4:$G$203)*SUMIFS('BOM Mapping'!$J$4:$J$23,'BOM Mapping'!$C$4:$C$23,$A5)+SUMPRODUCT(('Sales Orders'!$E$4:$E$203="Latitude")*('Sales Orders'!$J$4:$J$203="Confirmed")*'Sales Orders'!$G$4:$G$203)*SUMIFS('BOM Mapping'!$K$4:$K$23,'BOM Mapping'!$D$4:$D$23,$A5)+SUMPRODUCT(('Sales Orders'!$E$4:$E$203="Altitude")*('Sales Orders'!$J$4:$J$203="Confirmed")*'Sales Orders'!$G$4:$G$203)*SUMIFS('BOM Mapping'!$L$4:$L$23,'BOM Mapping'!$E$4:$E$23,$A5) | G5: 0 | H5: =MAX(E5,F5)+C5 | I5: =MAX(0,H5-D5-G5) | J5: ='Master Inventory'!D5 | K5: =I5*J5 | L5: =IF(F5>0,"P1 COMMITTED",IF(E5>0,"P2 PLAN",IF(C5>0,"P3 MSL","NONE"))) | M5: =IF(I5>0,"BUY / RFQ","NO BUY") | N5: =IF(I5=0,"",IF(IFERROR(VLOOKUP(A5,'Component Catalogue'!$G$5:$T$76,10,FALSE),1)>1,"PLAN EARLY","NORMAL")) | O5: =K5
A6: ='Master Inventory'!A6 | B6: ='Master Inventory'!C6 | C6: ='Master Inventory'!E6 | D6: ='Master Inventory'!J6 | E6: =SUMIFS('BOM Mapping'!$J$4:$J$23,'BOM Mapping'!$C$4:$C$23,$A6,'BOM Mapping'!$I$4:$I$23,"Approved")*SUM('Monthly Materials'!$D$6:$D$41)+SUMIFS('BOM Mapping'!$K$4:$K$23,'BOM Mapping'!$D$4:$D$23,$A6,'BOM Mapping'!$I$4:$I$23,"Approved")*SUM('Monthly Materials'!$E$6:$E$41)+SUMIFS('BOM Mapping'!$L$4:$L$23,'BOM Mapping'!$E$4:$E$23,$A6,'BOM Mapping'!$I$4:$I$23,"Approved")*SUM('Monthly Materials'!$F$6:$F$41) | F6: =SUMPRODUCT(('Sales Orders'!$E$4:$E$203="Longitude")*('Sales Orders'!$J$4:$J$203="Confirmed")*'Sales Orders'!$G$4:$G$203)*SUMIFS('BOM Mapping'!$J$4:$J$23,'BOM Mapping'!$C$4:$C$23,$A6)+SUMPRODUCT(('Sales Orders'!$E$4:$E$203="Latitude")*('Sales Orders'!$J$4:$J$203="Confirmed")*'Sales Orders'!$G$4:$G$203)*SUMIFS('BOM Mapping'!$K$4:$K$23,'BOM Mapping'!$D$4:$D$23,$A6)+SUMPRODUCT(('Sales Orders'!$E$4:$E$203="Altitude")*('Sales Orders'!$J$4:$J$203="Confirmed")*'Sales Orders'!$G$4:$G$203)*SUMIFS('BOM Mapping'!$L$4:$L$23,'BOM Mapping'!$E$4:$E$23,$A6) | G6: 0 | H6: =MAX(E6,F6)+C6 | I6: =MAX(0,H6-D6-G6) | J6: ='Master Inventory'!D6 | K6: =I6*J6 | L6: =IF(F6>0,"P1 COMMITTED",IF(E6>0,"P2 PLAN",IF(C6>0,"P3 MSL","NONE"))) | M6: =IF(I6>0,"BUY / RFQ","NO BUY") | N6: =IF(I6=0,"",IF(IFERROR(VLOOKUP(A6,'Component Catalogue'!$G$5:$T$76,10,FALSE),1)>1,"PLAN EARLY","NORMAL")) | O6: =K6
A7: ='Master Inventory'!A7 | B7: ='Master Inventory'!C7 | C7: ='Master Inventory'!E7 | D7: ='Master Inventory'!J7 | E7: =SUMIFS('BOM Mapping'!$J$4:$J$23,'BOM Mapping'!$C$4:$C$23,$A7,'BOM Mapping'!$I$4:$I$23,"Approved")*SUM('Monthly Materials'!$D$6:$D$41)+SUMIFS('BOM Mapping'!$K$4:$K$23,'BOM Mapping'!$D$4:$D$23,$A7,'BOM Mapping'!$I$4:$I$23,"Approved")*SUM('Monthly Materials'!$E$6:$E$41)+SUMIFS('BOM Mapping'!$L$4:$L$23,'BOM Mapping'!$E$4:$E$23,$A7,'BOM Mapping'!$I$4:$I$23,"Approved")*SUM('Monthly Materials'!$F$6:$F$41) | F7: =SUMPRODUCT(('Sales Orders'!$E$4:$E$203="Longitude")*('Sales Orders'!$J$4:$J$203="Confirmed")*'Sales Orders'!$G$4:$G$203)*SUMIFS('BOM Mapping'!$J$4:$J$23,'BOM Mapping'!$C$4:$C$23,$A7)+SUMPRODUCT(('Sales Orders'!$E$4:$E$203="Latitude")*('Sales Orders'!$J$4:$J$203="Confirmed")*'Sales Orders'!$G$4:$G$203)*SUMIFS('BOM Mapping'!$K$4:$K$23,'BOM Mapping'!$D$4:$D$23,$A7)+SUMPRODUCT(('Sales Orders'!$E$4:$E$203="Altitude")*('Sales Orders'!$J$4:$J$203="Confirmed")*'Sales Orders'!$G$4:$G$203)*SUMIFS('BOM Mapping'!$L$4:$L$23,'BOM Mapping'!$E$4:$E$23,$A7) | G7: 0 | H7: =MAX(E7,F7)+C7 | I7: =MAX(0,H7-D7-G7) | J7: ='Master Inventory'!D7 | K7: =I7*J7 | L7: =IF(F7>0,"P1 COMMITTED",IF(E7>0,"P2 PLAN",IF(C7>0,"P3 MSL","NONE"))) | M7: =IF(I7>0,"BUY / RFQ","NO BUY") | N7: =IF(I7=0,"",IF(IFERROR(VLOOKUP(A7,'Component Catalogue'!$G$5:$T$76,10,FALSE),1)>1,"PLAN EARLY","NORMAL")) | O7: =K7
A8: ='Master Inventory'!A8 | B8: ='Master Inventory'!C8 | C8: ='Master Inventory'!E8 | D8: ='Master Inventory'!J8 | E8: =SUMIFS('BOM Mapping'!$J$4:$J$23,'BOM Mapping'!$C$4:$C$23,$A8,'BOM Mapping'!$I$4:$I$23,"Approved")*SUM('Monthly Materials'!$D$6:$D$41)+SUMIFS('BOM Mapping'!$K$4:$K$23,'BOM Mapping'!$D$4:$D$23,$A8,'BOM Mapping'!$I$4:$I$23,"Approved")*SUM('Monthly Materials'!$E$6:$E$41)+SUMIFS('BOM Mapping'!$L$4:$L$23,'BOM Mapping'!$E$4:$E$23,$A8,'BOM Mapping'!$I$4:$I$23,"Approved")*SUM('Monthly Materials'!$F$6:$F$41) | F8: =SUMPRODUCT(('Sales Orders'!$E$4:$E$203="Longitude")*('Sales Orders'!$J$4:$J$203="Confirmed")*'Sales Orders'!$G$4:$G$203)*SUMIFS('BOM Mapping'!$J$4:$J$23,'BOM Mapping'!$C$4:$C$23,$A8)+SUMPRODUCT(('Sales Orders'!$E$4:$E$203="Latitude")*('Sales Orders'!$J$4:$J$203="Confirmed")*'Sales Orders'!$G$4:$G$203)*SUMIFS('BOM Mapping'!$K$4:$K$23,'BOM Mapping'!$D$4:$D$23,$A8)+SUMPRODUCT(('Sales Orders'!$E$4:$E$203="Altitude")*('Sales Orders'!$J$4:$J$203="Confirmed")*'Sales Orders'!$G$4:$G$203)*SUMIFS('BOM Mapping'!$L$4:$L$23,'BOM Mapping'!$E$4:$E$23,$A8) | G8: 0 | H8: =MAX(E8,F8)+C8 | I8: =MAX(0,H8-D8-G8) | J8: ='Master Inventory'!D8 | K8: =I8*J8 | L8: =IF(F8>0,"P1 COMMITTED",IF(E8>0,"P2 PLAN",IF(C8>0,"P3 MSL","NONE"))) | M8: =IF(I8>0,"BUY / RFQ","NO BUY") | N8: =IF(I8=0,"",IF(IFERROR(VLOOKUP(A8,'Component Catalogue'!$G$5:$T$76,10,FALSE),1)>1,"PLAN EARLY","NORMAL")) | O8: =K8
A9: ='Master Inventory'!A9 | B9: ='Master Inventory'!C9 | C9: ='Master Inventory'!E9 | D9: ='Master Inventory'!J9 | E9: =SUMIFS('BOM Mapping'!$J$4:$J$23,'BOM Mapping'!$C$4:$C$23,$A9,'BOM Mapping'!$I$4:$I$23,"Approved")*SUM('Monthly Materials'!$D$6:$D$41)+SUMIFS('BOM Mapping'!$K$4:$K$23,'BOM Mapping'!$D$4:$D$23,$A9,'BOM Mapping'!$I$4:$I$23,"Approved")*SUM('Monthly Materials'!$E$6:$E$41)+SUMIFS('BOM Mapping'!$L$4:$L$23,'BOM Mapping'!$E$4:$E$23,$A9,'BOM Mapping'!$I$4:$I$23,"Approved")*SUM('Monthly Materials'!$F$6:$F$41) | F9: =SUMPRODUCT(('Sales Orders'!$E$4:$E$203="Longitude")*('Sales Orders'!$J$4:$J$203="Confirmed")*'Sales Orders'!$G$4:$G$203)*SUMIFS('BOM Mapping'!$J$4:$J$23,'BOM Mapping'!$C$4:$C$23,$A9)+SUMPRODUCT(('Sales Orders'!$E$4:$E$203="Latitude")*('Sales Orders'!$J$4:$J$203="Confirmed")*'Sales Orders'!$G$4:$G$203)*SUMIFS('BOM Mapping'!$K$4:$K$23,'BOM Mapping'!$D$4:$D$23,$A9)+SUMPRODUCT(('Sales Orders'!$E$4:$E$203="Altitude")*('Sales Orders'!$J$4:$J$203="Confirmed")*'Sales Orders'!$G$4:$G$203)*SUMIFS('BOM Mapping'!$L$4:$L$23,'BOM Mapping'!$E$4:$E$23,$A9) | G9: 0 | H9: =MAX(E9,F9)+C9 | I9: =MAX(0,H9-D9-G9) | J9: ='Master Inventory'!D9 | K9: =I9*J9 | L9: =IF(F9>0,"P1 COMMITTED",IF(E9>0,"P2 PLAN",IF(C9>0,"P3 MSL","NONE"))) | M9: =IF(I9>0,"BUY / RFQ","NO BUY") | N9: =IF(I9=0,"",IF(IFERROR(VLOOKUP(A9,'Component Catalogue'!$G$5:$T$76,10,FALSE),1)>1,"PLAN EARLY","NORMAL")) | O9: =K9
A10: ='Master Inventory'!A10 | B10: ='Master Inventory'!C10 | C10: ='Master Inventory'!E10 | D10: ='Master Inventory'!J10 | E10: =SUMIFS('BOM Mapping'!$J$4:$J$23,'BOM Mapping'!$C$4:$C$23,$A10,'BOM Mapping'!$I$4:$I$23,"Approved")*SUM('Monthly Materials'!$D$6:$D$41)+SUMIFS('BOM Mapping'!$K$4:$K$23,'BOM Mapping'!$D$4:$D$23,$A10,'BOM Mapping'!$I$4:$I$23,"Approved")*SUM('Monthly Materials'!$E$6:$E$41)+SUMIFS('BOM Mapping'!$L$4:$L$23,'BOM Mapping'!$E$4:$E$23,$A10,'BOM Mapping'!$I$4:$I$23,"Approved")*SUM('Monthly Materials'!$F$6:$F$41) | F10: =SUMPRODUCT(('Sales Orders'!$E$4:$E$203="Longitude")*('Sales Orders'!$J$4:$J$203="Confirmed")*'Sales Orders'!$G$4:$G$203)*SUMIFS('BOM Mapping'!$J$4:$J$23,'BOM Mapping'!$C$4:$C$23,$A10)+SUMPRODUCT(('Sales Orders'!$E$4:$E$203="Latitude")*('Sales Orders'!$J$4:$J$203="Confirmed")*'Sales Orders'!$G$4:$G$203)*SUMIFS('BOM Mapping'!$K$4:$K$23,'BOM Mapping'!$D$4:$D$23,$A10)+SUMPRODUCT(('Sales Orders'!$E$4:$E$203="Altitude")*('Sales Orders'!$J$4:$J$203="Confirmed")*'Sales Orders'!$G$4:$G$203)*SUMIFS('BOM Mapping'!$L$4:$L$23,'BOM Mapping'!$E$4:$E$23,$A10) | G10: 0 | H10: =MAX(E10,F10)+C10 | I10: =MAX(0,H10-D10-G10) | J10: ='Master Inventory'!D10 | K10: =I10*J10 | L10: =IF(F10>0,"P1 COMMITTED",IF(E10>0,"P2 PLAN",IF(C10>0,"P3 MSL","NONE"))) | M10: =IF(I10>0,"BUY / RFQ","NO BUY") | N10: =IF(I10=0,"",IF(IFERROR(VLOOKUP(A10,'Component Catalogue'!$G$5:$T$76,10,FALSE),1)>1,"PLAN EARLY","NORMAL")) | O10: =K10
A11: ='Master Inventory'!A11 | B11: ='Master Inventory'!C11 | C11: ='Master Inventory'!E11 | D11: ='Master Inventory'!J11 | E11: =SUMIFS('BOM Mapping'!$J$4:$J$23,'BOM Mapping'!$C$4:$C$23,$A11,'BOM Mapping'!$I$4:$I$23,"Approved")*SUM('Monthly Materials'!$D$6:$D$41)+SUMIFS('BOM Mapping'!$K$4:$K$23,'BOM Mapping'!$D$4:$D$23,$A11,'BOM Mapping'!$I$4:$I$23,"Approved")*SUM('Monthly Materials'!$E$6:$E$41)+SUMIFS('BOM Mapping'!$L$4:$L$23,'BOM Mapping'!$E$4:$E$23,$A11,'BOM Mapping'!$I$4:$I$23,"Approved")*SUM('Monthly Materials'!$F$6:$F$41) | F11: =SUMPRODUCT(('Sales Orders'!$E$4:$E$203="Longitude")*('Sales Orders'!$J$4:$J$203="Confirmed")*'Sales Orders'!$G$4:$G$203)*SUMIFS('BOM Mapping'!$J$4:$J$23,'BOM Mapping'!$C$4:$C$23,$A11)+SUMPRODUCT(('Sales Orders'!$E$4:$E$203="Latitude")*('Sales Orders'!$J$4:$J$203="Confirmed")*'Sales Orders'!$G$4:$G$203)*SUMIFS('BOM Mapping'!$K$4:$K$23,'BOM Mapping'!$D$4:$D$23,$A11)+SUMPRODUCT(('Sales Orders'!$E$4:$E$203="Altitude")*('Sales Orders'!$J$4:$J$203="Confirmed")*'Sales Orders'!$G$4:$G$203)*SUMIFS('BOM Mapping'!$L$4:$L$23,'BOM Mapping'!$E$4:$E$23,$A11) | G11: 0 | H11: =MAX(E11,F11)+C11 | I11: =MAX(0,H11-D11-G11) | J11: ='Master Inventory'!D11 | K11: =I11*J11 | L11: =IF(F11>0,"P1 COMMITTED",IF(E11>0,"P2 PLAN",IF(C11>0,"P3 MSL","NONE"))) | M11: =IF(I11>0,"BUY / RFQ","NO BUY") | N11: =IF(I11=0,"",IF(IFERROR(VLOOKUP(A11,'Component Catalogue'!$G$5:$T$76,10,FALSE),1)>1,"PLAN EARLY","NORMAL")) | O11: =K11
A12: ='Master Inventory'!A12 | B12: ='Master Inventory'!C12 | C12: ='Master Inventory'!E12 | D12: ='Master Inventory'!J12 | E12: =SUMIFS('BOM Mapping'!$J$4:$J$23,'BOM Mapping'!$C$4:$C$23,$A12,'BOM Mapping'!$I$4:$I$23,"Approved")*SUM('Monthly Materials'!$D$6:$D$41)+SUMIFS('BOM Mapping'!$K$4:$K$23,'BOM Mapping'!$D$4:$D$23,$A12,'BOM Mapping'!$I$4:$I$23,"Approved")*SUM('Monthly Materials'!$E$6:$E$41)+SUMIFS('BOM Mapping'!$L$4:$L$23,'BOM Mapping'!$E$4:$E$23,$A12,'BOM Mapping'!$I$4:$I$23,"Approved")*SUM('Monthly Materials'!$F$6:$F$41) | F12: =SUMPRODUCT(('Sales Orders'!$E$4:$E$203="Longitude")*('Sales Orders'!$J$4:$J$203="Confirmed")*'Sales Orders'!$G$4:$G$203)*SUMIFS('BOM Mapping'!$J$4:$J$23,'BOM Mapping'!$C$4:$C$23,$A12)+SUMPRODUCT(('Sales Orders'!$E$4:$E$203="Latitude")*('Sales Orders'!$J$4:$J$203="Confirmed")*'Sales Orders'!$G$4:$G$203)*SUMIFS('BOM Mapping'!$K$4:$K$23,'BOM Mapping'!$D$4:$D$23,$A12)+SUMPRODUCT(('Sales Orders'!$E$4:$E$203="Altitude")*('Sales Orders'!$J$4:$J$203="Confirmed")*'Sales Orders'!$G$4:$G$203)*SUMIFS('BOM Mapping'!$L$4:$L$23,'BOM Mapping'!$E$4:$E$23,$A12) | G12: 0 | H12: =MAX(E12,F12)+C12 | I12: =MAX(0,H12-D12-G12) | J12: ='Master Inventory'!D12 | K12: =I12*J12 | L12: =IF(F12>0,"P1 COMMITTED",IF(E12>0,"P2 PLAN",IF(C12>0,"P3 MSL","NONE"))) | M12: =IF(I12>0,"BUY / RFQ","NO BUY") | N12: =IF(I12=0,"",IF(IFERROR(VLOOKUP(A12,'Component Catalogue'!$G$5:$T$76,10,FALSE),1)>1,"PLAN EARLY","NORMAL")) | O12: =K12
A13: ='Master Inventory'!A13 | B13: ='Master Inventory'!C13 | C13: ='Master Inventory'!E13 | D13: ='Master Inventory'!J13 | E13: =SUMIFS('BOM Mapping'!$J$4:$J$23,'BOM Mapping'!$C$4:$C$23,$A13,'BOM Mapping'!$I$4:$I$23,"Approved")*SUM('Monthly Materials'!$D$6:$D$41)+SUMIFS('BOM Mapping'!$K$4:$K$23,'BOM Mapping'!$D$4:$D$23,$A13,'BOM Mapping'!$I$4:$I$23,"Approved")*SUM('Monthly Materials'!$E$6:$E$41)+SUMIFS('BOM Mapping'!$L$4:$L$23,'BOM Mapping'!$E$4:$E$23,$A13,'BOM Mapping'!$I$4:$I$23,"Approved")*SUM('Monthly Materials'!$F$6:$F$41) | F13: =SUMPRODUCT(('Sales Orders'!$E$4:$E$203="Longitude")*('Sales Orders'!$J$4:$J$203="Confirmed")*'Sales Orders'!$G$4:$G$203)*SUMIFS('BOM Mapping'!$J$4:$J$23,'BOM Mapping'!$C$4:$C$23,$A13)+SUMPRODUCT(('Sales Orders'!$E$4:$E$203="Latitude")*('Sales Orders'!$J$4:$J$203="Confirmed")*'Sales Orders'!$G$4:$G$203)*SUMIFS('BOM Mapping'!$K$4:$K$23,'BOM Mapping'!$D$4:$D$23,$A13)+SUMPRODUCT(('Sales Orders'!$E$4:$E$203="Altitude")*('Sales Orders'!$J$4:$J$203="Confirmed")*'Sales Orders'!$G$4:$G$203)*SUMIFS('BOM Mapping'!$L$4:$L$23,'BOM Mapping'!$E$4:$E$23,$A13) | G13: 0 | H13: =MAX(E13,F13)+C13 | I13: =MAX(0,H13-D13-G13) | J13: ='Master Inventory'!D13 | K13: =I13*J13 | L13: =IF(F13>0,"P1 COMMITTED",IF(E13>0,"P2 PLAN",IF(C13>0,"P3 MSL","NONE"))) | M13: =IF(I13>0,"BUY / RFQ","NO BUY") | N13: =IF(I13=0,"",IF(IFERROR(VLOOKUP(A13,'Component Catalogue'!$G$5:$T$76,10,FALSE),1)>1,"PLAN EARLY","NORMAL")) | O13: =K13
A14: ='Master Inventory'!A14 | B14: ='Master Inventory'!C14 | C14: ='Master Inventory'!E14 | D14: ='Master Inventory'!J14 | E14: =SUMIFS('BOM Mapping'!$J$4:$J$23,'BOM Mapping'!$C$4:$C$23,$A14,'BOM Mapping'!$I$4:$I$23,"Approved")*SUM('Monthly Materials'!$D$6:$D$41)+SUMIFS('BOM Mapping'!$K$4:$K$23,'BOM Mapping'!$D$4:$D$23,$A14,'BOM Mapping'!$I$4:$I$23,"Approved")*SUM('Monthly Materials'!$E$6:$E$41)+SUMIFS('BOM Mapping'!$L$4:$L$23,'BOM Mapping'!$E$4:$E$23,$A14,'BOM Mapping'!$I$4:$I$23,"Approved")*SUM('Monthly Materials'!$F$6:$F$41) | F14: =SUMPRODUCT(('Sales Orders'!$E$4:$E$203="Longitude")*('Sales Orders'!$J$4:$J$203="Confirmed")*'Sales Orders'!$G$4:$G$203)*SUMIFS('BOM Mapping'!$J$4:$J$23,'BOM Mapping'!$C$4:$C$23,$A14)+SUMPRODUCT(('Sales Orders'!$E$4:$E$203="Latitude")*('Sales Orders'!$J$4:$J$203="Confirmed")*'Sales Orders'!$G$4:$G$203)*SUMIFS('BOM Mapping'!$K$4:$K$23,'BOM Mapping'!$D$4:$D$23,$A14)+SUMPRODUCT(('Sales Orders'!$E$4:$E$203="Altitude")*('Sales Orders'!$J$4:$J$203="Confirmed")*'Sales Orders'!$G$4:$G$203)*SUMIFS('BOM Mapping'!$L$4:$L$23,'BOM Mapping'!$E$4:$E$23,$A14) | G14: 0 | H14: =MAX(E14,F14)+C14 | I14: =MAX(0,H14-D14-G14) | J14: ='Master Inventory'!D14 | K14: =I14*J14 | L14: =IF(F14>0,"P1 COMMITTED",IF(E14>0,"P2 PLAN",IF(C14>0,"P3 MSL","NONE"))) | M14: =IF(I14>0,"BUY / RFQ","NO BUY") | N14: =IF(I14=0,"",IF(IFERROR(VLOOKUP(A14,'Component Catalogue'!$G$5:$T$76,10,FALSE),1)>1,"PLAN EARLY","NORMAL")) | O14: =K14
A15: ='Master Inventory'!A15 | B15: ='Master Inventory'!C15 | C15: ='Master Inventory'!E15 | D15: ='Master Inventory'!J15 | E15: =SUMIFS('BOM Mapping'!$J$4:$J$23,'BOM Mapping'!$C$4:$C$23,$A15,'BOM Mapping'!$I$4:$I$23,"Approved")*SUM('Monthly Materials'!$D$6:$D$41)+SUMIFS('BOM Mapping'!$K$4:$K$23,'BOM Mapping'!$D$4:$D$23,$A15,'BOM Mapping'!$I$4:$I$23,"Approved")*SUM('Monthly Materials'!$E$6:$E$41)+SUMIFS('BOM Mapping'!$L$4:$L$23,'BOM Mapping'!$E$4:$E$23,$A15,'BOM Mapping'!$I$4:$I$23,"Approved")*SUM('Monthly Materials'!$F$6:$F$41) | F15: =SUMPRODUCT(('Sales Orders'!$E$4:$E$203="Longitude")*('Sales Orders'!$J$4:$J$203="Confirmed")*'Sales Orders'!$G$4:$G$203)*SUMIFS('BOM Mapping'!$J$4:$J$23,'BOM Mapping'!$C$4:$C$23,$A15)+SUMPRODUCT(('Sales Orders'!$E$4:$E$203="Latitude")*('Sales Orders'!$J$4:$J$203="Confirmed")*'Sales Orders'!$G$4:$G$203)*SUMIFS('BOM Mapping'!$K$4:$K$23,'BOM Mapping'!$D$4:$D$23,$A15)+SUMPRODUCT(('Sales Orders'!$E$4:$E$203="Altitude")*('Sales Orders'!$J$4:$J$203="Confirmed")*'Sales Orders'!$G$4:$G$203)*SUMIFS('BOM Mapping'!$L$4:$L$23,'BOM Mapping'!$E$4:$E$23,$A15) | G15: 0 | H15: =MAX(E15,F15)+C15 | I15: =MAX(0,H15-D15-G15) | J15: ='Master Inventory'!D15 | K15: =I15*J15 | L15: =IF(F15>0,"P1 COMMITTED",IF(E15>0,"P2 PLAN",IF(C15>0,"P3 MSL","NONE"))) | M15: =IF(I15>0,"BUY / RFQ","NO BUY") | N15: =IF(I15=0,"",IF(IFERROR(VLOOKUP(A15,'Component Catalogue'!$G$5:$T$76,10,FALSE),1)>1,"PLAN EARLY","NORMAL")) | O15: =K15
... A69: ='Master Inventory'!A69 | B69: ='Master Inventory'!C69 | C69: ='Master Inventory'!E69 | D69: ='Master Inventory'!J69 | E69: =SUMIFS('BOM Mapping'!$J$4:$J$23,'BOM Mapping'!$C$4:$C$23,$A69,'BOM Mapping'!$I$4:$I$23,"Approved")*SUM('Monthly Materials'!$D$6:$D$41)+SUMIFS('BOM Mapping'!$K$4:$K$23,'BOM Mapping'!$D$4:$D$23,$A69,'BOM Mapping'!$I$4:$I$23,"Approved")*SUM('Monthly Materials'!$E$6:$E$41)+SUMIFS('BOM Mapping'!$L$4:$L$23,'BOM Mapping'!$E$4:$E$23,$A69,'BOM Mapping'!$I$4:$I$23,"Approved")*SUM('Monthly Materials'!$F$6:$F$41) | F69: =SUMPRODUCT(('Sales Orders'!$E$4:$E$203="Longitude")*('Sales Orders'!$J$4:$J$203="Confirmed")*'Sales Orders'!$G$4:$G$203)*SUMIFS('BOM Mapping'!$J$4:$J$23,'BOM Mapping'!$C$4:$C$23,$A69)+SUMPRODUCT(('Sales Orders'!$E$4:$E$203="Latitude")*('Sales Orders'!$J$4:$J$203="Confirmed")*'Sales Orders'!$G$4:$G$203)*SUMIFS('BOM Mapping'!$K$4:$K$23,'BOM Mapping'!$D$4:$D$23,$A69)+SUMPRODUCT(('Sales Orders'!$E$4:$E$203="Altitude")*('Sales Orders'!$J$4:$J$203="Confirmed")*'Sales Orders'!$G$4:$G$203)*SUMIFS('BOM Mapping'!$L$4:$L$23,'BOM Mapping'!$E$4:$E$23,$A69) | G69: 0 | H69: =MAX(E69,F69)+C69 | I69: =MAX(0,H69-D69-G69) | J69: ='Master Inventory'!D69 | K69: =I69*J69 | L69: =IF(F69>0,"P1 COMMITTED",IF(E69>0,"P2 PLAN",IF(C69>0,"P3 MSL","NONE"))) | M69: =IF(I69>0,"BUY / RFQ","NO BUY") | N69: =IF(I69=0,"",IF(IFERROR(VLOOKUP(A69,'Component Catalogue'!$G$5:$T$76,10,FALSE),1)>1,"PLAN EARLY","NORMAL")) | O69: =K69
A70: ='Master Inventory'!A70 | B70: ='Master Inventory'!C70 | C70: ='Master Inventory'!E70 | D70: ='Master Inventory'!J70 | E70: =SUMIFS('BOM Mapping'!$J$4:$J$23,'BOM Mapping'!$C$4:$C$23,$A70,'BOM Mapping'!$I$4:$I$23,"Approved")*SUM('Monthly Materials'!$D$6:$D$41)+SUMIFS('BOM Mapping'!$K$4:$K$23,'BOM Mapping'!$D$4:$D$23,$A70,'BOM Mapping'!$I$4:$I$23,"Approved")*SUM('Monthly Materials'!$E$6:$E$41)+SUMIFS('BOM Mapping'!$L$4:$L$23,'BOM Mapping'!$E$4:$E$23,$A70,'BOM Mapping'!$I$4:$I$23,"Approved")*SUM('Monthly Materials'!$F$6:$F$41) | F70: =SUMPRODUCT(('Sales Orders'!$E$4:$E$203="Longitude")*('Sales Orders'!$J$4:$J$203="Confirmed")*'Sales Orders'!$G$4:$G$203)*SUMIFS('BOM Mapping'!$J$4:$J$23,'BOM Mapping'!$C$4:$C$23,$A70)+SUMPRODUCT(('Sales Orders'!$E$4:$E$203="Latitude")*('Sales Orders'!$J$4:$J$203="Confirmed")*'Sales Orders'!$G$4:$G$203)*SUMIFS('BOM Mapping'!$K$4:$K$23,'BOM Mapping'!$D$4:$D$23,$A70)+SUMPRODUCT(('Sales Orders'!$E$4:$E$203="Altitude")*('Sales Orders'!$J$4:$J$203="Confirmed")*'Sales Orders'!$G$4:$G$203)*SUMIFS('BOM Mapping'!$L$4:$L$23,'BOM Mapping'!$E$4:$E$23,$A70) | H70: =MAX(E70,F70)+C70 | I70: =MAX(0,H70-D70-G70) | J70: ='Master Inventory'!D70 | K70: =I70*J70 | L70: =IF(F70>0,"P1 COMMITTED",IF(E70>0,"P2 PLAN",IF(C70>0,"P3 MSL","NONE"))) | M70: =IF(I70>0,"BUY / RFQ","NO BUY") | N70: =IF(I70=0,"",IF(IFERROR(VLOOKUP(A70,'Component Catalogue'!$G$5:$T$76,10,FALSE),1)>1,"PLAN EARLY","NORMAL")) | O70: =K70
A71: ='Master Inventory'!A71 | B71: ='Master Inventory'!C71 | C71: ='Master Inventory'!E71 | D71: ='Master Inventory'!J71 | E71: =SUMIFS('BOM Mapping'!$J$4:$J$23,'BOM Mapping'!$C$4:$C$23,$A71,'BOM Mapping'!$I$4:$I$23,"Approved")*SUM('Monthly Materials'!$D$6:$D$41)+SUMIFS('BOM Mapping'!$K$4:$K$23,'BOM Mapping'!$D$4:$D$23,$A71,'BOM Mapping'!$I$4:$I$23,"Approved")*SUM('Monthly Materials'!$E$6:$E$41)+SUMIFS('BOM Mapping'!$L$4:$L$23,'BOM Mapping'!$E$4:$E$23,$A71,'BOM Mapping'!$I$4:$I$23,"Approved")*SUM('Monthly Materials'!$F$6:$F$41) | F71: =SUMPRODUCT(('Sales Orders'!$E$4:$E$203="Longitude")*('Sales Orders'!$J$4:$J$203="Confirmed")*'Sales Orders'!$G$4:$G$203)*SUMIFS('BOM Mapping'!$J$4:$J$23,'BOM Mapping'!$C$4:$C$23,$A71)+SUMPRODUCT(('Sales Orders'!$E$4:$E$203="Latitude")*('Sales Orders'!$J$4:$J$203="Confirmed")*'Sales Orders'!$G$4:$G$203)*SUMIFS('BOM Mapping'!$K$4:$K$23,'BOM Mapping'!$D$4:$D$23,$A71)+SUMPRODUCT(('Sales Orders'!$E$4:$E$203="Altitude")*('Sales Orders'!$J$4:$J$203="Confirmed")*'Sales Orders'!$G$4:$G$203)*SUMIFS('BOM Mapping'!$L$4:$L$23,'BOM Mapping'!$E$4:$E$23,$A71) | H71: =MAX(E71,F71)+C71 | I71: =MAX(0,H71-D71-G71) | J71: ='Master Inventory'!D71 | K71: =I71*J71 | L71: =IF(F71>0,"P1 COMMITTED",IF(E71>0,"P2 PLAN",IF(C71>0,"P3 MSL","NONE"))) | M71: =IF(I71>0,"BUY / RFQ","NO BUY") | N71: =IF(I71=0,"",IF(IFERROR(VLOOKUP(A71,'Component Catalogue'!$G$5:$T$76,10,FALSE),1)>1,"PLAN EARLY","NORMAL")) | O71: =K71
A72: ='Master Inventory'!A72 | B72: ='Master Inventory'!C72 | C72: ='Master Inventory'!E72 | D72: ='Master Inventory'!J72 | E72: =SUMIFS('BOM Mapping'!$J$4:$J$23,'BOM Mapping'!$C$4:$C$23,$A72,'BOM Mapping'!$I$4:$I$23,"Approved")*SUM('Monthly Materials'!$D$6:$D$41)+SUMIFS('BOM Mapping'!$K$4:$K$23,'BOM Mapping'!$D$4:$D$23,$A72,'BOM Mapping'!$I$4:$I$23,"Approved")*SUM('Monthly Materials'!$E$6:$E$41)+SUMIFS('BOM Mapping'!$L$4:$L$23,'BOM Mapping'!$E$4:$E$23,$A72,'BOM Mapping'!$I$4:$I$23,"Approved")*SUM('Monthly Materials'!$F$6:$F$41) | F72: =SUMPRODUCT(('Sales Orders'!$E$4:$E$203="Longitude")*('Sales Orders'!$J$4:$J$203="Confirmed")*'Sales Orders'!$G$4:$G$203)*SUMIFS('BOM Mapping'!$J$4:$J$23,'BOM Mapping'!$C$4:$C$23,$A72)+SUMPRODUCT(('Sales Orders'!$E$4:$E$203="Latitude")*('Sales Orders'!$J$4:$J$203="Confirmed")*'Sales Orders'!$G$4:$G$203)*SUMIFS('BOM Mapping'!$K$4:$K$23,'BOM Mapping'!$D$4:$D$23,$A72)+SUMPRODUCT(('Sales Orders'!$E$4:$E$203="Altitude")*('Sales Orders'!$J$4:$J$203="Confirmed")*'Sales Orders'!$G$4:$G$203)*SUMIFS('BOM Mapping'!$L$4:$L$23,'BOM Mapping'!$E$4:$E$23,$A72) | H72: =MAX(E72,F72)+C72 | I72: =MAX(0,H72-D72-G72) | J72: ='Master Inventory'!D72 | K72: =I72*J72 | L72: =IF(F72>0,"P1 COMMITTED",IF(E72>0,"P2 PLAN",IF(C72>0,"P3 MSL","NONE"))) | M72: =IF(I72>0,"BUY / RFQ","NO BUY") | N72: =IF(I72=0,"",IF(IFERROR(VLOOKUP(A72,'Component Catalogue'!$G$5:$T$76,10,FALSE),1)>1,"PLAN EARLY","NORMAL")) | O72: =K72
A73: ='Master Inventory'!A73 | B73: ='Master Inventory'!C73 | C73: ='Master Inventory'!E73 | D73: ='Master Inventory'!J73 | E73: =SUMIFS('BOM Mapping'!$J$4:$J$23,'BOM Mapping'!$C$4:$C$23,$A73,'BOM Mapping'!$I$4:$I$23,"Approved")*SUM('Monthly Materials'!$D$6:$D$41)+SUMIFS('BOM Mapping'!$K$4:$K$23,'BOM Mapping'!$D$4:$D$23,$A73,'BOM Mapping'!$I$4:$I$23,"Approved")*SUM('Monthly Materials'!$E$6:$E$41)+SUMIFS('BOM Mapping'!$L$4:$L$23,'BOM Mapping'!$E$4:$E$23,$A73,'BOM Mapping'!$I$4:$I$23,"Approved")*SUM('Monthly Materials'!$F$6:$F$41) | F73: =SUMPRODUCT(('Sales Orders'!$E$4:$E$203="Longitude")*('Sales Orders'!$J$4:$J$203="Confirmed")*'Sales Orders'!$G$4:$G$203)*SUMIFS('BOM Mapping'!$J$4:$J$23,'BOM Mapping'!$C$4:$C$23,$A73)+SUMPRODUCT(('Sales Orders'!$E$4:$E$203="Latitude")*('Sales Orders'!$J$4:$J$203="Confirmed")*'Sales Orders'!$G$4:$G$203)*SUMIFS('BOM Mapping'!$K$4:$K$23,'BOM Mapping'!$D$4:$D$23,$A73)+SUMPRODUCT(('Sales Orders'!$E$4:$E$203="Altitude")*('Sales Orders'!$J$4:$J$203="Confirmed")*'Sales Orders'!$G$4:$G$203)*SUMIFS('BOM Mapping'!$L$4:$L$23,'BOM Mapping'!$E$4:$E$23,$A73) | H73: =MAX(E73,F73)+C73 | I73: =MAX(0,H73-D73-G73) | J73: ='Master Inventory'!D73 | K73: =I73*J73 | L73: =IF(F73>0,"P1 COMMITTED",IF(E73>0,"P2 PLAN",IF(C73>0,"P3 MSL","NONE"))) | M73: =IF(I73>0,"BUY / RFQ","NO BUY") | N73: =IF(I73=0,"",IF(IFERROR(VLOOKUP(A73,'Component Catalogue'!$G$5:$T$76,10,FALSE),1)>1,"PLAN EARLY","NORMAL")) | O73: =K73
A74: ='Master Inventory'!A74 | B74: ='Master Inventory'!C74 | C74: ='Master Inventory'!E74 | D74: ='Master Inventory'!J74 | E74: =SUMIFS('BOM Mapping'!$J$4:$J$23,'BOM Mapping'!$C$4:$C$23,$A74,'BOM Mapping'!$I$4:$I$23,"Approved")*SUM('Monthly Materials'!$D$6:$D$41)+SUMIFS('BOM Mapping'!$K$4:$K$23,'BOM Mapping'!$D$4:$D$23,$A74,'BOM Mapping'!$I$4:$I$23,"Approved")*SUM('Monthly Materials'!$E$6:$E$41)+SUMIFS('BOM Mapping'!$L$4:$L$23,'BOM Mapping'!$E$4:$E$23,$A74,'BOM Mapping'!$I$4:$I$23,"Approved")*SUM('Monthly Materials'!$F$6:$F$41) | F74: =SUMPRODUCT(('Sales Orders'!$E$4:$E$203="Longitude")*('Sales Orders'!$J$4:$J$203="Confirmed")*'Sales Orders'!$G$4:$G$203)*SUMIFS('BOM Mapping'!$J$4:$J$23,'BOM Mapping'!$C$4:$C$23,$A74)+SUMPRODUCT(('Sales Orders'!$E$4:$E$203="Latitude")*('Sales Orders'!$J$4:$J$203="Confirmed")*'Sales Orders'!$G$4:$G$203)*SUMIFS('BOM Mapping'!$K$4:$K$23,'BOM Mapping'!$D$4:$D$23,$A74)+SUMPRODUCT(('Sales Orders'!$E$4:$E$203="Altitude")*('Sales Orders'!$J$4:$J$203="Confirmed")*'Sales Orders'!$G$4:$G$203)*SUMIFS('BOM Mapping'!$L$4:$L$23,'BOM Mapping'!$E$4:$E$23,$A74) | H74: =MAX(E74,F74)+C74 | I74: =MAX(0,H74-D74-G74) | J74: ='Master Inventory'!D74 | K74: =I74*J74 | L74: =IF(F74>0,"P1 COMMITTED",IF(E74>0,"P2 PLAN",IF(C74>0,"P3 MSL","NONE"))) | M74: =IF(I74>0,"BUY / RFQ","NO BUY") | N74: =IF(I74=0,"",IF(IFERROR(VLOOKUP(A74,'Component Catalogue'!$G$5:$T$76,10,FALSE),1)>1,"PLAN EARLY","NORMAL")) | O74: =K74
A75: ='Master Inventory'!A75 | B75: ='Master Inventory'!C75 | C75: ='Master Inventory'!E75 | D75: ='Master Inventory'!J75 | E75: =SUMIFS('BOM Mapping'!$J$4:$J$23,'BOM Mapping'!$C$4:$C$23,$A75,'BOM Mapping'!$I$4:$I$23,"Approved")*SUM('Monthly Materials'!$D$6:$D$41)+SUMIFS('BOM Mapping'!$K$4:$K$23,'BOM Mapping'!$D$4:$D$23,$A75,'BOM Mapping'!$I$4:$I$23,"Approved")*SUM('Monthly Materials'!$E$6:$E$41)+SUMIFS('BOM Mapping'!$L$4:$L$23,'BOM Mapping'!$E$4:$E$23,$A75,'BOM Mapping'!$I$4:$I$23,"Approved")*SUM('Monthly Materials'!$F$6:$F$41) | F75: =SUMPRODUCT(('Sales Orders'!$E$4:$E$203="Longitude")*('Sales Orders'!$J$4:$J$203="Confirmed")*'Sales Orders'!$G$4:$G$203)*SUMIFS('BOM Mapping'!$J$4:$J$23,'BOM Mapping'!$C$4:$C$23,$A75)+SUMPRODUCT(('Sales Orders'!$E$4:$E$203="Latitude")*('Sales Orders'!$J$4:$J$203="Confirmed")*'Sales Orders'!$G$4:$G$203)*SUMIFS('BOM Mapping'!$K$4:$K$23,'BOM Mapping'!$D$4:$D$23,$A75)+SUMPRODUCT(('Sales Orders'!$E$4:$E$203="Altitude")*('Sales Orders'!$J$4:$J$203="Confirmed")*'Sales Orders'!$G$4:$G$203)*SUMIFS('BOM Mapping'!$L$4:$L$23,'BOM Mapping'!$E$4:$E$23,$A75) | H75: =MAX(E75,F75)+C75 | I75: =MAX(0,H75-D75-G75) | J75: ='Master Inventory'!D75 | K75: =I75*J75 | L75: =IF(F75>0,"P1 COMMITTED",IF(E75>0,"P2 PLAN",IF(C75>0,"P3 MSL","NONE"))) | M75: =IF(I75>0,"BUY / RFQ","NO BUY") | N75: =IF(I75=0,"",IF(IFERROR(VLOOKUP(A75,'Component Catalogue'!$G$5:$T$76,10,FALSE),1)>1,"PLAN EARLY","NORMAL")) | O75: =K75

Sheet IBPE Control
A1: VYNDI Integrated Business Planning Engine · deterministic workbook control layer
A3: Control | B3: Classification | C3: Value | D3: Threshold / Authority | E3: Status | F3: Recommended Decision | G3: Lineage | H3: Owner
A4: 36M unit plan | B4: Plan | C4: ='Monthly Funding'!C42 | D4: Approved operating plan | E4: =IF(C4>0,"OK","BLOCK") | F4: ="Maintain approved ramp unless revised" | G4: Approved Plan → Monthly Funding | H4: Planning
A5: Core funding | B5: Plan | C5: =Inputs!B68 | D5: ₹L | E5: =IF(C5=200,"OK","REVIEW") | F5: ="Stage according to T1–T5" | G5: Inputs → Funding | H5: Finance
A6: Additional funding gap | B6: Forecast | C6: =SUM('Monthly Funding'!$M$6:$M$41) | D6: ₹L | E6: =IF(C6>0,"ACTION","OK") | F6: =IF(C6>0,"Raise/slow plan/renegotiate procurement","No action") | G6: Cash model → floor constraint | H6: Founder/Finance
A7: Inventory ATP shortage | B7: Committed/Actual | C7: =COUNTIF('Master Inventory'!L4:L69,"OUT") | D7: 0 stockouts | E7: =IF(C7=0,"OK","ACTION") | F7: =IF(C7>0,"Prioritise committed demand + MSL RFQs","No action") | G7: Movements − reservations → ATP | H7: Supply
A8: Procurement buy value | B8: Forecast | C8: =SUM('Procurement Plan'!$K$4:$K$75) | D8: ₹ | E8: =IF(C8>0,"ACTION","OK") | F8: ="Approve RFQs only; forecast never posts PO" | G8: Canonical BOM → Inventory ATP → Procurement → MRP Cash Bridge → Funding | H8: Supply/Finance
A9: Confirmed order value | B9: Committed | C9: =SUMIFS('Sales Orders'!I4:I53,'Sales Orders'!J4:J53,"Confirmed") | D9: ₹L | E9: =IF(C9>0,"ACTIVE","NONE") | F9: ="Release job cards only against approved BOM" | G9: Sales Orders → Job Cards | H9: Commercial/Production
A10: Released job cards | B10: Committed | C10: =COUNTIF('Job Cards'!G4:G53,"RELEASED") | D10: Count | E10: =IF(C10=COUNTIF('Sales Orders'!M4:M53,"YES"),"OK","REVIEW") | F10: ="Reconcile order revision before production" | G10: Confirmed Order → Job Card | H10: Production
A11: Traveller failed gates | B11: Actual | C11: =COUNTIF(Traveller!L4:L403,"Fail") | D11: 0 failures | E11: =IF(C11=0,"OK","HOLD") | F11: =IF(C11>0,"Hold affected job; open NCR","No action") | G11: Traveller → Quality Gate | H11: Quality
A12: Supplier/PO authority | B12: Master/Committed | C12: Supplier Master → PR → PO | D12: Approved/Open PO only | E12: OK | F12: No forecast recommendation creates supplier commitment | G12: MRP → PR → PO → GRN | H12: Supply/Finance
A13: FIFO valuation | B13: Actual | C13: GRN → FIFO layer → Allocation | D13: No negative layer balance | E13: OK | F13: Allocate oldest released layer first | G13: GRN / Movement / Job Card | H13: Inventory/Finance
A14: Capacity planning | B14: Plan/Committed | C14: Job Card × routing standard | D14: No effective-hour breach | E14: OK | F14: Escalate capacity shortfall before release | G14: Job Cards → Work Centre → Capacity | H14: Production
A15: Transaction truth | B15: Governance | C15: Ledger-specific truth classes | D15: Plan ≠ Committed ≠ Actual | E15: OK | F15: Status-derived truth; no volatile timestamps | G15: Orders/Reservations/Movements/PO/GRN | H15: Governance
A16: Decision governance | B16: Governance | C16: IBPE finding → decision register | D16: Owner + decision + evidence | E16: OK | F16: Close decision only with evidence | G16: IBPE Control → Decision Register | H16: Founder/Governance
A17: Architecture version | B17: Governance | C17: v5 Operational Execution & Governance | D17: v4 MRP/cash preserved | E17: OK | F17: Operate through controlled transaction chain | G17: v4 core + v5 execution layer | H17: System

Sheet Audit Trail
A1: Audit / Decision Evidence Register
A3: Event ID | B3: Timestamp | C3: Object Type | D3: Object ID | E3: Revision | F3: Action | G3: Actor | H3: Approval Status | I3: Evidence Ref | J3: Rationale
A4: =IF(D4="","","AUD-"&TEXT(ROW()-3,"0000")) | B4: Model | C4: BOM Mapping | D4: Made BOM Mapping the single canonical model-specific BOM authority | E4: Correction | F4: IBPE parity | G4: BOM Mapping J:L | H4: MRP/Job Material | I4: Open | J4: 2026-09-08
A5: =IF(D5="","","AUD-"&TEXT(ROW()-3,"0000")) | B5: Inventory | C5: Master Inventory | D5: Removed fixed movement/reservation row ceilings | E5: Correction | F5: Scalability | G5: Movement/Reservation ledgers | H5: ATP | I5: Open | J5: 2026-09-08
A6: =IF(D6="","","AUD-"&TEXT(ROW()-3,"0000")) | B6: Supply | C6: Procurement Plan | D6: Rebased requirements on canonical BOM including raw materials | E6: Correction | F6: MRP integrity | G6: BOM + plan/orders + ATP | H6: Net Buy | I6: Open | J6: 2026-09-08
A7: =IF(D7="","","AUD-"&TEXT(ROW()-3,"0000")) | B7: Finance | C7: MRP Cash Bridge | D7: Connected net procurement recommendation to monthly cash/funding | E7: Correction | F7: Liquidity integrity | G7: Procurement Plan | H7: Monthly Funding | I7: Open | J7: 2026-09-08
A8: =IF(D8="","","AUD-"&TEXT(ROW()-3,"0000")) | B8: Production | C8: Job Material Req | D8: Rewired Job Card material readiness through canonical BOM, ATP and reservations | E8: Correction | F8: Release control | G8: Job Card + BOM + ATP | H8: Release Gate | I8: Open | J8: 2026-09-08
A9: AUD-V5-001 | B9: 2026-09-08 | C9: Supplier Master | D9: Supplier Master | E9: 1 | F9: Added approved-vendor/master-data register | G9: System | H9: Implemented | I9: Supplier Master | J9: No invented supplier/tax facts; evidence required
A10: AUD-V5-002 | B10: 2026-09-08 | C10: Procurement Workflow | D10: PR→PO→GRN | E10: 1 | F10: Added governed procurement transaction chain | G10: System | H10: Implemented | I10: PR / PO / GRN | J10: Forecast recommendation separated from supplier commitment
A11: AUD-V5-003 | B11: 2026-09-08 | C11: FIFO | D11: FIFO Layers + Allocations | E11: 1 | F11: Added lot-level FIFO valuation/allocation control | G11: System | H11: Implemented | I11: FIFO Layers / Allocations | J11: Posted allocations reduce released receipt layers
A12: AUD-V5-004 | B12: 2026-09-08 | C12: Capacity | D12: Capacity Planning | E12: 1 | F12: Added work-centre capacity model linked to Job Cards | G12: System | H12: Implemented | I12: Work Centre Master / Capacity | J12: Released and draft loads vs effective hours
A13: AUD-V5-005 | B13: 2026-09-08 | C13: Truth | D13: Transaction Ledgers | E13: 1 | F13: Added ledger-specific truth classification | G13: System | H13: Implemented | I13: Orders / Reservations / Movements / Job Cards / PO / GRN | J13: Master Inventory stays derived state view
A14: AUD-V5-006 | B14: 2026-09-08 | C14: Governance | D14: Decision Register | E14: 1 | F14: Added decision approval/closure register | G14: System | H14: Implemented | I14: Decision Register | J14: IBPE recommendation to auditable management decision
A15: =IF(D15="","","AUD-"&TEXT(ROW()-3,"0000"))
A16: =IF(D16="","","AUD-"&TEXT(ROW()-3,"0000"))
A17: =IF(D17="","","AUD-"&TEXT(ROW()-3,"0000"))
A18: =IF(D18="","","AUD-"&TEXT(ROW()-3,"0000"))
A19: =IF(D19="","","AUD-"&TEXT(ROW()-3,"0000"))
A20: =IF(D20="","","AUD-"&TEXT(ROW()-3,"0000"))
A21: =IF(D21="","","AUD-"&TEXT(ROW()-3,"0000"))
A22: =IF(D22="","","AUD-"&TEXT(ROW()-3,"0000"))
A23: =IF(D23="","","AUD-"&TEXT(ROW()-3,"0000"))
A24: =IF(D24="","","AUD-"&TEXT(ROW()-3,"0000"))
A25: =IF(D25="","","AUD-"&TEXT(ROW()-3,"0000"))
A26: =IF(D26="","","AUD-"&TEXT(ROW()-3,"0000"))
... A103: =IF(D103="","","AUD-"&TEXT(ROW()-3,"0000"))

Sheet Control Dashboard
A1: VYNDI 36-Month Integrated Operating Workbook
A2: Approved plan → demand → BOM → ATP/reservation → procurement → Job Card → Traveller → finance → audit
A4: Executive KPI | B4: Value | C4: Status / interpretation | F4: Workflow
A5: 36M units | B5: ='Monthly Funding'!C42 | C5: Approved plan volume | F5: 1 | G5: Approved Plan
A6: Core staged funding ₹L | B6: =Inputs!B68 | C6: T1–T5 | F6: 2 | G6: Demand / Orders
A7: Optional standby ₹L | B7: =Inputs!B69 | C7: Contingent | F7: 3 | G7: Approved BOM
A8: Additional funding gap ₹L | B8: =Inputs!B70 | C8: Cash-floor preserving gap | F8: 4 | G8: ATP / Reservation
A9: 36M material cost ₹L | B9: ='Monthly Funding'!F42 | C9: Existing aggregate materials plan | F9: 5 | G9: Procurement
A10: Inventory value ₹ | B10: =SUM('Master Inventory'!N4:N69) | C10: Posted physical stock only | F10: 6 | G10: Job Card
A11: SKUs below MSL / out | B11: =COUNTIF('Master Inventory'!L4:L69,"<>HEALTHY") | C11: Supply risk | F11: 7 | G11: Traveller / Quality
A12: Net procurement buy ₹ | B12: =SUM('Procurement Plan'!K4:K69) | C12: Planning + committed demand reconciled | F12: 8 | G12: Finance / Audit
A13: Confirmed orders ₹L | B13: =SUMIFS('Sales Orders'!I4:I53,'Sales Orders'!J4:J53,"Confirmed") | C13: Committed commercial demand
A14: Released job cards | B14: =COUNTIF('Job Cards'!G4:G53,"RELEASED") | C14: Controlled production releases
A15: Failed traveller gates | B15: =COUNTIF(Traveller!L4:L403,"Fail") | C15: Quality holds
A18: Layer | B18: Workbook authority | C18: Editable? | D18: Purpose
A19: Plan | B19: Inputs / Monthly Funding / Monthly Materials | C19: Inputs only | D19: Approved 36-month plan and cash/material forecast
A20: Catalogue | B20: Component Catalogue | C20: Price/MSL only | D20: Item/category/SKU master; stock never seeded
A21: Actual stock | B21: Inventory Movements → Master Inventory | C21: Posted movements | D21: Physical on-hand, FIFO lot evidence and ATP
A22: Committed demand | B22: Sales Orders + Reservations | C22: Controlled | D22: Order revision and stock allocation
A23: Engineering | B23: BOM Mapping | C23: Controlled approval | D23: Approved BOM-line → SKU authority
A24: Production | B24: Job Cards + Traveller | C24: Status/sign-off | D24: Release and execution traceability
A25: Decision | B25: IBPE Control | C25: Read-only recommendations | D25: Forecast/findings never directly post transactions
A26: Governance | B26: Audit Trail | C26: Append-only in real system | D26: Actor, approval, evidence and rationale
A29: Detailed Operating Cost | B29: Value | C29: Interpretation
A30: 36M Engine OPEX ₹L | B30: ='Monthly Funding'!D42 | C30: Repository finance-engine control total
A31: 36M Detailed OPEX ₹L | B31: ='Monthly Operating Costs'!M41 | C31: Rent + manpower + GST/CA + utilities + admin + travel + outsourcing + consumables
A32: Office equipment purchases ₹L | B32: ='Monthly Operating Costs'!P41 | C32: Setup assets; separate accounting treatment
A33: 36M Operating + Setup ₹L | B33: ='Monthly Operating Costs'!Q41 | C33: OPEX plus office-equipment cash outflow
A34: Outsourcing within OPEX ₹L | B34: ='Monthly Operating Costs'!J41 | C34: Stage-wise professional/engineering external services
A37: Repository Ledger Census | B37: Count | C37: Meaning
A38: Census objects | B38: =COUNTA('Repo Ledger Census'!B5:B25) | C38: Reviewed repository ledger/control objects
A39: Canonical objects | B39: =COUNTIF('Repo Ledger Census'!F5:F25,"YES*") | C39: Use as source of truth within stated truth class
A40: Not fully imported | B40: =COUNTIF('Repo Ledger Census'!H5:H25,"<>YES") | C40: Need live rows, historical numeric data or deeper accounting import
A41: Legacy / noncanonical objects | B41: =COUNTIF('Repo Ledger Census'!F5:F25,"NO*") | C41: Do not promote to parallel truth
A44: v5 Operational Execution & Governance
A45: Control | B45: Value | C45: Interpretation
A46: Approved suppliers | B46: =COUNTIF('Supplier Master'!$K$4:$K$53,"Yes") | C46: Approved vendor master records
A47: Open purchase requisitions | B47: =COUNTIFS('Purchase Requisitions'!$M$4:$M$53,"Approved")+COUNTIFS('Purchase Requisitions'!$M$4:$M$53,"RFQ") | C47: Approved/RFQ requisitions awaiting PO conversion
A48: Committed PO open qty | B48: =SUM('Purchase Orders'!$V$4:$V$53) | C48: External supply commitment still outstanding
A49: Quarantine / rejected GRNs | B49: =COUNTIF('Goods Receipts'!$K$4:$K$53,"Quarantine")+COUNTIF('Goods Receipts'!$K$4:$K$53,"Rejected") | C49: Receipt quality exceptions requiring action
A50: FIFO layers available | B50: =COUNTIF('FIFO Layers'!$O$4:$O$53,"AVAILABLE") | C50: Released FIFO layers with remaining quantity
A51: Capacity shortfall months | B51: =COUNTIF('Capacity Planning'!$N$4:$N$291,"CAPACITY SHORTFALL") | C51: Work-centre/month combinations over effective capacity
A52: Open IBPE decisions | B52: =COUNTIFS('Decision Register'!$M$4:$M$53,"<>Closed",'Decision Register'!$A$4:$A$53,"<>") | C52: Management decisions not yet closed

Sheet Operating Cost Detail
A1: VYNDI Detailed Operating Cost Plan · stage-wise OPEX + setup cash
A2: Blue values are editable proposed allocations. Formula total is constrained to the repository finance-engine OPEX envelope; office equipment is shown separately as setup CAPEX.
A4: Stage | B4: Months | C4: Base OPEX ₹L/mo | D4: Rent ₹L/mo | E4: Payroll & Manpower ₹L/mo | F4: GST/CA Filing ₹L/mo | G4: Utilities/Internet ₹L/mo | H4: Admin/Insurance ₹L/mo | I4: Travel/Marketing ₹L/mo | J4: Outsourcing ₹L/mo | K4: Office Consumables ₹L/mo | L4: Other/Contingency ₹L/mo | M4: Detailed OPEX ₹L/mo | N4: Variance vs Engine | O4: Office Equip Purchase ₹L | P4: Operating + Setup Cash ₹L/mo
A5: S1 Foundation | B5: M1–M3 | C5: 2.8 | D5: 0.3 | E5: 0.8 | F5: 0.08 | G5: 0.12 | H5: 0.15 | I5: 0.15 | J5: 0.9 | K5: 0.1 | L5: 0.2 | M5: =SUM(D5:L5) | N5: =M5-C5 | O5: 0.8 | P5: =M5+O5
A6: S2 Engineering | B6: M4–M8 | C6: 4.2 | D6: 0.45 | E6: 1.25 | F6: 0.1 | G6: 0.18 | H6: 0.2 | I6: 0.25 | J6: 1.35 | K6: 0.12 | L6: 0.3 | M6: =SUM(D6:L6) | N6: =M6-C6 | O6: 1.2 | P6: =M6+O6
A7: S3 Validation | B7: M9–M11 | C7: 6 | D7: 0.6 | E7: 1.85 | F7: 0.12 | G7: 0.23 | H7: 0.25 | I7: 0.35 | J7: 2 | K7: 0.15 | L7: 0.45 | M7: =SUM(D7:L7) | N7: =M7-C7 | O7: 0.9 | P7: =M7+O7
A8: S4 Launch Readiness | B8: M12–M14 | C8: 7.8 | D8: 0.8 | E8: 2.8 | F8: 0.15 | G8: 0.3 | H8: 0.35 | I8: 0.5 | J8: 2.2 | K8: 0.2 | L8: 0.5 | M8: =SUM(D8:L8) | N8: =M8-C8 | O8: 1.1 | P8: =M8+O8
A9: S5 Commercial Scale | B9: M15–M36 | C9: 9.2 | D9: 1 | E9: 4.2 | F9: 0.18 | G9: 0.38 | H9: 0.44 | I9: 0.7 | J9: 1.45 | K9: 0.25 | L9: 0.6 | M9: =SUM(D9:L9) | N9: =M9-C9 | O9: 0.25 | P9: =M9+O9
A12: Source / control | B12: Repository path | C12: Status | D12: Note
A13: Base staged OPEX | B13: https://github.com/shyamsundhar1982/tiger-field-flora-finch/blob/main/src/lib/finance/model.ts | C13: Source baseline | D13: opexFor(): 2.8 / 4.2 / 6.0 / 7.8 / 9.2 ₹L per month relative to launch
A14: Equipment-ledger structure | B14: https://github.com/shyamsundhar1982/tiger-field-flora-finch/blob/main/src/lib/finance/equipment-ledger.ts | C14: Source baseline | D14: Office/Admin, manufacturing, quality-support and consumables ledgers retained
A15: GST/CA governance | B15: https://github.com/shyamsundhar1982/tiger-field-flora-finch/blob/main/src/lib/finance/accounting.ts | C15: Source baseline | D15: GST/tax controls retained; filing fee allocation is planning input

Sheet Manpower & Salary
A1: Manpower & Salary Plan · stage-wise proposed monthly payroll
A3: Role / Cost Pool | B3: S1 HC | C3: S1 ₹L/mo | D3: S2 HC | E3: S2 ₹L/mo | F3: S3 HC | G3: S3 ₹L/mo | H3: S4 HC | I3: S4 ₹L/mo | J3: S5 HC | K3: S5 ₹L/mo | L3: Basis
A4: Founder / MD | B4: 1 | C4: 0.2 | D4: 1 | E4: 0.3 | F4: 1 | G4: 0.4 | H4: 1 | I4: 0.5 | J4: 1 | K4: 0.6 | L4: Lean founder draw; editable
A5: Engineering / Product | B5: 1 | C5: 0.3 | D5: 2 | E5: 0.55 | F5: 2 | G5: 0.75 | H5: 3 | I5: 1.05 | J5: 4 | K5: 1.35 | L5: Core engineering team
A6: Operations / Supply Chain | B6: 0 | C6: 0 | D6: 1 | E6: 0.2 | F6: 1 | G6: 0.3 | H6: 2 | I6: 0.5 | J6: 3 | K6: 0.75 | L6: Ramp with procurement/production
A7: Quality / Compliance | B7: 0 | C7: 0 | D7: 0 | E7: 0 | F7: 1 | G7: 0.25 | H7: 1 | I7: 0.35 | J7: 2 | K7: 0.55 | L7: Validation onward
A8: Finance / Admin | B8: 1 | C8: 0.15 | D8: 1 | E8: 0.2 | F8: 1 | G8: 0.25 | H8: 1 | I8: 0.3 | J8: 2 | K8: 0.45 | L8: Admin/accounts support
A9: Sales / Customer | B9: 0 | C9: 0 | D9: 0 | E9: 0 | F9: 1 | G9: 0.15 | H9: 2 | I9: 0.3 | J9: 3 | K9: 0.5 | L9: Commercial ramp
A10: Benefits / statutory / temp manpower | B10: 0 | C10: 0.15 | D10: 0 | E10: 0 | F10: 0 | G10: 0 | H10: 0 | I10: 0.8 | J10: 0 | K10: 0 | L10: Balancing pool to stage payroll control; editable
A12: TOTAL | B12: =SUM(B4:B10) | C12: =SUM(C4:C10) | D12: =SUM(D4:D10) | E12: =SUM(E4:E10) | F12: =SUM(F4:F10) | G12: =SUM(G4:G10) | H12: =SUM(H4:H10) | I12: =SUM(I4:I10) | ... K12: =SUM(K4:K10)

Sheet Outsourcing Costs
A1: Outsourcing Cost Ledger · stage-wise professional / engineering services
A3: Service | B3: S1 ₹L/mo | C3: S2 ₹L/mo | D3: S3 ₹L/mo | E3: S4 ₹L/mo | F3: S5 ₹L/mo | G3: Cost Type | H3: Owner | I3: Evidence / PO Ref | J3: Notes
A4: CAD / CAE / Industrial Design | B4: 0.3 | C4: 0.45 | D4: 0.3 | E4: 0.15 | F4: 0.05 | G4: Engineering service | H4: Engineering
A5: Prototype / composite specialist support | B5: 0.2 | C5: 0.35 | D5: 0.45 | E5: 0.35 | F5: 0.2 | G5: Engineering service | H5: Engineering/OEM
A6: Testing / lab / certification | B6: 0.05 | C6: 0.2 | D6: 0.55 | E6: 0.55 | F6: 0.15 | G6: Validation service | H6: Quality
A7: Legal / IP / contracts | B7: 0.1 | C7: 0.1 | D7: 0.1 | E7: 0.1 | F7: 0.08 | G7: Professional service | H7: Governance
A8: CA / tax advisory beyond filing | B8: 0.05 | C8: 0.05 | D8: 0.1 | E8: 0.1 | F8: 0.1 | G8: Professional service | H8: Finance
A9: Website / creative / investor collateral | B9: 0.1 | C9: 0.1 | D9: 0.1 | E9: 0.2 | F9: 0.2 | G9: Commercial service | H9: Commercial
A10: Recruitment / HR / specialist consultants | B10: 0.05 | C10: 0.05 | D10: 0.1 | E10: 0.15 | F10: 0.2 | G10: Professional service | H10: Admin
A11: Logistics / sourcing support | B11: 0.05 | C11: 0.05 | D11: 0.15 | E11: 0.3 | F11: 0.47 | G11: Supply service | H11: Supply
A13: TOTAL | B13: =SUM(B4:B11) | C13: =SUM(C4:C11) | D13: =SUM(D4:D11) | E13: =SUM(E4:E11) | F13: =SUM(F4:F11)

Sheet Office Equipment
A1: Office & Administration Equipment Purchase Ledger
A3: Asset | B3: Category | C3: Qty | D3: Unit Cost ₹ | E3: Total ₹L | F3: Purchase Month | G3: Stage | H3: Useful Life Months | I3: Monthly Depn ₹L | J3: Status | K3: Source / Note
A4: Computers / laptops | B4: IT | C4: 4 | D4: 75000 | E4: =C4*D4/100000 | F4: 1 | G4: S1 Foundation | H4: 36 | I4: =E4/H4 | J4: Proposed | K4: Repository officeAdmin/IT category
A5: Tables / desks | B5: Furniture | C5: 4 | D5: 15000 | E5: =C5*D5/100000 | F5: 1 | G5: S1 Foundation | H5: 60 | I5: =E5/H5 | J5: Proposed | K5: Repository officeAdmin/Furniture
A6: Chairs | B6: Furniture | C6: 6 | D6: 8000 | E6: =C6*D6/100000 | F6: 1 | G6: S1 Foundation | H6: 60 | I6: =E6/H6 | J6: Proposed | K6: Repository officeAdmin/Furniture
A7: Air conditioners | B7: Facilities | C7: 2 | D7: 45000 | E7: =C7*D7/100000 | F7: 4 | G7: S2 Engineering | H7: 60 | I7: =E7/H7 | J7: Proposed | K7: Repository officeAdmin/Facilities
A8: Water dispenser | B8: Facilities | C8: 1 | D8: 15000 | E8: =C8*D8/100000 | F8: 4 | G8: S2 Engineering | H8: 60 | I8: =E8/H8 | J8: Proposed | K8: Repository officeAdmin/Facilities
A9: Sofa / meeting seating | B9: Furniture | C9: 1 | D9: 60000 | E9: =C9*D9/100000 | F9: 4 | G9: S2 Engineering | H9: 60 | I9: =E9/H9 | J9: Proposed | K9: Repository officeAdmin/Furniture
A10: Additional engineering workstations | B10: IT | C10: 3 | D10: 100000 | E10: =C10*D10/100000 | F10: 9 | G10: S3 Validation | H10: 36 | I10: =E10/H10 | J10: Proposed | K10: Capacity ramp
A11: QA / admin IT additions | B11: IT | C11: 2 | D11: 75000 | E11: =C11*D11/100000 | F11: 12 | G11: S4 Launch Readiness | H11: 36 | I11: =E11/H11 | J11: Proposed | K11: Launch staffing
A12: Commercial / support laptops | B12: IT | C12: 2 | D12: 75000 | E12: =C12*D12/100000 | F12: 15 | G12: S5 Commercial Scale | H12: 36 | I12: =E12/H12 | J12: Proposed | K12: Post-launch staffing
A14: TOTAL | E14: =SUM(E4:E12)

Sheet Monthly Operating Costs
A1: 36-Month Detailed Operating Cost Projection
A3: Month | B3: Date | C3: Stage | D3: Rent | E3: Payroll | F3: GST/ CA Filing | G3: Utilities | H3: Admin/ Insurance | I3: Travel/ Marketing | J3: Outsourcing | K3: Office Consumables | L3: Other/ Contingency | M3: Detailed OPEX ₹L | N3: Engine OPEX ₹L | O3: Variance | P3: Office Equip ₹L | Q3: Total Operating + Setup ₹L | R3: Source Status
A4: 1 | B4: ='Monthly Funding'!B6 | C4: ='Operating Cost Detail'!A5 | D4: ='Operating Cost Detail'!D5 | E4: ='Operating Cost Detail'!E5 | F4: ='Operating Cost Detail'!F5 | G4: ='Operating Cost Detail'!G5 | H4: ='Operating Cost Detail'!H5 | I4: ='Operating Cost Detail'!I5 | J4: ='Operating Cost Detail'!J5 | K4: ='Operating Cost Detail'!K5 | L4: ='Operating Cost Detail'!L5 | M4: =SUM(D4:L4) | N4: ='Monthly Funding'!D6 | O4: =M4-N4 | P4: =SUMIFS('Office Equipment'!$E$4:$E$12,'Office Equipment'!$F$4:$F$12,A4) | Q4: =M4+P4 | R4: Reconciled to finance-engine OPEX
A5: 2 | B5: ='Monthly Funding'!B7 | C5: ='Operating Cost Detail'!A5 | D5: ='Operating Cost Detail'!D5 | E5: ='Operating Cost Detail'!E5 | F5: ='Operating Cost Detail'!F5 | G5: ='Operating Cost Detail'!G5 | H5: ='Operating Cost Detail'!H5 | I5: ='Operating Cost Detail'!I5 | J5: ='Operating Cost Detail'!J5 | K5: ='Operating Cost Detail'!K5 | L5: ='Operating Cost Detail'!L5 | M5: =SUM(D5:L5) | N5: ='Monthly Funding'!D7 | O5: =M5-N5 | P5: =SUMIFS('Office Equipment'!$E$4:$E$12,'Office Equipment'!$F$4:$F$12,A5) | Q5: =M5+P5 | R5: Reconciled to finance-engine OPEX
A6: 3 | B6: ='Monthly Funding'!B8 | C6: ='Operating Cost Detail'!A5 | D6: ='Operating Cost Detail'!D5 | E6: ='Operating Cost Detail'!E5 | F6: ='Operating Cost Detail'!F5 | G6: ='Operating Cost Detail'!G5 | H6: ='Operating Cost Detail'!H5 | I6: ='Operating Cost Detail'!I5 | J6: ='Operating Cost Detail'!J5 | K6: ='Operating Cost Detail'!K5 | L6: ='Operating Cost Detail'!L5 | M6: =SUM(D6:L6) | N6: ='Monthly Funding'!D8 | O6: =M6-N6 | P6: =SUMIFS('Office Equipment'!$E$4:$E$12,'Office Equipment'!$F$4:$F$12,A6) | Q6: =M6+P6 | R6: Reconciled to finance-engine OPEX
A7: 4 | B7: ='Monthly Funding'!B9 | C7: ='Operating Cost Detail'!A6 | D7: ='Operating Cost Detail'!D6 | E7: ='Operating Cost Detail'!E6 | F7: ='Operating Cost Detail'!F6 | G7: ='Operating Cost Detail'!G6 | H7: ='Operating Cost Detail'!H6 | I7: ='Operating Cost Detail'!I6 | J7: ='Operating Cost Detail'!J6 | K7: ='Operating Cost Detail'!K6 | L7: ='Operating Cost Detail'!L6 | M7: =SUM(D7:L7) | N7: ='Monthly Funding'!D9 | O7: =M7-N7 | P7: =SUMIFS('Office Equipment'!$E$4:$E$12,'Office Equipment'!$F$4:$F$12,A7) | Q7: =M7+P7 | R7: Reconciled to finance-engine OPEX
A8: 5 | B8: ='Monthly Funding'!B10 | C8: ='Operating Cost Detail'!A6 | D8: ='Operating Cost Detail'!D6 | E8: ='Operating Cost Detail'!E6 | F8: ='Operating Cost Detail'!F6 | G8: ='Operating Cost Detail'!G6 | H8: ='Operating Cost Detail'!H6 | I8: ='Operating Cost Detail'!I6 | J8: ='Operating Cost Detail'!J6 | K8: ='Operating Cost Detail'!K6 | L8: ='Operating Cost Detail'!L6 | M8: =SUM(D8:L8) | N8: ='Monthly Funding'!D10 | O8: =M8-N8 | P8: =SUMIFS('Office Equipment'!$E$4:$E$12,'Office Equipment'!$F$4:$F$12,A8) | Q8: =M8+P8 | R8: Reconciled to finance-engine OPEX
A9: 6 | B9: ='Monthly Funding'!B11 | C9: ='Operating Cost Detail'!A6 | D9: ='Operating Cost Detail'!D6 | E9: ='Operating Cost Detail'!E6 | F9: ='Operating Cost Detail'!F6 | G9: ='Operating Cost Detail'!G6 | H9: ='Operating Cost Detail'!H6 | I9: ='Operating Cost Detail'!I6 | J9: ='Operating Cost Detail'!J6 | K9: ='Operating Cost Detail'!K6 | L9: ='Operating Cost Detail'!L6 | M9: =SUM(D9:L9) | N9: ='Monthly Funding'!D11 | O9: =M9-N9 | P9: =SUMIFS('Office Equipment'!$E$4:$E$12,'Office Equipment'!$F$4:$F$12,A9) | Q9: =M9+P9 | R9: Reconciled to finance-engine OPEX
A10: 7 | B10: ='Monthly Funding'!B12 | C10: ='Operating Cost Detail'!A6 | D10: ='Operating Cost Detail'!D6 | E10: ='Operating Cost Detail'!E6 | F10: ='Operating Cost Detail'!F6 | G10: ='Operating Cost Detail'!G6 | H10: ='Operating Cost Detail'!H6 | I10: ='Operating Cost Detail'!I6 | J10: ='Operating Cost Detail'!J6 | K10: ='Operating Cost Detail'!K6 | L10: ='Operating Cost Detail'!L6 | M10: =SUM(D10:L10) | N10: ='Monthly Funding'!D12 | O10: =M10-N10 | P10: =SUMIFS('Office Equipment'!$E$4:$E$12,'Office Equipment'!$F$4:$F$12,A10) | Q10: =M10+P10 | R10: Reconciled to finance-engine OPEX
A11: 8 | B11: ='Monthly Funding'!B13 | C11: ='Operating Cost Detail'!A6 | D11: ='Operating Cost Detail'!D6 | E11: ='Operating Cost Detail'!E6 | F11: ='Operating Cost Detail'!F6 | G11: ='Operating Cost Detail'!G6 | H11: ='Operating Cost Detail'!H6 | I11: ='Operating Cost Detail'!I6 | J11: ='Operating Cost Detail'!J6 | K11: ='Operating Cost Detail'!K6 | L11: ='Operating Cost Detail'!L6 | M11: =SUM(D11:L11) | N11: ='Monthly Funding'!D13 | O11: =M11-N11 | P11: =SUMIFS('Office Equipment'!$E$4:$E$12,'Office Equipment'!$F$4:$F$12,A11) | Q11: =M11+P11 | R11: Reconciled to finance-engine OPEX
A12: 9 | B12: ='Monthly Funding'!B14 | C12: ='Operating Cost Detail'!A7 | D12: ='Operating Cost Detail'!D7 | E12: ='Operating Cost Detail'!E7 | F12: ='Operating Cost Detail'!F7 | G12: ='Operating Cost Detail'!G7 | H12: ='Operating Cost Detail'!H7 | I12: ='Operating Cost Detail'!I7 | J12: ='Operating Cost Detail'!J7 | K12: ='Operating Cost Detail'!K7 | L12: ='Operating Cost Detail'!L7 | M12: =SUM(D12:L12) | N12: ='Monthly Funding'!D14 | O12: =M12-N12 | P12: =SUMIFS('Office Equipment'!$E$4:$E$12,'Office Equipment'!$F$4:$F$12,A12) | Q12: =M12+P12 | R12: Reconciled to finance-engine OPEX
A13: 10 | B13: ='Monthly Funding'!B15 | C13: ='Operating Cost Detail'!A7 | D13: ='Operating Cost Detail'!D7 | E13: ='Operating Cost Detail'!E7 | F13: ='Operating Cost Detail'!F7 | G13: ='Operating Cost Detail'!G7 | H13: ='Operating Cost Detail'!H7 | I13: ='Operating Cost Detail'!I7 | J13: ='Operating Cost Detail'!J7 | K13: ='Operating Cost Detail'!K7 | L13: ='Operating Cost Detail'!L7 | M13: =SUM(D13:L13) | N13: ='Monthly Funding'!D15 | O13: =M13-N13 | P13: =SUMIFS('Office Equipment'!$E$4:$E$12,'Office Equipment'!$F$4:$F$12,A13) | Q13: =M13+P13 | R13: Reconciled to finance-engine OPEX
A14: 11 | B14: ='Monthly Funding'!B16 | C14: ='Operating Cost Detail'!A7 | D14: ='Operating Cost Detail'!D7 | E14: ='Operating Cost Detail'!E7 | F14: ='Operating Cost Detail'!F7 | G14: ='Operating Cost Detail'!G7 | H14: ='Operating Cost Detail'!H7 | I14: ='Operating Cost Detail'!I7 | J14: ='Operating Cost Detail'!J7 | K14: ='Operating Cost Detail'!K7 | L14: ='Operating Cost Detail'!L7 | M14: =SUM(D14:L14) | N14: ='Monthly Funding'!D16 | O14: =M14-N14 | P14: =SUMIFS('Office Equipment'!$E$4:$E$12,'Office Equipment'!$F$4:$F$12,A14) | Q14: =M14+P14 | R14: Reconciled to finance-engine OPEX
A15: 12 | B15: ='Monthly Funding'!B17 | C15: ='Operating Cost Detail'!A8 | D15: ='Operating Cost Detail'!D8 | E15: ='Operating Cost Detail'!E8 | F15: ='Operating Cost Detail'!F8 | G15: ='Operating Cost Detail'!G8 | H15: ='Operating Cost Detail'!H8 | I15: ='Operating Cost Detail'!I8 | J15: ='Operating Cost Detail'!J8 | K15: ='Operating Cost Detail'!K8 | L15: ='Operating Cost Detail'!L8 | M15: =SUM(D15:L15) | N15: ='Monthly Funding'!D17 | O15: =M15-N15 | P15: =SUMIFS('Office Equipment'!$E$4:$E$12,'Office Equipment'!$F$4:$F$12,A15) | Q15: =M15+P15 | R15: Reconciled to finance-engine OPEX
A16: 13 | B16: ='Monthly Funding'!B18 | C16: ='Operating Cost Detail'!A8 | D16: ='Operating Cost Detail'!D8 | E16: ='Operating Cost Detail'!E8 | F16: ='Operating Cost Detail'!F8 | G16: ='Operating Cost Detail'!G8 | H16: ='Operating Cost Detail'!H8 | I16: ='Operating Cost Detail'!I8 | J16: ='Operating Cost Detail'!J8 | K16: ='Operating Cost Detail'!K8 | L16: ='Operating Cost Detail'!L8 | M16: =SUM(D16:L16) | N16: ='Monthly Funding'!D18 | O16: =M16-N16 | P16: =SUMIFS('Office Equipment'!$E$4:$E$12,'Office Equipment'!$F$4:$F$12,A16) | Q16: =M16+P16 | R16: Reconciled to finance-engine OPEX
A17: 14 | B17: ='Monthly Funding'!B19 | C17: ='Operating Cost Detail'!A8 | D17: ='Operating Cost Detail'!D8 | E17: ='Operating Cost Detail'!E8 | F17: ='Operating Cost Detail'!F8 | G17: ='Operating Cost Detail'!G8 | H17: ='Operating Cost Detail'!H8 | I17: ='Operating Cost Detail'!I8 | J17: ='Operating Cost Detail'!J8 | K17: ='Operating Cost Detail'!K8 | L17: ='Operating Cost Detail'!L8 | M17: =SUM(D17:L17) | N17: ='Monthly Funding'!D19 | O17: =M17-N17 | P17: =SUMIFS('Office Equipment'!$E$4:$E$12,'Office Equipment'!$F$4:$F$12,A17) | Q17: =M17+P17 | R17: Reconciled to finance-engine OPEX
A18: 15 | B18: ='Monthly Funding'!B20 | C18: ='Operating Cost Detail'!A9 | D18: ='Operating Cost Detail'!D9 | E18: ='Operating Cost Detail'!E9 | F18: ='Operating Cost Detail'!F9 | G18: ='Operating Cost Detail'!G9 | H18: ='Operating Cost Detail'!H9 | I18: ='Operating Cost Detail'!I9 | J18: ='Operating Cost Detail'!J9 | K18: ='Operating Cost Detail'!K9 | L18: ='Operating Cost Detail'!L9 | M18: =SUM(D18:L18) | N18: ='Monthly Funding'!D20 | O18: =M18-N18 | P18: =SUMIFS('Office Equipment'!$E$4:$E$12,'Office Equipment'!$F$4:$F$12,A18) | Q18: =M18+P18 | R18: Reconciled to finance-engine OPEX
A19: 16 | B19: ='Monthly Funding'!B21 | C19: ='Operating Cost Detail'!A9 | D19: ='Operating Cost Detail'!D9 | E19: ='Operating Cost Detail'!E9 | F19: ='Operating Cost Detail'!F9 | G19: ='Operating Cost Detail'!G9 | H19: ='Operating Cost Detail'!H9 | I19: ='Operating Cost Detail'!I9 | J19: ='Operating Cost Detail'!J9 | K19: ='Operating Cost Detail'!K9 | L19: ='Operating Cost Detail'!L9 | M19: =SUM(D19:L19) | N19: ='Monthly Funding'!D21 | O19: =M19-N19 | P19: =SUMIFS('Office Equipment'!$E$4:$E$12,'Office Equipment'!$F$4:$F$12,A19) | Q19: =M19+P19 | R19: Reconciled to finance-engine OPEX
A20: 17 | B20: ='Monthly Funding'!B22 | C20: ='Operating Cost Detail'!A9 | D20: ='Operating Cost Detail'!D9 | E20: ='Operating Cost Detail'!E9 | F20: ='Operating Cost Detail'!F9 | G20: ='Operating Cost Detail'!G9 | H20: ='Operating Cost Detail'!H9 | I20: ='Operating Cost Detail'!I9 | J20: ='Operating Cost Detail'!J9 | K20: ='Operating Cost Detail'!K9 | L20: ='Operating Cost Detail'!L9 | M20: =SUM(D20:L20) | N20: ='Monthly Funding'!D22 | O20: =M20-N20 | P20: =SUMIFS('Office Equipment'!$E$4:$E$12,'Office Equipment'!$F$4:$F$12,A20) | Q20: =M20+P20 | R20: Reconciled to finance-engine OPEX
A21: 18 | B21: ='Monthly Funding'!B23 | C21: ='Operating Cost Detail'!A9 | D21: ='Operating Cost Detail'!D9 | E21: ='Operating Cost Detail'!E9 | F21: ='Operating Cost Detail'!F9 | G21: ='Operating Cost Detail'!G9 | H21: ='Operating Cost Detail'!H9 | I21: ='Operating Cost Detail'!I9 | J21: ='Operating Cost Detail'!J9 | K21: ='Operating Cost Detail'!K9 | L21: ='Operating Cost Detail'!L9 | M21: =SUM(D21:L21) | N21: ='Monthly Funding'!D23 | O21: =M21-N21 | P21: =SUMIFS('Office Equipment'!$E$4:$E$12,'Office Equipment'!$F$4:$F$12,A21) | Q21: =M21+P21 | R21: Reconciled to finance-engine OPEX
A22: 19 | B22: ='Monthly Funding'!B24 | C22: ='Operating Cost Detail'!A9 | D22: ='Operating Cost Detail'!D9 | E22: ='Operating Cost Detail'!E9 | F22: ='Operating Cost Detail'!F9 | G22: ='Operating Cost Detail'!G9 | H22: ='Operating Cost Detail'!H9 | I22: ='Operating Cost Detail'!I9 | J22: ='Operating Cost Detail'!J9 | K22: ='Operating Cost Detail'!K9 | L22: ='Operating Cost Detail'!L9 | M22: =SUM(D22:L22) | N22: ='Monthly Funding'!D24 | O22: =M22-N22 | P22: =SUMIFS('Office Equipment'!$E$4:$E$12,'Office Equipment'!$F$4:$F$12,A22) | Q22: =M22+P22 | R22: Reconciled to finance-engine OPEX
A23: 20 | B23: ='Monthly Funding'!B25 | C23: ='Operating Cost Detail'!A9 | D23: ='Operating Cost Detail'!D9 | E23: ='Operating Cost Detail'!E9 | F23: ='Operating Cost Detail'!F9 | G23: ='Operating Cost Detail'!G9 | H23: ='Operating Cost Detail'!H9 | I23: ='Operating Cost Detail'!I9 | J23: ='Operating Cost Detail'!J9 | K23: ='Operating Cost Detail'!K9 | L23: ='Operating Cost Detail'!L9 | M23: =SUM(D23:L23) | N23: ='Monthly Funding'!D25 | O23: =M23-N23 | P23: =SUMIFS('Office Equipment'!$E$4:$E$12,'Office Equipment'!$F$4:$F$12,A23) | Q23: =M23+P23 | R23: Reconciled to finance-engine OPEX
A24: 21 | B24: ='Monthly Funding'!B26 | C24: ='Operating Cost Detail'!A9 | D24: ='Operating Cost Detail'!D9 | E24: ='Operating Cost Detail'!E9 | F24: ='Operating Cost Detail'!F9 | G24: ='Operating Cost Detail'!G9 | H24: ='Operating Cost Detail'!H9 | I24: ='Operating Cost Detail'!I9 | J24: ='Operating Cost Detail'!J9 | K24: ='Operating Cost Detail'!K9 | L24: ='Operating Cost Detail'!L9 | M24: =SUM(D24:L24) | N24: ='Monthly Funding'!D26 | O24: =M24-N24 | P24: =SUMIFS('Office Equipment'!$E$4:$E$12,'Office Equipment'!$F$4:$F$12,A24) | Q24: =M24+P24 | R24: Reconciled to finance-engine OPEX
A25: 22 | B25: ='Monthly Funding'!B27 | C25: ='Operating Cost Detail'!A9 | D25: ='Operating Cost Detail'!D9 | E25: ='Operating Cost Detail'!E9 | F25: ='Operating Cost Detail'!F9 | G25: ='Operating Cost Detail'!G9 | H25: ='Operating Cost Detail'!H9 | I25: ='Operating Cost Detail'!I9 | J25: ='Operating Cost Detail'!J9 | K25: ='Operating Cost Detail'!K9 | L25: ='Operating Cost Detail'!L9 | M25: =SUM(D25:L25) | N25: ='Monthly Funding'!D27 | O25: =M25-N25 | P25: =SUMIFS('Office Equipment'!$E$4:$E$12,'Office Equipment'!$F$4:$F$12,A25) | Q25: =M25+P25 | R25: Reconciled to finance-engine OPEX
A26: 23 | B26: ='Monthly Funding'!B28 | C26: ='Operating Cost Detail'!A9 | D26: ='Operating Cost Detail'!D9 | E26: ='Operating Cost Detail'!E9 | F26: ='Operating Cost Detail'!F9 | G26: ='Operating Cost Detail'!G9 | H26: ='Operating Cost Detail'!H9 | I26: ='Operating Cost Detail'!I9 | J26: ='Operating Cost Detail'!J9 | K26: ='Operating Cost Detail'!K9 | L26: ='Operating Cost Detail'!L9 | M26: =SUM(D26:L26) | N26: ='Monthly Funding'!D28 | O26: =M26-N26 | P26: =SUMIFS('Office Equipment'!$E$4:$E$12,'Office Equipment'!$F$4:$F$12,A26) | Q26: =M26+P26 | R26: Reconciled to finance-engine OPEX
A27: 24 | B27: ='Monthly Funding'!B29 | C27: ='Operating Cost Detail'!A9 | D27: ='Operating Cost Detail'!D9 | E27: ='Operating Cost Detail'!E9 | F27: ='Operating Cost Detail'!F9 | G27: ='Operating Cost Detail'!G9 | H27: ='Operating Cost Detail'!H9 | I27: ='Operating Cost Detail'!I9 | J27: ='Operating Cost Detail'!J9 | K27: ='Operating Cost Detail'!K9 | L27: ='Operating Cost Detail'!L9 | M27: =SUM(D27:L27) | N27: ='Monthly Funding'!D29 | O27: =M27-N27 | P27: =SUMIFS('Office Equipment'!$E$4:$E$12,'Office Equipment'!$F$4:$F$12,A27) | Q27: =M27+P27 | R27: Reconciled to finance-engine OPEX
A28: 25 | B28: ='Monthly Funding'!B30 | C28: ='Operating Cost Detail'!A9 | D28: ='Operating Cost Detail'!D9 | E28: ='Operating Cost Detail'!E9 | F28: ='Operating Cost Detail'!F9 | G28: ='Operating Cost Detail'!G9 | H28: ='Operating Cost Detail'!H9 | I28: ='Operating Cost Detail'!I9 | J28: ='Operating Cost Detail'!J9 | K28: ='Operating Cost Detail'!K9 | L28: ='Operating Cost Detail'!L9 | M28: =SUM(D28:L28) | N28: ='Monthly Funding'!D30 | O28: =M28-N28 | P28: =SUMIFS('Office Equipment'!$E$4:$E$12,'Office Equipment'!$F$4:$F$12,A28) | Q28: =M28+P28 | R28: Reconciled to finance-engine OPEX
A29: 26 | B29: ='Monthly Funding'!B31 | C29: ='Operating Cost Detail'!A9 | D29: ='Operating Cost Detail'!D9 | E29: ='Operating Cost Detail'!E9 | F29: ='Operating Cost Detail'!F9 | G29: ='Operating Cost Detail'!G9 | H29: ='Operating Cost Detail'!H9 | I29: ='Operating Cost Detail'!I9 | J29: ='Operating Cost Detail'!J9 | K29: ='Operating Cost Detail'!K9 | L29: ='Operating Cost Detail'!L9 | M29: =SUM(D29:L29) | N29: ='Monthly Funding'!D31 | O29: =M29-N29 | P29: =SUMIFS('Office Equipment'!$E$4:$E$12,'Office Equipment'!$F$4:$F$12,A29) | Q29: =M29+P29 | R29: Reconciled to finance-engine OPEX
A30: 27 | B30: ='Monthly Funding'!B32 | C30: ='Operating Cost Detail'!A9 | D30: ='Operating Cost Detail'!D9 | E30: ='Operating Cost Detail'!E9 | F30: ='Operating Cost Detail'!F9 | G30: ='Operating Cost Detail'!G9 | H30: ='Operating Cost Detail'!H9 | I30: ='Operating Cost Detail'!I9 | J30: ='Operating Cost Detail'!J9 | K30: ='Operating Cost Detail'!K9 | L30: ='Operating Cost Detail'!L9 | M30: =SUM(D30:L30) | N30: ='Monthly Funding'!D32 | O30: =M30-N30 | P30: =SUMIFS('Office Equipment'!$E$4:$E$12,'Office Equipment'!$F$4:$F$12,A30) | Q30: =M30+P30 | R30: Reconciled to finance-engine OPEX
A31: 28 | B31: ='Monthly Funding'!B33 | C31: ='Operating Cost Detail'!A9 | D31: ='Operating Cost Detail'!D9 | E31: ='Operating Cost Detail'!E9 | F31: ='Operating Cost Detail'!F9 | G31: ='Operating Cost Detail'!G9 | H31: ='Operating Cost Detail'!H9 | I31: ='Operating Cost Detail'!I9 | J31: ='Operating Cost Detail'!J9 | K31: ='Operating Cost Detail'!K9 | L31: ='Operating Cost Detail'!L9 | M31: =SUM(D31:L31) | N31: ='Monthly Funding'!D33 | O31: =M31-N31 | P31: =SUMIFS('Office Equipment'!$E$4:$E$12,'Office Equipment'!$F$4:$F$12,A31) | Q31: =M31+P31 | R31: Reconciled to finance-engine OPEX
A32: 29 | B32: ='Monthly Funding'!B34 | C32: ='Operating Cost Detail'!A9 | D32: ='Operating Cost Detail'!D9 | E32: ='Operating Cost Detail'!E9 | F32: ='Operating Cost Detail'!F9 | G32: ='Operating Cost Detail'!G9 | H32: ='Operating Cost Detail'!H9 | I32: ='Operating Cost Detail'!I9 | J32: ='Operating Cost Detail'!J9 | K32: ='Operating Cost Detail'!K9 | L32: ='Operating Cost Detail'!L9 | M32: =SUM(D32:L32) | N32: ='Monthly Funding'!D34 | O32: =M32-N32 | P32: =SUMIFS('Office Equipment'!$E$4:$E$12,'Office Equipment'!$F$4:$F$12,A32) | Q32: =M32+P32 | R32: Reconciled to finance-engine OPEX
A33: 30 | B33: ='Monthly Funding'!B35 | C33: ='Operating Cost Detail'!A9 | D33: ='Operating Cost Detail'!D9 | E33: ='Operating Cost Detail'!E9 | F33: ='Operating Cost Detail'!F9 | G33: ='Operating Cost Detail'!G9 | H33: ='Operating Cost Detail'!H9 | I33: ='Operating Cost Detail'!I9 | J33: ='Operating Cost Detail'!J9 | K33: ='Operating Cost Detail'!K9 | L33: ='Operating Cost Detail'!L9 | M33: =SUM(D33:L33) | N33: ='Monthly Funding'!D35 | O33: =M33-N33 | P33: =SUMIFS('Office Equipment'!$E$4:$E$12,'Office Equipment'!$F$4:$F$12,A33) | Q33: =M33+P33 | R33: Reconciled to finance-engine OPEX
A34: 31 | B34: ='Monthly Funding'!B36 | C34: ='Operating Cost Detail'!A9 | D34: ='Operating Cost Detail'!D9 | E34: ='Operating Cost Detail'!E9 | F34: ='Operating Cost Detail'!F9 | G34: ='Operating Cost Detail'!G9 | H34: ='Operating Cost Detail'!H9 | I34: ='Operating Cost Detail'!I9 | J34: ='Operating Cost Detail'!J9 | K34: ='Operating Cost Detail'!K9 | L34: ='Operating Cost Detail'!L9 | M34: =SUM(D34:L34) | N34: ='Monthly Funding'!D36 | O34: =M34-N34 | P34: =SUMIFS('Office Equipment'!$E$4:$E$12,'Office Equipment'!$F$4:$F$12,A34) | Q34: =M34+P34 | R34: Reconciled to finance-engine OPEX
A35: 32 | B35: ='Monthly Funding'!B37 | C35: ='Operating Cost Detail'!A9 | D35: ='Operating Cost Detail'!D9 | E35: ='Operating Cost Detail'!E9 | F35: ='Operating Cost Detail'!F9 | G35: ='Operating Cost Detail'!G9 | H35: ='Operating Cost Detail'!H9 | I35: ='Operating Cost Detail'!I9 | J35: ='Operating Cost Detail'!J9 | K35: ='Operating Cost Detail'!K9 | L35: ='Operating Cost Detail'!L9 | M35: =SUM(D35:L35) | N35: ='Monthly Funding'!D37 | O35: =M35-N35 | P35: =SUMIFS('Office Equipment'!$E$4:$E$12,'Office Equipment'!$F$4:$F$12,A35) | Q35: =M35+P35 | R35: Reconciled to finance-engine OPEX
A36: 33 | B36: ='Monthly Funding'!B38 | C36: ='Operating Cost Detail'!A9 | D36: ='Operating Cost Detail'!D9 | E36: ='Operating Cost Detail'!E9 | F36: ='Operating Cost Detail'!F9 | G36: ='Operating Cost Detail'!G9 | H36: ='Operating Cost Detail'!H9 | I36: ='Operating Cost Detail'!I9 | J36: ='Operating Cost Detail'!J9 | K36: ='Operating Cost Detail'!K9 | L36: ='Operating Cost Detail'!L9 | M36: =SUM(D36:L36) | N36: ='Monthly Funding'!D38 | O36: =M36-N36 | P36: =SUMIFS('Office Equipment'!$E$4:$E$12,'Office Equipment'!$F$4:$F$12,A36) | Q36: =M36+P36 | R36: Reconciled to finance-engine OPEX
A37: 34 | B37: ='Monthly Funding'!B39 | C37: ='Operating Cost Detail'!A9 | D37: ='Operating Cost Detail'!D9 | E37: ='Operating Cost Detail'!E9 | F37: ='Operating Cost Detail'!F9 | G37: ='Operating Cost Detail'!G9 | H37: ='Operating Cost Detail'!H9 | I37: ='Operating Cost Detail'!I9 | J37: ='Operating Cost Detail'!J9 | K37: ='Operating Cost Detail'!K9 | L37: ='Operating Cost Detail'!L9 | M37: =SUM(D37:L37) | N37: ='Monthly Funding'!D39 | O37: =M37-N37 | P37: =SUMIFS('Office Equipment'!$E$4:$E$12,'Office Equipment'!$F$4:$F$12,A37) | Q37: =M37+P37 | R37: Reconciled to finance-engine OPEX
A38: 35 | B38: ='Monthly Funding'!B40 | C38: ='Operating Cost Detail'!A9 | D38: ='Operating Cost Detail'!D9 | E38: ='Operating Cost Detail'!E9 | F38: ='Operating Cost Detail'!F9 | G38: ='Operating Cost Detail'!G9 | H38: ='Operating Cost Detail'!H9 | I38: ='Operating Cost Detail'!I9 | J38: ='Operating Cost Detail'!J9 | K38: ='Operating Cost Detail'!K9 | L38: ='Operating Cost Detail'!L9 | M38: =SUM(D38:L38) | N38: ='Monthly Funding'!D40 | O38: =M38-N38 | P38: =SUMIFS('Office Equipment'!$E$4:$E$12,'Office Equipment'!$F$4:$F$12,A38) | Q38: =M38+P38 | R38: Reconciled to finance-engine OPEX
A39: 36 | B39: ='Monthly Funding'!B41 | C39: ='Operating Cost Detail'!A9 | D39: ='Operating Cost Detail'!D9 | E39: ='Operating Cost Detail'!E9 | F39: ='Operating Cost Detail'!F9 | G39: ='Operating Cost Detail'!G9 | H39: ='Operating Cost Detail'!H9 | I39: ='Operating Cost Detail'!I9 | J39: ='Operating Cost Detail'!J9 | K39: ='Operating Cost Detail'!K9 | L39: ='Operating Cost Detail'!L9 | M39: =SUM(D39:L39) | N39: ='Monthly Funding'!D41 | O39: =M39-N39 | P39: =SUMIFS('Office Equipment'!$E$4:$E$12,'Office Equipment'!$F$4:$F$12,A39) | Q39: =M39+P39 | R39: Reconciled to finance-engine OPEX
A41: 36M TOTAL | D41: =SUM(D4:D39) | E41: =SUM(E4:E39) | F41: =SUM(F4:F39) | G41: =SUM(G4:G39) | H41: =SUM(H4:H39) | I41: =SUM(I4:I39) | J41: =SUM(J4:J39) | K41: =SUM(K4:K39) | ... N41: =SUM(N4:N39) | P41: =SUM(P4:P39) | Q41: =SUM(Q4:Q39)

Sheet Job Material Req
A1: Job Material Requirements · Job Card → Approved BOM → SKU → ATP → Shortage
A2: This is the auditable material-readiness ledger. Job Cards summarize this sheet; the status formula no longer performs a hidden multi-line BOM lookup.
A3: Job Card | B3: Order ID | C3: Model | D3: BOM Line | E3: SKU | F3: Qty / Bike | G3: Job Qty | H3: Required Qty | I3: ATP | J3: Reserved for Job | K3: Uncovered Qty | L3: Readiness
A4: =IF('Job Cards'!$A$4="","",'Job Cards'!$A$4) | B4: =IF(A4="","",'Job Cards'!$B$4) | C4: =IF(A4="","",'Job Cards'!$D$4) | D4: =IF(A4="","",'BOM Mapping'!$A$4) | E4: =IF(C4="Longitude",'BOM Mapping'!$C$4,IF(C4="Latitude",'BOM Mapping'!$D$4,IF(C4="Altitude",'BOM Mapping'!$E$4,""))) | F4: =IF(C4="Longitude",'BOM Mapping'!$J$4,IF(C4="Latitude",'BOM Mapping'!$K$4,IF(C4="Altitude",'BOM Mapping'!$L$4,0))) | G4: =IF(A4="","",'Job Cards'!$E$4) | H4: =IF(E4="","",F4*G4) | I4: =IF(E4="","",IFERROR(VLOOKUP(E4,'Master Inventory'!$A:$N,10,FALSE),0)) | J4: =IF(E4="","",SUMIFS(Reservations!$G:$G,Reservations!$D:$D,A4,Reservations!$E:$E,E4,Reservations!$H:$H,"Active")) | K4: =IF(E4="","",MAX(0,H4-I4-J4)) | L4: =IF(E4="","",IF(K4>0,"SHORTAGE",IF(J4>=H4,"RESERVED","READY TO RESERVE")))
A5: =IF('Job Cards'!$A$4="","",'Job Cards'!$A$4) | B5: =IF(A5="","",'Job Cards'!$B$4) | C5: =IF(A5="","",'Job Cards'!$D$4) | D5: =IF(A5="","",'BOM Mapping'!$A$5) | E5: =IF(C5="Longitude",'BOM Mapping'!$C$5,IF(C5="Latitude",'BOM Mapping'!$D$5,IF(C5="Altitude",'BOM Mapping'!$E$5,""))) | F5: =IF(C5="Longitude",'BOM Mapping'!$J$5,IF(C5="Latitude",'BOM Mapping'!$K$5,IF(C5="Altitude",'BOM Mapping'!$L$5,0))) | G5: =IF(A5="","",'Job Cards'!$E$4) | H5: =IF(E5="","",F5*G5) | I5: =IF(E5="","",IFERROR(VLOOKUP(E5,'Master Inventory'!$A:$N,10,FALSE),0)) | J5: =IF(E5="","",SUMIFS(Reservations!$G:$G,Reservations!$D:$D,A5,Reservations!$E:$E,E5,Reservations!$H:$H,"Active")) | K5: =IF(E5="","",MAX(0,H5-I5-J5)) | L5: =IF(E5="","",IF(K5>0,"SHORTAGE",IF(J5>=H5,"RESERVED","READY TO RESERVE")))
A6: =IF('Job Cards'!$A$4="","",'Job Cards'!$A$4) | B6: =IF(A6="","",'Job Cards'!$B$4) | C6: =IF(A6="","",'Job Cards'!$D$4) | D6: =IF(A6="","",'BOM Mapping'!$A$6) | E6: =IF(C6="Longitude",'BOM Mapping'!$C$6,IF(C6="Latitude",'BOM Mapping'!$D$6,IF(C6="Altitude",'BOM Mapping'!$E$6,""))) | F6: =IF(C6="Longitude",'BOM Mapping'!$J$6,IF(C6="Latitude",'BOM Mapping'!$K$6,IF(C6="Altitude",'BOM Mapping'!$L$6,0))) | G6: =IF(A6="","",'Job Cards'!$E$4) | H6: =IF(E6="","",F6*G6) | I6: =IF(E6="","",IFERROR(VLOOKUP(E6,'Master Inventory'!$A:$N,10,FALSE),0)) | J6: =IF(E6="","",SUMIFS(Reservations!$G:$G,Reservations!$D:$D,A6,Reservations!$E:$E,E6,Reservations!$H:$H,"Active")) | K6: =IF(E6="","",MAX(0,H6-I6-J6)) | L6: =IF(E6="","",IF(K6>0,"SHORTAGE",IF(J6>=H6,"RESERVED","READY TO RESERVE")))
A7: =IF('Job Cards'!$A$4="","",'Job Cards'!$A$4) | B7: =IF(A7="","",'Job Cards'!$B$4) | C7: =IF(A7="","",'Job Cards'!$D$4) | D7: =IF(A7="","",'BOM Mapping'!$A$7) | E7: =IF(C7="Longitude",'BOM Mapping'!$C$7,IF(C7="Latitude",'BOM Mapping'!$D$7,IF(C7="Altitude",'BOM Mapping'!$E$7,""))) | F7: =IF(C7="Longitude",'BOM Mapping'!$J$7,IF(C7="Latitude",'BOM Mapping'!$K$7,IF(C7="Altitude",'BOM Mapping'!$L$7,0))) | G7: =IF(A7="","",'Job Cards'!$E$4) | H7: =IF(E7="","",F7*G7) | I7: =IF(E7="","",IFERROR(VLOOKUP(E7,'Master Inventory'!$A:$N,10,FALSE),0)) | J7: =IF(E7="","",SUMIFS(Reservations!$G:$G,Reservations!$D:$D,A7,Reservations!$E:$E,E7,Reservations!$H:$H,"Active")) | K7: =IF(E7="","",MAX(0,H7-I7-J7)) | L7: =IF(E7="","",IF(K7>0,"SHORTAGE",IF(J7>=H7,"RESERVED","READY TO RESERVE")))
A8: =IF('Job Cards'!$A$4="","",'Job Cards'!$A$4) | B8: =IF(A8="","",'Job Cards'!$B$4) | C8: =IF(A8="","",'Job Cards'!$D$4) | D8: =IF(A8="","",'BOM Mapping'!$A$8) | E8: =IF(C8="Longitude",'BOM Mapping'!$C$8,IF(C8="Latitude",'BOM Mapping'!$D$8,IF(C8="Altitude",'BOM Mapping'!$E$8,""))) | F8: =IF(C8="Longitude",'BOM Mapping'!$J$8,IF(C8="Latitude",'BOM Mapping'!$K$8,IF(C8="Altitude",'BOM Mapping'!$L$8,0))) | G8: =IF(A8="","",'Job Cards'!$E$4) | H8: =IF(E8="","",F8*G8) | I8: =IF(E8="","",IFERROR(VLOOKUP(E8,'Master Inventory'!$A:$N,10,FALSE),0)) | J8: =IF(E8="","",SUMIFS(Reservations!$G:$G,Reservations!$D:$D,A8,Reservations!$E:$E,E8,Reservations!$H:$H,"Active")) | K8: =IF(E8="","",MAX(0,H8-I8-J8)) | L8: =IF(E8="","",IF(K8>0,"SHORTAGE",IF(J8>=H8,"RESERVED","READY TO RESERVE")))
A9: =IF('Job Cards'!$A$4="","",'Job Cards'!$A$4) | B9: =IF(A9="","",'Job Cards'!$B$4) | C9: =IF(A9="","",'Job Cards'!$D$4) | D9: =IF(A9="","",'BOM Mapping'!$A$9) | E9: =IF(C9="Longitude",'BOM Mapping'!$C$9,IF(C9="Latitude",'BOM Mapping'!$D$9,IF(C9="Altitude",'BOM Mapping'!$E$9,""))) | F9: =IF(C9="Longitude",'BOM Mapping'!$J$9,IF(C9="Latitude",'BOM Mapping'!$K$9,IF(C9="Altitude",'BOM Mapping'!$L$9,0))) | G9: =IF(A9="","",'Job Cards'!$E$4) | H9: =IF(E9="","",F9*G9) | I9: =IF(E9="","",IFERROR(VLOOKUP(E9,'Master Inventory'!$A:$N,10,FALSE),0)) | J9: =IF(E9="","",SUMIFS(Reservations!$G:$G,Reservations!$D:$D,A9,Reservations!$E:$E,E9,Reservations!$H:$H,"Active")) | K9: =IF(E9="","",MAX(0,H9-I9-J9)) | L9: =IF(E9="","",IF(K9>0,"SHORTAGE",IF(J9>=H9,"RESERVED","READY TO RESERVE")))
A10: =IF('Job Cards'!$A$4="","",'Job Cards'!$A$4) | B10: =IF(A10="","",'Job Cards'!$B$4) | C10: =IF(A10="","",'Job Cards'!$D$4) | D10: =IF(A10="","",'BOM Mapping'!$A$10) | E10: =IF(C10="Longitude",'BOM Mapping'!$C$10,IF(C10="Latitude",'BOM Mapping'!$D$10,IF(C10="Altitude",'BOM Mapping'!$E$10,""))) | F10: =IF(C10="Longitude",'BOM Mapping'!$J$10,IF(C10="Latitude",'BOM Mapping'!$K$10,IF(C10="Altitude",'BOM Mapping'!$L$10,0))) | G10: =IF(A10="","",'Job Cards'!$E$4) | H10: =IF(E10="","",F10*G10) | I10: =IF(E10="","",IFERROR(VLOOKUP(E10,'Master Inventory'!$A:$N,10,FALSE),0)) | J10: =IF(E10="","",SUMIFS(Reservations!$G:$G,Reservations!$D:$D,A10,Reservations!$E:$E,E10,Reservations!$H:$H,"Active")) | K10: =IF(E10="","",MAX(0,H10-I10-J10)) | L10: =IF(E10="","",IF(K10>0,"SHORTAGE",IF(J10>=H10,"RESERVED","READY TO RESERVE")))
A11: =IF('Job Cards'!$A$4="","",'Job Cards'!$A$4) | B11: =IF(A11="","",'Job Cards'!$B$4) | C11: =IF(A11="","",'Job Cards'!$D$4) | D11: =IF(A11="","",'BOM Mapping'!$A$11) | E11: =IF(C11="Longitude",'BOM Mapping'!$C$11,IF(C11="Latitude",'BOM Mapping'!$D$11,IF(C11="Altitude",'BOM Mapping'!$E$11,""))) | F11: =IF(C11="Longitude",'BOM Mapping'!$J$11,IF(C11="Latitude",'BOM Mapping'!$K$11,IF(C11="Altitude",'BOM Mapping'!$L$11,0))) | G11: =IF(A11="","",'Job Cards'!$E$4) | H11: =IF(E11="","",F11*G11) | I11: =IF(E11="","",IFERROR(VLOOKUP(E11,'Master Inventory'!$A:$N,10,FALSE),0)) | J11: =IF(E11="","",SUMIFS(Reservations!$G:$G,Reservations!$D:$D,A11,Reservations!$E:$E,E11,Reservations!$H:$H,"Active")) | K11: =IF(E11="","",MAX(0,H11-I11-J11)) | L11: =IF(E11="","",IF(K11>0,"SHORTAGE",IF(J11>=H11,"RESERVED","READY TO RESERVE")))
A12: =IF('Job Cards'!$A$4="","",'Job Cards'!$A$4) | B12: =IF(A12="","",'Job Cards'!$B$4) | C12: =IF(A12="","",'Job Cards'!$D$4) | D12: =IF(A12="","",'BOM Mapping'!$A$12) | E12: =IF(C12="Longitude",'BOM Mapping'!$C$12,IF(C12="Latitude",'BOM Mapping'!$D$12,IF(C12="Altitude",'BOM Mapping'!$E$12,""))) | F12: =IF(C12="Longitude",'BOM Mapping'!$J$12,IF(C12="Latitude",'BOM Mapping'!$K$12,IF(C12="Altitude",'BOM Mapping'!$L$12,0))) | G12: =IF(A12="","",'Job Cards'!$E$4) | H12: =IF(E12="","",F12*G12) | I12: =IF(E12="","",IFERROR(VLOOKUP(E12,'Master Inventory'!$A:$N,10,FALSE),0)) | J12: =IF(E12="","",SUMIFS(Reservations!$G:$G,Reservations!$D:$D,A12,Reservations!$E:$E,E12,Reservations!$H:$H,"Active")) | K12: =IF(E12="","",MAX(0,H12-I12-J12)) | L12: =IF(E12="","",IF(K12>0,"SHORTAGE",IF(J12>=H12,"RESERVED","READY TO RESERVE")))
A13: =IF('Job Cards'!$A$4="","",'Job Cards'!$A$4) | B13: =IF(A13="","",'Job Cards'!$B$4) | C13: =IF(A13="","",'Job Cards'!$D$4) | D13: =IF(A13="","",'BOM Mapping'!$A$13) | E13: =IF(C13="Longitude",'BOM Mapping'!$C$13,IF(C13="Latitude",'BOM Mapping'!$D$13,IF(C13="Altitude",'BOM Mapping'!$E$13,""))) | F13: =IF(C13="Longitude",'BOM Mapping'!$J$13,IF(C13="Latitude",'BOM Mapping'!$K$13,IF(C13="Altitude",'BOM Mapping'!$L$13,0))) | G13: =IF(A13="","",'Job Cards'!$E$4) | H13: =IF(E13="","",F13*G13) | I13: =IF(E13="","",IFERROR(VLOOKUP(E13,'Master Inventory'!$A:$N,10,FALSE),0)) | J13: =IF(E13="","",SUMIFS(Reservations!$G:$G,Reservations!$D:$D,A13,Reservations!$E:$E,E13,Reservations!$H:$H,"Active")) | K13: =IF(E13="","",MAX(0,H13-I13-J13)) | L13: =IF(E13="","",IF(K13>0,"SHORTAGE",IF(J13>=H13,"RESERVED","READY TO RESERVE")))
A14: =IF('Job Cards'!$A$4="","",'Job Cards'!$A$4) | B14: =IF(A14="","",'Job Cards'!$B$4) | C14: =IF(A14="","",'Job Cards'!$D$4) | D14: =IF(A14="","",'BOM Mapping'!$A$14) | E14: =IF(C14="Longitude",'BOM Mapping'!$C$14,IF(C14="Latitude",'BOM Mapping'!$D$14,IF(C14="Altitude",'BOM Mapping'!$E$14,""))) | F14: =IF(C14="Longitude",'BOM Mapping'!$J$14,IF(C14="Latitude",'BOM Mapping'!$K$14,IF(C14="Altitude",'BOM Mapping'!$L$14,0))) | G14: =IF(A14="","",'Job Cards'!$E$4) | H14: =IF(E14="","",F14*G14) | I14: =IF(E14="","",IFERROR(VLOOKUP(E14,'Master Inventory'!$A:$N,10,FALSE),0)) | J14: =IF(E14="","",SUMIFS(Reservations!$G:$G,Reservations!$D:$D,A14,Reservations!$E:$E,E14,Reservations!$H:$H,"Active")) | K14: =IF(E14="","",MAX(0,H14-I14-J14)) | L14: =IF(E14="","",IF(K14>0,"SHORTAGE",IF(J14>=H14,"RESERVED","READY TO RESERVE")))
A15: =IF('Job Cards'!$A$4="","",'Job Cards'!$A$4) | B15: =IF(A15="","",'Job Cards'!$B$4) | C15: =IF(A15="","",'Job Cards'!$D$4) | D15: =IF(A15="","",'BOM Mapping'!$A$15) | E15: =IF(C15="Longitude",'BOM Mapping'!$C$15,IF(C15="Latitude",'BOM Mapping'!$D$15,IF(C15="Altitude",'BOM Mapping'!$E$15,""))) | F15: =IF(C15="Longitude",'BOM Mapping'!$J$15,IF(C15="Latitude",'BOM Mapping'!$K$15,IF(C15="Altitude",'BOM Mapping'!$L$15,0))) | G15: =IF(A15="","",'Job Cards'!$E$4) | H15: =IF(E15="","",F15*G15) | I15: =IF(E15="","",IFERROR(VLOOKUP(E15,'Master Inventory'!$A:$N,10,FALSE),0)) | J15: =IF(E15="","",SUMIFS(Reservations!$G:$G,Reservations!$D:$D,A15,Reservations!$E:$E,E15,Reservations!$H:$H,"Active")) | K15: =IF(E15="","",MAX(0,H15-I15-J15)) | L15: =IF(E15="","",IF(K15>0,"SHORTAGE",IF(J15>=H15,"RESERVED","READY TO RESERVE")))
A16: =IF('Job Cards'!$A$4="","",'Job Cards'!$A$4) | B16: =IF(A16="","",'Job Cards'!$B$4) | C16: =IF(A16="","",'Job Cards'!$D$4) | D16: =IF(A16="","",'BOM Mapping'!$A$16) | E16: =IF(C16="Longitude",'BOM Mapping'!$C$16,IF(C16="Latitude",'BOM Mapping'!$D$16,IF(C16="Altitude",'BOM Mapping'!$E$16,""))) | F16: =IF(C16="Longitude",'BOM Mapping'!$J$16,IF(C16="Latitude",'BOM Mapping'!$K$16,IF(C16="Altitude",'BOM Mapping'!$L$16,0))) | G16: =IF(A16="","",'Job Cards'!$E$4) | H16: =IF(E16="","",F16*G16) | I16: =IF(E16="","",IFERROR(VLOOKUP(E16,'Master Inventory'!$A:$N,10,FALSE),0)) | J16: =IF(E16="","",SUMIFS(Reservations!$G:$G,Reservations!$D:$D,A16,Reservations!$E:$E,E16,Reservations!$H:$H,"Active")) | K16: =IF(E16="","",MAX(0,H16-I16-J16)) | L16: =IF(E16="","",IF(K16>0,"SHORTAGE",IF(J16>=H16,"RESERVED","READY TO RESERVE")))
A17: =IF('Job Cards'!$A$4="","",'Job Cards'!$A$4) | B17: =IF(A17="","",'Job Cards'!$B$4) | C17: =IF(A17="","",'Job Cards'!$D$4) | D17: =IF(A17="","",'BOM Mapping'!$A$17) | E17: =IF(C17="Longitude",'BOM Mapping'!$C$17,IF(C17="Latitude",'BOM Mapping'!$D$17,IF(C17="Altitude",'BOM Mapping'!$E$17,""))) | F17: =IF(C17="Longitude",'BOM Mapping'!$J$17,IF(C17="Latitude",'BOM Mapping'!$K$17,IF(C17="Altitude",'BOM Mapping'!$L$17,0))) | G17: =IF(A17="","",'Job Cards'!$E$4) | H17: =IF(E17="","",F17*G17) | I17: =IF(E17="","",IFERROR(VLOOKUP(E17,'Master Inventory'!$A:$N,10,FALSE),0)) | J17: =IF(E17="","",SUMIFS(Reservations!$G:$G,Reservations!$D:$D,A17,Reservations!$E:$E,E17,Reservations!$H:$H,"Active")) | K17: =IF(E17="","",MAX(0,H17-I17-J17)) | L17: =IF(E17="","",IF(K17>0,"SHORTAGE",IF(J17>=H17,"RESERVED","READY TO RESERVE")))
A18: =IF('Job Cards'!$A$4="","",'Job Cards'!$A$4) | B18: =IF(A18="","",'Job Cards'!$B$4) | C18: =IF(A18="","",'Job Cards'!$D$4) | D18: =IF(A18="","",'BOM Mapping'!$A$18) | E18: =IF(C18="Longitude",'BOM Mapping'!$C$18,IF(C18="Latitude",'BOM Mapping'!$D$18,IF(C18="Altitude",'BOM Mapping'!$E$18,""))) | F18: =IF(C18="Longitude",'BOM Mapping'!$J$18,IF(C18="Latitude",'BOM Mapping'!$K$18,IF(C18="Altitude",'BOM Mapping'!$L$18,0))) | G18: =IF(A18="","",'Job Cards'!$E$4) | H18: =IF(E18="","",F18*G18) | I18: =IF(E18="","",IFERROR(VLOOKUP(E18,'Master Inventory'!$A:$N,10,FALSE),0)) | J18: =IF(E18="","",SUMIFS(Reservations!$G:$G,Reservations!$D:$D,A18,Reservations!$E:$E,E18,Reservations!$H:$H,"Active")) | K18: =IF(E18="","",MAX(0,H18-I18-J18)) | L18: =IF(E18="","",IF(K18>0,"SHORTAGE",IF(J18>=H18,"RESERVED","READY TO RESERVE")))
A19: =IF('Job Cards'!$A$4="","",'Job Cards'!$A$4) | B19: =IF(A19="","",'Job Cards'!$B$4) | C19: =IF(A19="","",'Job Cards'!$D$4) | D19: =IF(A19="","",'BOM Mapping'!$A$19) | E19: =IF(C19="Longitude",'BOM Mapping'!$C$19,IF(C19="Latitude",'BOM Mapping'!$D$19,IF(C19="Altitude",'BOM Mapping'!$E$19,""))) | F19: =IF(C19="Longitude",'BOM Mapping'!$J$19,IF(C19="Latitude",'BOM Mapping'!$K$19,IF(C19="Altitude",'BOM Mapping'!$L$19,0))) | G19: =IF(A19="","",'Job Cards'!$E$4) | H19: =IF(E19="","",F19*G19) | I19: =IF(E19="","",IFERROR(VLOOKUP(E19,'Master Inventory'!$A:$N,10,FALSE),0)) | J19: =IF(E19="","",SUMIFS(Reservations!$G:$G,Reservations!$D:$D,A19,Reservations!$E:$E,E19,Reservations!$H:$H,"Active")) | K19: =IF(E19="","",MAX(0,H19-I19-J19)) | L19: =IF(E19="","",IF(K19>0,"SHORTAGE",IF(J19>=H19,"RESERVED","READY TO RESERVE")))
A20: =IF('Job Cards'!$A$4="","",'Job Cards'!$A$4) | B20: =IF(A20="","",'Job Cards'!$B$4) | C20: =IF(A20="","",'Job Cards'!$D$4) | D20: =IF(A20="","",'BOM Mapping'!$A$20) | E20: =IF(C20="Longitude",'BOM Mapping'!$C$20,IF(C20="Latitude",'BOM Mapping'!$D$20,IF(C20="Altitude",'BOM Mapping'!$E$20,""))) | F20: =IF(C20="Longitude",'BOM Mapping'!$J$20,IF(C20="Latitude",'BOM Mapping'!$K$20,IF(C20="Altitude",'BOM Mapping'!$L$20,0))) | G20: =IF(A20="","",'Job Cards'!$E$4) | H20: =IF(E20="","",F20*G20) | I20: =IF(E20="","",IFERROR(VLOOKUP(E20,'Master Inventory'!$A:$N,10,FALSE),0)) | J20: =IF(E20="","",SUMIFS(Reservations!$G:$G,Reservations!$D:$D,A20,Reservations!$E:$E,E20,Reservations!$H:$H,"Active")) | K20: =IF(E20="","",MAX(0,H20-I20-J20)) | L20: =IF(E20="","",IF(K20>0,"SHORTAGE",IF(J20>=H20,"RESERVED","READY TO RESERVE")))
A21: =IF('Job Cards'!$A$4="","",'Job Cards'!$A$4) | B21: =IF(A21="","",'Job Cards'!$B$4) | C21: =IF(A21="","",'Job Cards'!$D$4) | D21: =IF(A21="","",'BOM Mapping'!$A$21) | E21: =IF(C21="Longitude",'BOM Mapping'!$C$21,IF(C21="Latitude",'BOM Mapping'!$D$21,IF(C21="Altitude",'BOM Mapping'!$E$21,""))) | F21: =IF(C21="Longitude",'BOM Mapping'!$J$21,IF(C21="Latitude",'BOM Mapping'!$K$21,IF(C21="Altitude",'BOM Mapping'!$L$21,0))) | G21: =IF(A21="","",'Job Cards'!$E$4) | H21: =IF(E21="","",F21*G21) | I21: =IF(E21="","",IFERROR(VLOOKUP(E21,'Master Inventory'!$A:$N,10,FALSE),0)) | J21: =IF(E21="","",SUMIFS(Reservations!$G:$G,Reservations!$D:$D,A21,Reservations!$E:$E,E21,Reservations!$H:$H,"Active")) | K21: =IF(E21="","",MAX(0,H21-I21-J21)) | L21: =IF(E21="","",IF(K21>0,"SHORTAGE",IF(J21>=H21,"RESERVED","READY TO RESERVE")))
